Workbook

Sheet Lisez-moi
A1: Cartographie du sport associatif et du sport féminin en Val d'Oise
A2: Base consolidée construite à partir des fichiers de la Direction des Sports. Version du 21/09/2026.
A4: Onglet | B4: Contenu
A5: Communes | B5: 183 communes du Val d'Oise. Volumes 2025 (associations civiles, adhérent·es F/H, bénévoles F, salariées F), scolaires, subventions, équipements, manifestations, sections sportives, séries 2019-2025. Les ratios sont des formules.
A6: Cantons | B6: 18 cantons regroupés (Argenteuil 1-2-3 et Cergy 1-2 fusionnés, car ils découpent une même commune). Sommes par SUMIFS sur l'onglet Communes.
A7: EPCI | B7: 12 intercommunalités (rattachement au code officiel géographique). Sommes par SUMIFS sur l'onglet Communes.
A8: Associations_2025 | B8: Liste des 553 associations civiles 2025 avec commune, canton, EPCI, adhérent·es F/H, part F et profil de mixité.
A9: Evolution | B9: Totaux départementaux 2019-2025 : nombre d'associations civiles et volume de licencié·es / adhérent·es.
A10: Comites | B10: Comités départementaux : licencié·es et féminines par saison (2022/23 à 2025/26), actions « pratique féminine ».
A11: Gouvernance | B11: Enquête 2021 (pratiquantes, bénévoles, éducatrices, arbitres, présidentes) et répartition F/H des élu·es et directeur·rices des sports.
A12: Sections_sportives | B12: Sections sportives scolaires 2026-2027 du Val d'Oise (extrait du PDF académique).
A13: Installations | B13: Liste des 1 543 lieux de pratique, avec code commune.
A15: Définitions et limites
A16: Champ | B16: Les fichiers « associations civiles (01) et scolaires (02) » portent sur les associations aidées par le Département. Ce n'est pas un recensement de tous les clubs. Une commune « sans association » peut avoir des clubs non aidés.
A17: Part F 2025 | B17: Adhérentes féminines / (adhérentes + adhérents masculins), déclaré par les associations en 2025. Même calcul pour 2024.
A18: Libellés trompeurs | B18: Dans les fichiers 2023-2025, plusieurs colonnes libellées « F » contiennent en fait des totaux F+H. Ex. 2025 : « Licencié F » = adhérents F+H dans 99 % des cas ; « Moins 18 F » + « Plus 18 F » = total F+H dans 95 % des cas. Ces colonnes ne sont pas utilisées comme données féminines. Idem pour « licencié Feminine » en 2023, traité comme un total.
A19: Rupture de série | B19: Jusqu'en 2023 le volume est un nombre de licencié·es ; en 2024-2025 c'est un nombre d'adhérent·es (F+H). La hausse 2023-2024 reflète en partie ce changement de mesure.
A20: Scolaires 2025 | B20: La colonne s'intitule « Nombre Licencié F ». Le libellé n'est pas vérifiable ; le chiffre est probablement un total. À confirmer avec la Direction des Sports.
A21: Cantons | B21: Canton connu pour 108 communes (liste des subventions 2025). Pour les 75 autres, canton imputé à partir de la commune voisine la plus proche (colonne « canton_source »). À vérifier avec la liste officielle INSEE.
A22: Population | B22: Population municipale du code officiel géographique (paquet etalab « découpage administratif », mars 2026).
A23: Taux pour 1 000 hab. | B23: Les adhérent·es sont comptés dans la commune du siège de l'association, pas dans leur commune de résidence. Les taux par habitant indiquent une offre locale, pas une pratique des habitantes.
A24: Effectifs faibles | B24: Une part F calculée sur moins de 100 adhérent·es est fragile (colonne « fiabilite_part_F »).
A25: Installations | B25: Chaque ligne est un lieu. La colonne source « installation Nombre » n'est pas documentée ; elle est reprise sans être interprétée.
A26: Hors département | B26: 2 associations civiles 2025 et 2 associations subventionnées ont leur siège hors Val d'Oise (Conflans-Sainte-Honorine, Sacy-le-Grand, Belle-Église). Elles sont exclues des agrégats communaux.
A28: Ajouts 22/09/2026
A29: Disciplines_5_saisons | B29: Part des femmes par discipline : 2020/21 (enquête) puis 2022/23 à 2025/26 (comités). Total calculé sur les disciplines présentes les 5 saisons.
A30: Territoires_2019_2025 | B30: Nombre d'associations aidées, volume de licencié·es / adhérent·es et panel d'associations présentes les 7 années, par canton et intercommunalité.

Sheet Communes
A1: Indicateurs par commune
A2: Colonnes grises = données sources agrégées ; colonnes de droite = ratios calculés par formule. Voir Lisez-moi pour les définitions.
A4: Code INSEE | B4: Commune | C4: Canton | D4: Source du canton | E4: EPCI | F4: Grille de densité INSEE | G4: Population | H4: Asso. civiles 2025 | I4: Adhérentes F 2025 | J4: Adhérents H 2025 | K4: Bénévoles F 2025 | L4: Salariées F 2025 | M4: Asso. <20 % F (2025) | N4: Asso. ≥60 % F (2025) | O4: Asso. civiles 2024 | P4: Adhérentes F 2024 | Q4: Adhérents H 2024 | R4: Asso. scolaires 2025 | S4: Licencié·es scolaires 2025 (libellé F) | T4: Sections scolaires 2025 | U4: Asso. civiles subventionnées 2025 | V4: Asso. scolaires subventionnées 2025 | W4: Lieux de pratique | X4: dont établissements scolaires | Y4: dont piscines | Z4: Manifestations 2023 | AA4: Manifestations 2024 | AB4: Manifestations 2025 | AC4: Sections sportives scolaires 2026-27 | AD4: dont sections féminines | AE4: Asso. civiles 2019 | AF4: Asso. civiles 2020 | AG4: Asso. civiles 2021 | AH4: Asso. civiles 2022 | AI4: Asso. civiles 2023 | AJ4: Licencié·es / adhérent·es 2019 | AK4: Licencié·es / adhérent·es 2020 | AL4: Licencié·es / adhérent·es 2021 | AM4: Licencié·es / adhérent·es 2022 | AN4: Licencié·es / adhérent·es 2023 | AO4: Licencié·es / adhérent·es 2024 | AP4: Licencié·es / adhérent·es 2025 | AQ4: Adhérent·es total 2025 | AR4: Part F 2025 | AS4: Part F 2024 | AT4: Évolution part F (points) | AU4: Adhérentes F pour 1 000 hab. | AV4: Asso. civiles pour 10 000 hab. | AW4: Lieux pour 10 000 hab. | AX4: Bénévoles F pour 100 adhérentes | AY4: Fiabilité part F
A5: 95002 | B5: Ableiges | C5: Pontoise | D5: liste subventions 2025 | E5: CC Vexin Centre | F5: Rural à habitat dispersé | G5: 1108 | H5: 1 | I5: 38 | J5: 185 | K5: 7 | L5: 0 | M5: 1 | N5: 0 | O5: 1 | P5: 43 | Q5: 141 | R5: 0 | S5: 0 | T5: 0 | U5: 1 | V5: 0 | W5: 5 | X5: 2 | Y5: 0 | Z5: 0 | AA5: 0 | AB5: 0 | AC5: 0 | AD5: 0 | AE5: 2 | AF5: 2 | AG5: 2 | AH5: 2 | AI5: 2 | AJ5: 453 | AK5: 434 | AL5: 316 | AM5: 156 | AN5: 198 | AO5: 184 | AP5: 223 | AQ5: =I5+J5 -> 223 | AR5: =IF(AQ5>0,I5/AQ5,"") -> 0.17040359 | AS5: =IF((P5+Q5)>0,P5/(P5+Q5),"") -> 0.23369565 | AT5: =IF(AND(ISNUMBER(AR5),ISNUMBER(AS5)),(AR5-AS5)*100,"") -> -6.3292065 | AU5: =IF(G5>0,I5/G5*1000,"") -> 34.296029 | AV5: =IF(G5>0,H5/G5*10000,"") -> 9.0252708 | AW5: =IF(G5>0,W5/G5*10000,"") -> 45.126354 | AX5: =IF(I5>0,K5/I5*100,"") -> 18.421053 | AY5: =IF(AQ5>=100,"ok",IF(AQ5>0,"effectif faible (<100)","aucune association")) -> ok
A6: 95008 | B6: Aincourt | C6: Vauréal | D6: imputé (commune voisine la plus proche) | E6: CC du Vexin-Val de Seine | F6: Rural à habitat dispersé | G6: 854 | H6: 0 | I6: 0 | J6: 0 | K6: 0 | L6: 0 | M6: 0 | N6: 0 | O6: 0 | P6: 0 | Q6: 0 | R6: 0 | S6: 0 | T6: 0 | U6: 0 | V6: 0 | W6: 3 | X6: 1 | Y6: 0 | Z6: 0 | AA6: 0 | AB6: 0 | AC6: 0 | AD6: 0 | AE6: 0 | AF6: 0 | AG6: 0 | AH6: 0 | AI6: 0 | AJ6: 0 | AK6: 0 | AL6: 0 | AM6: 0 | AN6: 0 | AO6: 0 | AP6: 0 | AQ6: =I6+J6 -> 0 | AR6: =IF(AQ6>0,I6/AQ6,"") | AS6: =IF((P6+Q6)>0,P6/(P6+Q6),"") | AT6: =IF(AND(ISNUMBER(AR6),ISNUMBER(AS6)),(AR6-AS6)*100,"") | AU6: =IF(G6>0,I6/G6*1000,"") -> 0 | AV6: =IF(G6>0,H6/G6*10000,"") -> 0 | AW6: =IF(G6>0,W6/G6*10000,"") -> 35.128806 | AX6: =IF(I6>0,K6/I6*100,"") | AY6: =IF(AQ6>=100,"ok",IF(AQ6>0,"effectif faible (<100)","aucune association")) -> aucune association
A7: 95011 | B7: Ambleville | C7: Vauréal | D7: imputé (commune voisine la plus proche) | E7: CC du Vexin-Val de Seine | G7: 388 | H7: 0 | I7: 0 | J7: 0 | K7: 0 | L7: 0 | M7: 0 | N7: 0 | O7: 0 | P7: 0 | Q7: 0 | R7: 0 | S7: 0 | T7: 0 | U7: 0 | V7: 0 | W7: 0 | X7: 0 | Y7: 0 | Z7: 0 | AA7: 0 | AB7: 0 | AC7: 0 | AD7: 0 | AE7: 0 | AF7: 0 | AG7: 0 | AH7: 0 | AI7: 0 | AJ7: 0 | AK7: 0 | AL7: 0 | AM7: 0 | AN7: 0 | AO7: 0 | AP7: 0 | AQ7: =I7+J7 -> 0 | AR7: =IF(AQ7>0,I7/AQ7,"") | AS7: =IF((P7+Q7)>0,P7/(P7+Q7),"") | AT7: =IF(AND(ISNUMBER(AR7),ISNUMBER(AS7)),(AR7-AS7)*100,"") | AU7: =IF(G7>0,I7/G7*1000,"") -> 0 | AV7: =IF(G7>0,H7/G7*10000,"") -> 0 | AW7: =IF(G7>0,W7/G7*10000,"") -> 0 | AX7: =IF(I7>0,K7/I7*100,"") | AY7: =IF(AQ7>=100,"ok",IF(AQ7>0,"effectif faible (<100)","aucune association")) -> aucune association
A8: 95012 | B8: Amenucourt | C8: Vauréal | D8: imputé (commune voisine la plus proche) | E8: CC du Vexin-Val de Seine | F8: Rural à habitat dispersé | G8: 212 | H8: 0 | I8: 0 | J8: 0 | K8: 0 | L8: 0 | M8: 0 | N8: 0 | O8: 0 | P8: 0 | Q8: 0 | R8: 0 | S8: 0 | T8: 0 | U8: 0 | V8: 0 | W8: 1 | X8: 0 | Y8: 0 | Z8: 0 | AA8: 0 | AB8: 0 | AC8: 0 | AD8: 0 | AE8: 0 | AF8: 0 | AG8: 0 | AH8: 0 | AI8: 0 | AJ8: 0 | AK8: 0 | AL8: 0 | AM8: 0 | AN8: 0 | AO8: 0 | AP8: 0 | AQ8: =I8+J8 -> 0 | AR8: =IF(AQ8>0,I8/AQ8,"") | AS8: =IF((P8+Q8)>0,P8/(P8+Q8),"") | AT8: =IF(AND(ISNUMBER(AR8),ISNUMBER(AS8)),(AR8-AS8)*100,"") | AU8: =IF(G8>0,I8/G8*1000,"") -> 0 | AV8: =IF(G8>0,H8/G8*10000,"") -> 0 | AW8: =IF(G8>0,W8/G8*10000,"") -> 47.169811 | AX8: =IF(I8>0,K8/I8*100,"") | AY8: =IF(AQ8>=100,"ok",IF(AQ8>0,"effectif faible (<100)","aucune association")) -> aucune association
A9: 95014 | B9: Andilly | C9: Montmorency | D9: imputé (commune voisine la plus proche) | E9: CA Plaine Vallée | F9: Grands centres urbains | G9: 2742 | H9: 0 | I9: 0 | J9: 0 | K9: 0 | L9: 0 | M9: 0 | N9: 0 | O9: 0 | P9: 0 | Q9: 0 | R9: 0 | S9: 0 | T9: 0 | U9: 0 | V9: 0 | W9: 6 | X9: 1 | Y9: 0 | Z9: 0 | AA9: 0 | AB9: 0 | AC9: 0 | AD9: 0 | AE9: 0 | AF9: 0 | AG9: 0 | AH9: 0 | AI9: 0 | AJ9: 0 | AK9: 0 | AL9: 0 | AM9: 0 | AN9: 0 | AO9: 0 | AP9: 0 | AQ9: =I9+J9 -> 0 | AR9: =IF(AQ9>0,I9/AQ9,"") | AS9: =IF((P9+Q9)>0,P9/(P9+Q9),"") | AT9: =IF(AND(ISNUMBER(AR9),ISNUMBER(AS9)),(AR9-AS9)*100,"") | AU9: =IF(G9>0,I9/G9*1000,"") -> 0 | AV9: =IF(G9>0,H9/G9*10000,"") -> 0 | AW9: =IF(G9>0,W9/G9*10000,"") -> 21.881838 | AX9: =IF(I9>0,K9/I9*100,"") | AY9: =IF(AQ9>=100,"ok",IF(AQ9>0,"effectif faible (<100)","aucune association")) -> aucune association
A10: 95018 | B10: Argenteuil | C10: Argenteuil (1-2-3) | D10: liste subventions 2025 | E10: Métropole du Grand Paris | F10: Grands centres urbains | G10: 106130 | H10: 24 | I10: 3364 | J10: 5334 | K10: 679 | L10: 68 | M10: 6 | N10: 3 | O10: 22 | P10: 3398 | Q10: 3688 | R10: 6 | S10: 683 | T10: 26 | U10: 24 | V10: 6 | W10: 68 | X10: 14 | Y10: 1 | Z10: 2 | AA10: 2 | AB10: 0 | AC10: 4 | AD10: 0 | AE10: 21 | AF10: 26 | AG10: 25 | AH10: 25 | AI10: 23 | AJ10: 7854 | AK10: 8955 | AL10: 8268 | AM10: 6751 | AN10: 6733 | AO10: 7086 | AP10: 8698 | AQ10: =I10+J10 -> 8698 | AR10: =IF(AQ10>0,I10/AQ10,"") -> 0.38675558 | AS10: =IF((P10+Q10)>0,P10/(P10+Q10),"") -> 0.47953712 | AT10: =IF(AND(ISNUMBER(AR10),ISNUMBER(AS10)),(AR10-AS10)*100,"") -> -9.2781539 | AU10: =IF(G10>0,I10/G10*1000,"") -> 31.696975 | AV10: =IF(G10>0,H10/G10*10000,"") -> 2.2613776 | AW10: =IF(G10>0,W10/G10*10000,"") -> 6.4072364 | AX10: =IF(I10>0,K10/I10*100,"") -> 20.184304 | AY10: =IF(AQ10>=100,"ok",IF(AQ10>0,"effectif faible (<100)","aucune association")) -> ok
A11: 95019 | B11: Arnouville | C11: Garges-lès-Gonesse | D11: liste subventions 2025 | E11: CA Roissy Pays de France | F11: Grands centres urbains | G11: 15023 | H11: 3 | I11: 137 | J11: 211 | K11: 77 | L11: 3 | M11: 0 | N11: 1 | O11: 3 | P11: 166 | Q11: 116 | R11: 1 | S11: 110 | T11: 3 | U11: 3 | V11: 1 | W11: 17 | X11: 10 | Y11: 0 | Z11: 0 | AA11: 0 | AB11: 0 | AC11: 0 | AD11: 0 | AE11: 5 | AF11: 5 | AG11: 4 | AH11: 3 | AI11: 3 | AJ11: 331 | AK11: 403 | AL11: 407 | AM11: 194 | AN11: 208 | AO11: 282 | AP11: 348 | AQ11: =I11+J11 -> 348 | AR11: =IF(AQ11>0,I11/AQ11,"") -> 0.39367816 | AS11: =IF((P11+Q11)>0,P11/(P11+Q11),"") -> 0.58865248 | AT11: =IF(AND(ISNUMBER(AR11),ISNUMBER(AS11)),(AR11-AS11)*100,"") -> -19.497432 | AU11: =IF(G11>0,I11/G11*1000,"") -> 9.1193503 | AV11: =IF(G11>0,H11/G11*10000,"") -> 1.996938 | AW11: =IF(G11>0,W11/G11*10000,"") -> 11.315982 | AX11: =IF(I11>0,K11/I11*100,"") -> 56.20438 | AY11: =IF(AQ11>=100,"ok",IF(AQ11>0,"effectif faible (<100)","aucune association")) -> ok
A12: 95023 | B12: Arronville | C12: Pontoise | D12: liste subventions 2025 | E12: CC Sausseron Impressionnistes | F12: Rural à habitat dispersé | G12: 618 | H12: 1 | I12: 5 | J12: 9 | K12: 0 | L12: 0 | M12: 0 | N12: 0 | O12: 1 | P12: 6 | Q12: 11 | R12: 0 | S12: 0 | T12: 0 | U12: 1 | V12: 0 | W12: 1 | X12: 1 | Y12: 0 | Z12: 0 | AA12: 0 | AB12: 0 | AC12: 0 | AD12: 0 | AE12: 1 | AF12: 1 | AG12: 1 | AH12: 1 | AI12: 1 | AJ12: 11 | AK12: 14 | AL12: 15 | AM12: 13 | AN12: 15 | AO12: 17 | AP12: 14 | AQ12: =I12+J12 -> 14 | AR12: =IF(AQ12>0,I12/AQ12,"") -> 0.35714286 | AS12: =IF((P12+Q12)>0,P12/(P12+Q12),"") -> 0.35294118 | AT12: =IF(AND(ISNUMBER(AR12),ISNUMBER(AS12)),(AR12-AS12)*100,"") -> 0.42016807 | AU12: =IF(G12>0,I12/G12*1000,"") -> 8.0906149 | AV12: =IF(G12>0,H12/G12*10000,"") -> 16.18123 | AW12: =IF(G12>0,W12/G12*10000,"") -> 16.18123 | AX12: =IF(I12>0,K12/I12*100,"") -> 0 | AY12: =IF(AQ12>=100,"ok",IF(AQ12>0,"effectif faible (<100)","aucune association")) -> effectif faible (<100)
A13: 95024 | B13: Arthies | C13: Vauréal | D13: liste subventions 2025 | E13: CC du Vexin-Val de Seine | F13: Rural à habitat dispersé | G13: 265 | H13: 1 | I13: 30 | J13: 23 | K13: 8 | L13: 1 | M13: 0 | N13: 0 | O13: 1 | P13: 20 | Q13: 22 | R13: 0 | S13: 0 | T13: 0 | U13: 1 | V13: 0 | W13: 4 | X13: 0 | Y13: 0 | Z13: 0 | AA13: 0 | AB13: 0 | AC13: 0 | AD13: 0 | AE13: 1 | AF13: 1 | AG13: 1 | AH13: 1 | AI13: 1 | AJ13: 72 | AK13: 60 | AL13: 70 | AM13: 66 | AN13: 61 | AO13: 42 | AP13: 53 | AQ13: =I13+J13 -> 53 | AR13: =IF(AQ13>0,I13/AQ13,"") -> 0.56603774 | AS13: =IF((P13+Q13)>0,P13/(P13+Q13),"") -> 0.47619048 | AT13: =IF(AND(ISNUMBER(AR13),ISNUMBER(AS13)),(AR13-AS13)*100,"") -> 8.984726 | AU13: =IF(G13>0,I13/G13*1000,"") -> 113.20755 | AV13: =IF(G13>0,H13/G13*10000,"") -> 37.735849 | AW13: =IF(G13>0,W13/G13*10000,"") -> 150.9434 | AX13: =IF(I13>0,K13/I13*100,"") -> 26.666667 | AY13: =IF(AQ13>=100,"ok",IF(AQ13>0,"effectif faible (<100)","aucune association")) -> effectif faible (<100)
A14: 95026 | B14: Asnières-sur-Oise | C14: Fosses | D14: imputé (commune voisine la plus proche) | E14: CC Carnelle Pays-de-France | F14: Ceintures urbaines | G14: 3127 | H14: 0 | I14: 0 | J14: 0 | K14: 0 | L14: 0 | M14: 0 | N14: 0 | O14: 1 | P14: 184 | Q14: 15 | R14: 0 | S14: 0 | T14: 0 | U14: 0 | V14: 0 | W14: 2 | X14: 0 | Y14: 0 | Z14: 0 | AA14: 0 | AB14: 0 | AC14: 0 | AD14: 0 | AE14: 1 | AF14: 1 | AG14: 1 | AH14: 1 | AI14: 1 | AJ14: 0 | AK14: 0 | AL14: 0 | AM14: 0 | AN14: 0 | AO14: 199 | AP14: 0 | AQ14: =I14+J14 -> 0 | AR14: =IF(AQ14>0,I14/AQ14,"") | AS14: =IF((P14+Q14)>0,P14/(P14+Q14),"") -> 0.92462312 | AT14: =IF(AND(ISNUMBER(AR14),ISNUMBER(AS14)),(AR14-AS14)*100,"") | AU14: =IF(G14>0,I14/G14*1000,"") -> 0 | AV14: =IF(G14>0,H14/G14*10000,"") -> 0 | AW14: =IF(G14>0,W14/G14*10000,"") -> 6.3959066 | AX14: =IF(I14>0,K14/I14*100,"") | AY14: =IF(AQ14>=100,"ok",IF(AQ14>0,"effectif faible (<100)","aucune association")) -> aucune association
A15: 95028 | B15: Attainville | C15: Fosses | D15: liste subventions 2025 | E15: CA Plaine Vallée | F15: Ceintures urbaines | G15: 1904 | H15: 3 | I15: 284 | J15: 391 | K15: 43 | L15: 7 | M15: 1 | N15: 1 | O15: 3 | P15: 301 | Q15: 329 | R15: 0 | S15: 0 | T15: 0 | U15: 3 | V15: 0 | W15: 4 | X15: 0 | Y15: 0 | Z15: 0 | AA15: 0 | AB15: 0 | AC15: 0 | AD15: 0 | AE15: 1 | AF15: 2 | AG15: 3 | AH15: 2 | AI15: 3 | AJ15: 140 | AK15: 245 | AL15: 288 | AM15: 137 | AN15: 360 | AO15: 630 | AP15: 675 | AQ15: =I15+J15 -> 675 | AR15: =IF(AQ15>0,I15/AQ15,"") -> 0.42074074 | AS15: =IF((P15+Q15)>0,P15/(P15+Q15),"") -> 0.47777778 | AT15: =IF(AND(ISNUMBER(AR15),ISNUMBER(AS15)),(AR15-AS15)*100,"") -> -5.7037037 | AU15: =IF(G15>0,I15/G15*1000,"") -> 149.15966 | AV15: =IF(G15>0,H15/G15*10000,"") -> 15.756303 | AW15: =IF(G15>0,W15/G15*10000,"") -> 21.008403 | AX15: =IF(I15>0,K15/I15*100,"") -> 15.140845 | AY15: =IF(AQ15>=100,"ok",IF(AQ15>0,"effectif faible (<100)","aucune association")) -> ok
A16: 95039 | B16: Auvers-sur-Oise | C16: Saint-Ouen-l'Aumône | D16: liste subventions 2025 | E16: CC Sausseron Impressionnistes | F16: Grands centres urbains | G16: 6863 | H16: 6 | I16: 462 | J16: 817 | K16: 112 | L16: 5 | M16: 1 | N16: 3 | O16: 7 | P16: 468 | Q16: 837 | R16: 2 | S16: 443 | T16: 7 | U16: 7 | V16: 2 | W16: 12 | X16: 2 | Y16: 0 | Z16: 0 | AA16: 0 | AB16: 0 | AC16: 1 | AD16: 0 | AE16: 6 | AF16: 7 | AG16: 8 | AH16: 7 | AI16: 7 | AJ16: 1849 | AK16: 1648 | AL16: 1245 | AM16: 1268 | AN16: 1116 | AO16: 1305 | AP16: 1279 | AQ16: =I16+J16 -> 1279 | AR16: =IF(AQ16>0,I16/AQ16,"") -> 0.3612197 | AS16: =IF((P16+Q16)>0,P16/(P16+Q16),"") -> 0.35862069 | AT16: =IF(AND(ISNUMBER(AR16),ISNUMBER(AS16)),(AR16-AS16)*100,"") -> 0.25990132 | AU16: =IF(G16>0,I16/G16*1000,"") -> 67.3175 | AV16: =IF(G16>0,H16/G16*10000,"") -> 8.7425324 | AW16: =IF(G16>0,W16/G16*10000,"") -> 17.485065 | AX16: =IF(I16>0,K16/I16*100,"") -> 24.242424 | AY16: =IF(AQ16>=100,"ok",IF(AQ16>0,"effectif faible (<100)","aucune association")) -> ok
A17: 95040 | B17: Avernes | C17: Vauréal | D17: liste subventions 2025 | E17: CC Vexin Centre | F17: Bourgs ruraux | G17: 871 | H17: 1 | I17: 2 | J17: 45 | K17: 6 | L17: 0 | M17: 1 | N17: 0 | O17: 1 | P17: 2 | Q17: 46 | R17: 0 | S17: 0 | T17: 0 | U17: 1 | V17: 0 | W17: 7 | X17: 1 | Y17: 0 | Z17: 0 | AA17: 0 | AB17: 0 | AC17: 0 | AD17: 0 | AE17: 1 | AF17: 0 | AG17: 0 | AH17: 1 | AI17: 1 | AJ17: 238 | AK17: 0 | AL17: 0 | AM17: 50 | AN17: 53 | AO17: 48 | AP17: 47 | AQ17: =I17+J17 -> 47 | AR17: =IF(AQ17>0,I17/AQ17,"") -> 0.042553191 | AS17: =IF((P17+Q17)>0,P17/(P17+Q17),"") -> 0.041666667 | AT17: =IF(AND(ISNUMBER(AR17),ISNUMBER(AS17)),(AR17-AS17)*100,"") -> 0.088652482 | AU17: =IF(G17>0,I17/G17*1000,"") -> 2.2962113 | AV17: =IF(G17>0,H17/G17*10000,"") -> 11.481056 | AW17: =IF(G17>0,W17/G17*10000,"") -> 80.367394 | AX17: =IF(I17>0,K17/I17*100,"") -> 300 | AY17: =IF(AQ17>=100,"ok",IF(AQ17>0,"effectif faible (<100)","aucune association")) -> effectif faible (<100)
A18: 95042 | B18: Baillet-en-France | C18: Domont | D18: liste subventions 2025 | E18: CC Carnelle Pays-de-France | F18: Ceintures urbaines | G18: 2021 | H18: 3 | I18: 134 | J18: 182 | K18: 15 | L18: 1 | M18: 0 | N18: 1 | O18: 3 | P18: 183 | Q18: 145 | R18: 0 | S18: 0 | T18: 0 | U18: 2 | V18: 0 | W18: 5 | X18: 0 | Y18: 0 | Z18: 1 | AA18: 0 | AB18: 0 | AC18: 0 | AD18: 0 | AE18: 2 | AF18: 1 | AG18: 1 | AH18: 2 | AI18: 3 | AJ18: 316 | AK18: 327 | AL18: 319 | AM18: 346 | AN18: 319 | AO18: 328 | AP18: 316 | AQ18: =I18+J18 -> 316 | AR18: =IF(AQ18>0,I18/AQ18,"") -> 0.42405063 | AS18: =IF((P18+Q18)>0,P18/(P18+Q18),"") -> 0.55792683 | AT18: =IF(AND(ISNUMBER(AR18),ISNUMBER(AS18)),(AR18-AS18)*100,"") -> -13.38762 | AU18: =IF(G18>0,I18/G18*1000,"") -> 66.30381 | AV18: =IF(G18>0,H18/G18*10000,"") -> 14.844137 | AW18: =IF(G18>0,W18/G18*10000,"") -> 24.740228 | AX18: =IF(I18>0,K18/I18*100,"") -> 11.19403 | AY18: =IF(AQ18>=100,"ok",IF(AQ18>0,"effectif faible (<100)","aucune association")) -> ok
A19: 95046 | B19: Banthelu | C19: Vauréal | D19: imputé (commune voisine la plus proche) | E19: CC du Vexin-Val de Seine | F19: Rural à habitat dispersé | G19: 146 | H19: 0 | I19: 0 | J19: 0 | K19: 0 | L19: 0 | M19: 0 | N19: 0 | O19: 0 | P19: 0 | Q19: 0 | R19: 0 | S19: 0 | T19: 0 | U19: 0 | V19: 0 | W19: 1 | X19: 0 | Y19: 0 | Z19: 0 | AA19: 0 | AB19: 0 | AC19: 0 | AD19: 0 | AE19: 0 | AF19: 0 | AG19: 0 | AH19: 0 | AI19: 0 | AJ19: 0 | AK19: 0 | AL19: 0 | AM19: 0 | AN19: 0 | AO19: 0 | AP19: 0 | AQ19: =I19+J19 -> 0 | AR19: =IF(AQ19>0,I19/AQ19,"") | AS19: =IF((P19+Q19)>0,P19/(P19+Q19),"") | AT19: =IF(AND(ISNUMBER(AR19),ISNUMBER(AS19)),(AR19-AS19)*100,"") | AU19: =IF(G19>0,I19/G19*1000,"") -> 0 | AV19: =IF(G19>0,H19/G19*10000,"") -> 0 | AW19: =IF(G19>0,W19/G19*10000,"") -> 68.493151 | AX19: =IF(I19>0,K19/I19*100,"") | AY19: =IF(AQ19>=100,"ok",IF(AQ19>0,"effectif faible (<100)","aucune association")) -> aucune association
... A41: 95134 | B41: Champagne-sur-Oise | C41: L'Isle-Adam | D41: liste subventions 2025 | E41: CC du Haut Val d'Oise | F41: Ceintures urbaines | G41: 5036 | H41: 3 | I41: 55 | J41: 183 | K41: 16 | L41: 3 | M41: 1 | N41: 0 | O41: 1 | P41: 52 | Q41: 133 | R41: 0 | S41: 0 | T41: 0 | U41: 3 | V41: 0 | W41: 9 | X41: 3 | Y41: 0 | Z41: 0 | AA41: 0 | AB41: 0 | AC41: 0 | AD41: 0 | AE41: 2 | AF41: 2 | AG41: 2 | AH41: 2 | AI41: 2 | AJ41: 268 | AK41: 205 | AL41: 162 | AM41: 171 | AN41: 151 | AO41: 185 | AP41: 238 | AQ41: =I41+J41 -> 238 | AR41: =IF(AQ41>0,I41/AQ41,"") -> 0.23109244 | AS41: =IF((P41+Q41)>0,P41/(P41+Q41),"") -> 0.28108108 | AT41: =IF(AND(ISNUMBER(AR41),ISNUMBER(AS41)),(AR41-AS41)*100,"") -> -4.9988644 | AU41: =IF(G41>0,I41/G41*1000,"") -> 10.921366 | AV41: =IF(G41>0,H41/G41*10000,"") -> 5.9571088 | AW41: =IF(G41>0,W41/G41*10000,"") -> 17.871326 | AX41: =IF(I41>0,K41/I41*100,"") -> 29.090909 | AY41: =IF(AQ41>=100,"ok",IF(AQ41>0,"effectif faible (<100)","aucune association")) -> ok
A42: 95141 | B42: Charmont | C42: Vauréal | D42: imputé (commune voisine la plus proche) | E42: CC du Vexin-Val de Seine | G42: 32 | H42: 0 | I42: 0 | J42: 0 | K42: 0 | L42: 0 | M42: 0 | N42: 0 | O42: 0 | P42: 0 | Q42: 0 | R42: 0 | S42: 0 | T42: 0 | U42: 0 | V42: 0 | W42: 0 | X42: 0 | Y42: 0 | Z42: 0 | AA42: 0 | AB42: 0 | AC42: 0 | AD42: 0 | AE42: 0 | AF42: 0 | AG42: 0 | AH42: 0 | AI42: 0 | AJ42: 0 | AK42: 0 | AL42: 0 | AM42: 0 | AN42: 0 | AO42: 0 | AP42: 0 | AQ42: =I42+J42 -> 0 | AR42: =IF(AQ42>0,I42/AQ42,"") | AS42: =IF((P42+Q42)>0,P42/(P42+Q42),"") | AT42: =IF(AND(ISNUMBER(AR42),ISNUMBER(AS42)),(AR42-AS42)*100,"") | AU42: =IF(G42>0,I42/G42*1000,"") -> 0 | AV42: =IF(G42>0,H42/G42*10000,"") -> 0 | AW42: =IF(G42>0,W42/G42*10000,"") -> 0 | AX42: =IF(I42>0,K42/I42*100,"") | AY42: =IF(AQ42>=100,"ok",IF(AQ42>0,"effectif faible (<100)","aucune association")) -> aucune association
A43: 95142 | B43: Chars | C43: Pontoise | D43: liste subventions 2025 | E43: CC Vexin Centre | F43: Bourgs ruraux | G43: 2006 | H43: 2 | I43: 30 | J43: 90 | K43: 45 | L43: 0 | M43: 1 | N43: 0 | O43: 2 | P43: 34 | Q43: 87 | R43: 1 | S43: 159 | T43: 20 | U43: 2 | V43: 1 | W43: 5 | X43: 1 | Y43: 0 | Z43: 0 | AA43: 0 | AB43: 0 | AC43: 0 | AD43: 0 | AE43: 1 | AF43: 1 | AG43: 1 | AH43: 1 | AI43: 2 | AJ43: 17 | AK43: 22 | AL43: 18 | AM43: 19 | AN43: 75 | AO43: 121 | AP43: 120 | AQ43: =I43+J43 -> 120 | AR43: =IF(AQ43>0,I43/AQ43,"") -> 0.25 | AS43: =IF((P43+Q43)>0,P43/(P43+Q43),"") -> 0.28099174 | AT43: =IF(AND(ISNUMBER(AR43),ISNUMBER(AS43)),(AR43-AS43)*100,"") -> -3.0991736 | AU43: =IF(G43>0,I43/G43*1000,"") -> 14.955135 | AV43: =IF(G43>0,H43/G43*10000,"") -> 9.9700897 | AW43: =IF(G43>0,W43/G43*10000,"") -> 24.925224 | AX43: =IF(I43>0,K43/I43*100,"") -> 150 | AY43: =IF(AQ43>=100,"ok",IF(AQ43>0,"effectif faible (<100)","aucune association")) -> ok
A44: 95149 | B44: Chaumontel | C44: Fosses | D44: liste subventions 2025 | E44: CC Carnelle Pays-de-France | F44: Petites villes | G44: 3332 | H44: 3 | I44: 347 | J44: 106 | K44: 8 | L44: 4 | M44: 2 | N44: 1 | O44: 4 | P44: 442 | Q44: 117 | R44: 0 | S44: 0 | T44: 0 | U44: 3 | V44: 0 | W44: 5 | X44: 1 | Y44: 0 | Z44: 0 | AA44: 0 | AB44: 0 | AC44: 0 | AD44: 0 | AE44: 4 | AF44: 3 | AG44: 4 | AH44: 4 | AI44: 3 | AJ44: 543 | AK44: 497 | AL44: 549 | AM44: 525 | AN44: 469 | AO44: 559 | AP44: 453 | AQ44: =I44+J44 -> 453 | AR44: =IF(AQ44>0,I44/AQ44,"") -> 0.76600442 | AS44: =IF((P44+Q44)>0,P44/(P44+Q44),"") -> 0.79069767 | AT44: =IF(AND(ISNUMBER(AR44),ISNUMBER(AS44)),(AR44-AS44)*100,"") -> -2.4693259 | AU44: =IF(G44>0,I44/G44*1000,"") -> 104.14166 | AV44: =IF(G44>0,H44/G44*10000,"") -> 9.0036014 | AW44: =IF(G44>0,W44/G44*10000,"") -> 15.006002 | AX44: =IF(I44>0,K44/I44*100,"") -> 2.3054755 | AY44: =IF(AQ44>=100,"ok",IF(AQ44>0,"effectif faible (<100)","aucune association")) -> ok
A45: 95150 | B45: Chaussy | C45: Vauréal | D45: liste subventions 2025 | E45: CC du Vexin-Val de Seine | F45: Rural à habitat dispersé | G45: 631 | H45: 1 | I45: 82 | J45: 223 | K45: 8 | L45: 10 | M45: 0 | N45: 0 | O45: 1 | P45: 92 | Q45: 218 | R45: 1 | S45: 69 | T45: 10 | U45: 1 | V45: 1 | W45: 5 | X45: 0 | Y45: 0 | Z45: 0 | AA45: 0 | AB45: 0 | AC45: 0 | AD45: 0 | AE45: 1 | AF45: 1 | AG45: 1 | AH45: 1 | AI45: 1 | AJ45: 512 | AK45: 350 | AL45: 340 | AM45: 340 | AN45: 297 | AO45: 310 | AP45: 305 | AQ45: =I45+J45 -> 305 | AR45: =IF(AQ45>0,I45/AQ45,"") -> 0.26885246 | AS45: =IF((P45+Q45)>0,P45/(P45+Q45),"") -> 0.29677419 | AT45: =IF(AND(ISNUMBER(AR45),ISNUMBER(AS45)),(AR45-AS45)*100,"") -> -2.7921735 | AU45: =IF(G45>0,I45/G45*1000,"") -> 129.95246 | AV45: =IF(G45>0,H45/G45*10000,"") -> 15.847861 | AW45: =IF(G45>0,W45/G45*10000,"") -> 79.239303 | AX45: =IF(I45>0,K45/I45*100,"") -> 9.7560976 | AY45: =IF(AQ45>=100,"ok",IF(AQ45>0,"effectif faible (<100)","aucune association")) -> ok
A46: 95151 | B46: Chauvry | C46: Domont | D46: imputé (commune voisine la plus proche) | E46: CC de la Vallée de l'Oise et des Trois Forêts | F46: Rural à habitat dispersé | G46: 297 | H46: 0 | I46: 0 | J46: 0 | K46: 0 | L46: 0 | M46: 0 | N46: 0 | O46: 0 | P46: 0 | Q46: 0 | R46: 0 | S46: 0 | T46: 0 | U46: 0 | V46: 0 | W46: 1 | X46: 0 | Y46: 0 | Z46: 0 | AA46: 0 | AB46: 0 | AC46: 0 | AD46: 0 | AE46: 0 | AF46: 0 | AG46: 0 | AH46: 0 | AI46: 0 | AJ46: 0 | AK46: 0 | AL46: 0 | AM46: 0 | AN46: 0 | AO46: 0 | AP46: 0 | AQ46: =I46+J46 -> 0 | AR46: =IF(AQ46>0,I46/AQ46,"") | AS46: =IF((P46+Q46)>0,P46/(P46+Q46),"") | AT46: =IF(AND(ISNUMBER(AR46),ISNUMBER(AS46)),(AR46-AS46)*100,"") | AU46: =IF(G46>0,I46/G46*1000,"") -> 0 | AV46: =IF(G46>0,H46/G46*10000,"") -> 0 | AW46: =IF(G46>0,W46/G46*10000,"") -> 33.670034 | AX46: =IF(I46>0,K46/I46*100,"") | AY46: =IF(AQ46>=100,"ok",IF(AQ46>0,"effectif faible (<100)","aucune association")) -> aucune association
A47: 95154 | B47: Chennevières-lès-Louvres | C47: Goussainville | D47: imputé (commune voisine la plus proche) | E47: CA Roissy Pays de France | F47: Rural à habitat dispersé | G47: 282 | H47: 0 | I47: 0 | J47: 0 | K47: 0 | L47: 0 | M47: 0 | N47: 0 | O47: 0 | P47: 0 | Q47: 0 | R47: 0 | S47: 0 | T47: 0 | U47: 0 | V47: 0 | W47: 2 | X47: 0 | Y47: 0 | Z47: 0 | AA47: 0 | AB47: 0 | AC47: 0 | AD47: 0 | AE47: 0 | AF47: 0 | AG47: 0 | AH47: 0 | AI47: 0 | AJ47: 0 | AK47: 0 | AL47: 0 | AM47: 0 | AN47: 0 | AO47: 0 | AP47: 0 | AQ47: =I47+J47 -> 0 | AR47: =IF(AQ47>0,I47/AQ47,"") | AS47: =IF((P47+Q47)>0,P47/(P47+Q47),"") | AT47: =IF(AND(ISNUMBER(AR47),ISNUMBER(AS47)),(AR47-AS47)*100,"") | AU47: =IF(G47>0,I47/G47*1000,"") -> 0 | AV47: =IF(G47>0,H47/G47*10000,"") -> 0 | AW47: =IF(G47>0,W47/G47*10000,"") -> 70.921986 | AX47: =IF(I47>0,K47/I47*100,"") | AY47: =IF(AQ47>=100,"ok",IF(AQ47>0,"effectif faible (<100)","aucune association")) -> aucune association
A48: 95144 | B48: Châtenay-en-France | C48: Fosses | D48: imputé (commune voisine la plus proche) | E48: CC Carnelle Pays-de-France | G48: 68 | H48: 0 | I48: 0 | J48: 0 | K48: 0 | L48: 0 | M48: 0 | N48: 0 | O48: 0 | P48: 0 | Q48: 0 | R48: 0 | S48: 0 | T48: 0 | U48: 0 | V48: 0 | W48: 0 | X48: 0 | Y48: 0 | Z48: 0 | AA48: 0 | AB48: 0 | AC48: 0 | AD48: 0 | AE48: 0 | AF48: 0 | AG48: 0 | AH48: 0 | AI48: 0 | AJ48: 0 | AK48: 0 | AL48: 0 | AM48: 0 | AN48: 0 | AO48: 0 | AP48: 0 | AQ48: =I48+J48 -> 0 | AR48: =IF(AQ48>0,I48/AQ48,"") | AS48: =IF((P48+Q48)>0,P48/(P48+Q48),"") | AT48: =IF(AND(ISNUMBER(AR48),ISNUMBER(AS48)),(AR48-AS48)*100,"") | AU48: =IF(G48>0,I48/G48*1000,"") -> 0 | AV48: =IF(G48>0,H48/G48*10000,"") -> 0 | AW48: =IF(G48>0,W48/G48*10000,"") -> 0 | AX48: =IF(I48>0,K48/I48*100,"") | AY48: =IF(AQ48>=100,"ok",IF(AQ48>0,"effectif faible (<100)","aucune association")) -> aucune association
A49: 95157 | B49: Chérence | C49: Vauréal | D49: liste subventions 2025 | E49: CC du Vexin-Val de Seine | F49: Rural à habitat dispersé | G49: 137 | H49: 1 | I49: 75 | J49: 188 | K49: 141 | L49: 3 | M49: 0 | N49: 0 | O49: 1 | P49: 73 | Q49: 210 | R49: 0 | S49: 0 | T49: 0 | U49: 1 | V49: 0 | W49: 3 | X49: 0 | Y49: 0 | Z49: 1 | AA49: 0 | AB49: 1 | AC49: 0 | AD49: 0 | AE49: 1 | AF49: 1 | AG49: 1 | AH49: 1 | AI49: 1 | AJ49: 236 | AK49: 256 | AL49: 293 | AM49: 243 | AN49: 272 | AO49: 283 | AP49: 263 | AQ49: =I49+J49 -> 263 | AR49: =IF(AQ49>0,I49/AQ49,"") -> 0.2851711 | AS49: =IF((P49+Q49)>0,P49/(P49+Q49),"") -> 0.25795053 | AT49: =IF(AND(ISNUMBER(AR49),ISNUMBER(AS49)),(AR49-AS49)*100,"") -> 2.7220573 | AU49: =IF(G49>0,I49/G49*1000,"") -> 547.44526 | AV49: =IF(G49>0,H49/G49*10000,"") -> 72.992701 | AW49: =IF(G49>0,W49/G49*10000,"") -> 218.9781 | AX49: =IF(I49>0,K49/I49*100,"") -> 188 | AY49: =IF(AQ49>=100,"ok",IF(AQ49>0,"effectif faible (<100)","aucune association")) -> ok
A50: 95166 | B50: Cléry-en-Vexin | C50: Vauréal | D50: liste subventions 2025 | E50: CC Vexin Centre | F50: Rural à habitat dispersé | G50: 476 | H50: 0 | I50: 0 | J50: 0 | K50: 0 | L50: 0 | M50: 0 | N50: 0 | O50: 1 | P50: 72 | Q50: 118 | R50: 1 | S50: 45 | T50: 1 | U50: 1 | V50: 1 | W50: 1 | X50: 0 | Y50: 0 | Z50: 0 | AA50: 0 | AB50: 0 | AC50: 0 | AD50: 0 | AE50: 1 | AF50: 1 | AG50: 1 | AH50: 1 | AI50: 1 | AJ50: 14 | AK50: 18 | AL50: 13 | AM50: 18 | AN50: 20 | AO50: 190 | AP50: 0 | AQ50: =I50+J50 -> 0 | AR50: =IF(AQ50>0,I50/AQ50,"") | AS50: =IF((P50+Q50)>0,P50/(P50+Q50),"") -> 0.37894737 | AT50: =IF(AND(ISNUMBER(AR50),ISNUMBER(AS50)),(AR50-AS50)*100,"") | AU50: =IF(G50>0,I50/G50*1000,"") -> 0 | AV50: =IF(G50>0,H50/G50*10000,"") -> 0 | AW50: =IF(G50>0,W50/G50*10000,"") -> 21.008403 | AX50: =IF(I50>0,K50/I50*100,"") | AY50: =IF(AQ50>=100,"ok",IF(AQ50>0,"effectif faible (<100)","aucune association")) -> aucune association
A51: 95169 | B51: Commeny | C51: Vauréal | D51: imputé (commune voisine la plus proche) | E51: CC Vexin Centre | F51: Rural à habitat dispersé | G51: 646 | H51: 0 | I51: 0 | J51: 0 | K51: 0 | L51: 0 | M51: 0 | N51: 0 | O51: 0 | P51: 0 | Q51: 0 | R51: 0 | S51: 0 | T51: 0 | U51: 0 | V51: 0 | W51: 5 | X51: 1 | Y51: 0 | Z51: 0 | AA51: 0 | AB51: 0 | AC51: 0 | AD51: 0 | AE51: 0 | AF51: 0 | AG51: 0 | AH51: 0 | AI51: 0 | AJ51: 0 | AK51: 0 | AL51: 0 | AM51: 0 | AN51: 0 | AO51: 0 | AP51: 0 | AQ51: =I51+J51 -> 0 | AR51: =IF(AQ51>0,I51/AQ51,"") | AS51: =IF((P51+Q51)>0,P51/(P51+Q51),"") | AT51: =IF(AND(ISNUMBER(AR51),ISNUMBER(AS51)),(AR51-AS51)*100,"") | AU51: =IF(G51>0,I51/G51*1000,"") -> 0 | AV51: =IF(G51>0,H51/G51*10000,"") -> 0 | AW51: =IF(G51>0,W51/G51*10000,"") -> 77.399381 | AX51: =IF(I51>0,K51/I51*100,"") | AY51: =IF(AQ51>=100,"ok",IF(AQ51>0,"effectif faible (<100)","aucune association")) -> aucune association
A52: 95170 | B52: Condécourt | C52: Vauréal | D52: imputé (commune voisine la plus proche) | E52: CC Vexin Centre | F52: Rural à habitat dispersé | G52: 564 | H52: 0 | I52: 0 | J52: 0 | K52: 0 | L52: 0 | M52: 0 | N52: 0 | O52: 0 | P52: 0 | Q52: 0 | R52: 0 | S52: 0 | T52: 0 | U52: 0 | V52: 0 | W52: 2 | X52: 1 | Y52: 0 | Z52: 0 | AA52: 0 | AB52: 0 | AC52: 0 | AD52: 0 | AE52: 0 | AF52: 0 | AG52: 0 | AH52: 0 | AI52: 0 | AJ52: 0 | AK52: 0 | AL52: 0 | AM52: 0 | AN52: 0 | AO52: 0 | AP52: 0 | AQ52: =I52+J52 -> 0 | AR52: =IF(AQ52>0,I52/AQ52,"") | AS52: =IF((P52+Q52)>0,P52/(P52+Q52),"") | AT52: =IF(AND(ISNUMBER(AR52),ISNUMBER(AS52)),(AR52-AS52)*100,"") | AU52: =IF(G52>0,I52/G52*1000,"") -> 0 | AV52: =IF(G52>0,H52/G52*10000,"") -> 0 | AW52: =IF(G52>0,W52/G52*10000,"") -> 35.460993 | AX52: =IF(I52>0,K52/I52*100,"") | AY52: =IF(AQ52>=100,"ok",IF(AQ52>0,"effectif faible (<100)","aucune association")) -> aucune association
A53: 95176 | B53: Cormeilles-en-Parisis | C53: Franconville | D53: liste subventions 2025 | E53: CA Val Parisis | F53: Grands centres urbains | G53: 27292 | H53: 1 | I53: 3779 | J53: 2055 | K53: 203 | L53: 46 | M53: 0 | N53: 1 | O53: 2 | P53: 3683 | Q53: 2055 | R53: 1 | S53: 155 | T53: 3 | U53: 1 | V53: 1 | W53: 28 | X53: 10 | Y53: 1 | Z53: 0 | AA53: 0 | AB53: 0 | AC53: 1 | AD53: 0 | AE53: 1 | AF53: 2 | AG53: 2 | AH53: 2 | AI53: 2 | AJ53: 3399 | AK53: 4103 | AL53: 4063 | AM53: 3294 | AN53: 5033 | AO53: 5738 | AP53: 5834 | AQ53: =I53+J53 -> 5834 | AR53: =IF(AQ53>0,I53/AQ53,"") -> 0.64775454 | AS53: =IF((P53+Q53)>0,P53/(P53+Q53),"") -> 0.64186128 | AT53: =IF(AND(ISNUMBER(AR53),ISNUMBER(AS53)),(AR53-AS53)*100,"") -> 0.58932666 | AU53: =IF(G53>0,I53/G53*1000,"") -> 138.46548 | AV53: =IF(G53>0,H53/G53*10000,"") -> 0.36640774 | AW53: =IF(G53>0,W53/G53*10000,"") -> 10.259417 | AX53: =IF(I53>0,K53/I53*100,"") -> 5.3717915 | AY53: =IF(AQ53>=100,"ok",IF(AQ53>0,"effectif faible (<100)","aucune association")) -> ok
A54: 95177 | B54: Cormeilles-en-Vexin | C54: Pontoise | D54: imputé (commune voisine la plus proche) | E54: CC Vexin Centre | F54: Bourgs ruraux | G54: 1297 | H54: 0 | I54: 0 | J54: 0 | K54: 0 | L54: 0 | M54: 0 | N54: 0 | O54: 0 | P54: 0 | Q54: 0 | R54: 0 | S54: 0 | T54: 0 | U54: 0 | V54: 0 | W54: 6 | X54: 1 | Y54: 0 | Z54: 0 | AA54: 0 | AB54: 0 | AC54: 0 | AD54: 0 | AE54: 0 | AF54: 0 | AG54: 0 | AH54: 0 | AI54: 0 | AJ54: 0 | AK54: 0 | AL54: 0 | AM54: 0 | AN54: 0 | AO54: 0 | AP54: 0 | AQ54: =I54+J54 -> 0 | AR54: =IF(AQ54>0,I54/AQ54,"") | AS54: =IF((P54+Q54)>0,P54/(P54+Q54),"") | AT54: =IF(AND(ISNUMBER(AR54),ISNUMBER(AS54)),(AR54-AS54)*100,"") | AU54: =IF(G54>0,I54/G54*1000,"") -> 0 | AV54: =IF(G54>0,H54/G54*10000,"") -> 0 | AW54: =IF(G54>0,W54/G54*10000,"") -> 46.260601 | AX54: =IF(I54>0,K54/I54*100,"") | AY54: =IF(AQ54>=100,"ok",IF(AQ54>0,"effectif faible (<100)","aucune association")) -> aucune association
A55: 95181 | B55: Courcelles-sur-Viosne | C55: Pontoise | D55: imputé (commune voisine la plus proche) | E55: CC Vexin Centre | F55: Rural à habitat dispersé | G55: 310 | H55: 0 | I55: 0 | J55: 0 | K55: 0 | L55: 0 | M55: 0 | N55: 0 | O55: 0 | P55: 0 | Q55: 0 | R55: 0 | S55: 0 | T55: 0 | U55: 0 | V55: 0 | W55: 2 | X55: 0 | Y55: 0 | Z55: 0 | AA55: 0 | AB55: 0 | AC55: 0 | AD55: 0 | AE55: 0 | AF55: 0 | AG55: 0 | AH55: 0 | AI55: 0 | AJ55: 0 | AK55: 0 | AL55: 0 | AM55: 0 | AN55: 0 | AO55: 0 | AP55: 0 | AQ55: =I55+J55 -> 0 | AR55: =IF(AQ55>0,I55/AQ55,"") | AS55: =IF((P55+Q55)>0,P55/(P55+Q55),"") | AT55: =IF(AND(ISNUMBER(AR55),ISNUMBER(AS55)),(AR55-AS55)*100,"") | AU55: =IF(G55>0,I55/G55*1000,"") -> 0 | AV55: =IF(G55>0,H55/G55*10000,"") -> 0 | AW55: =IF(G55>0,W55/G55*10000,"") -> 64.516129 | AX55: =IF(I55>0,K55/I55*100,"") | AY55: =IF(AQ55>=100,"ok",IF(AQ55>0,"effectif faible (<100)","aucune association")) -> aucune association
A56: 95183 | B56: Courdimanche | C56: Vauréal | D56: liste subventions 2025 | E56: CA de Cergy-Pontoise | F56: Grands centres urbains | G56: 7311 | H56: 4 | I56: 333 | J56: 645 | K56: 59 | L56: 11 | M56: 1 | N56: 2 | O56: 5 | P56: 343 | Q56: 682 | R56: 1 | S56: 416 | T56: 20 | U56: 5 | V56: 1 | W56: 7 | X56: 2 | Y56: 0 | Z56: 0 | AA56: 0 | AB56: 1 | AC56: 0 | AD56: 0 | AE56: 4 | AF56: 5 | AG56: 5 | AH56: 4 | AI56: 5 | AJ56: 494 | AK56: 996 | AL56: 952 | AM56: 757 | AN56: 918 | AO56: 1025 | AP56: 978 | AQ56: =I56+J56 -> 978 | AR56: =IF(AQ56>0,I56/AQ56,"") -> 0.3404908 | AS56: =IF((P56+Q56)>0,P56/(P56+Q56),"") -> 0.33463415 | AT56: =IF(AND(ISNUMBER(AR56),ISNUMBER(AS56)),(AR56-AS56)*100,"") -> 0.58566512 | AU56: =IF(G56>0,I56/G56*1000,"") -> 45.547805 | AV56: =IF(G56>0,H56/G56*10000,"") -> 5.4712078 | AW56: =IF(G56>0,W56/G56*10000,"") -> 9.5746136 | AX56: =IF(I56>0,K56/I56*100,"") -> 17.717718 | AY56: =IF(AQ56>=100,"ok",IF(AQ56>0,"effectif faible (<100)","aucune association")) -> ok
A57: 95197 | B57: Deuil-la-Barre | C57: Deuil-la-Barre | D57: liste subventions 2025 | E57: CA Plaine Vallée | F57: Grands centres urbains | G57: 23099 | H57: 6 | I57: 1140 | J57: 1428 | K57: 134 | L57: 16 | M57: 1 | N57: 2 | O57: 8 | P57: 1365 | Q57: 1771 | R57: 2 | S57: 236 | T57: 7 | U57: 6 | V57: 2 | W57: 19 | X57: 10 | Y57: 0 | Z57: 0 | AA57: 1 | AB57: 0 | AC57: 0 | AD57: 0 | AE57: 8 | AF57: 9 | AG57: 9 | AH57: 8 | AI57: 8 | AJ57: 2377 | AK57: 3056 | AL57: 2952 | AM57: 2643 | AN57: 3079 | AO57: 3136 | AP57: 2568 | AQ57: =I57+J57 -> 2568 | AR57: =IF(AQ57>0,I57/AQ57,"") -> 0.44392523 | AS57: =IF((P57+Q57)>0,P57/(P57+Q57),"") -> 0.43526786 | AT57: =IF(AND(ISNUMBER(AR57),ISNUMBER(AS57)),(AR57-AS57)*100,"") -> 0.86573765 | AU57: =IF(G57>0,I57/G57*1000,"") -> 49.352786 | AV57: =IF(G57>0,H57/G57*10000,"") -> 2.597515 | AW57: =IF(G57>0,W57/G57*10000,"") -> 8.2254643 | AX57: =IF(I57>0,K57/I57*100,"") -> 11.754386 | AY57: =IF(AQ57>=100,"ok",IF(AQ57>0,"effectif faible (<100)","aucune association")) -> ok
A58: 95199 | B58: Domont | C58: Domont | D58: liste subventions 2025 | E58: CA Plaine Vallée | F58: Grands centres urbains | G58: 16065 | H58: 12 | I58: 892 | J58: 1742 | K58: 230 | L58: 28 | M58: 3 | N58: 1 | O58: 12 | P58: 842 | Q58: 1616 | R58: 2 | S58: 401 | T58: 10 | U58: 13 | V58: 2 | W58: 13 | X58: 2 | Y58: 0 | Z58: 0 | AA58: 0 | AB58: 0 | AC58: 0 | AD58: 0 | AE58: 10 | AF58: 11 | AG58: 13 | AH58: 12 | AI58: 11 | AJ58: 2052 | AK58: 2020 | AL58: 2497 | AM58: 2621 | AN58: 2414 | AO58: 2458 | AP58: 2634 | AQ58: =I58+J58 -> 2634 | AR58: =IF(AQ58>0,I58/AQ58,"") -> 0.33864844 | AS58: =IF((P58+Q58)>0,P58/(P58+Q58),"") -> 0.34255492 | AT58: =IF(AND(ISNUMBER(AR58),ISNUMBER(AS58)),(AR58-AS58)*100,"") -> -0.39064793 | AU58: =IF(G58>0,I58/G58*1000,"") -> 55.524432 | AV58: =IF(G58>0,H58/G58*10000,"") -> 7.4696545 | AW58: =IF(G58>0,W58/G58*10000,"") -> 8.0921257 | AX58: =IF(I58>0,K58/I58*100,"") -> 25.784753 | AY58: =IF(AQ58>=100,"ok",IF(AQ58>0,"effectif faible (<100)","aucune association")) -> ok
A59: 95203 | B59: Eaubonne | C59: Ermont | D59: liste subventions 2025 | E59: CA Val Parisis | F59: Grands centres urbains | G59: 26211 | H59: 7 | I59: 1011 | J59: 583 | K59: 114 | L59: 23 | M59: 0 | N59: 3 | O59: 7 | P59: 1114 | Q59: 516 | R59: 1 | S59: 109 | T59: 4 | U59: 8 | V59: 1 | W59: 20 | X59: 0 | Y59: 1 | Z59: 4 | AA59: 1 | AB59: 4 | AC59: 0 | AD59: 0 | AE59: 6 | AF59: 6 | AG59: 7 | AH59: 7 | AI59: 6 | AJ59: 4317 | AK59: 4382 | AL59: 3698 | AM59: 1253 | AN59: 779 | AO59: 1630 | AP59: 1594 | AQ59: =I59+J59 -> 1594 | AR59: =IF(AQ59>0,I59/AQ59,"") -> 0.63425345 | AS59: =IF((P59+Q59)>0,P59/(P59+Q59),"") -> 0.68343558 | AT59: =IF(AND(ISNUMBER(AR59),ISNUMBER(AS59)),(AR59-AS59)*100,"") -> -4.9182132 | AU59: =IF(G59>0,I59/G59*1000,"") -> 38.571592 | AV59: =IF(G59>0,H59/G59*10000,"") -> 2.6706345 | AW59: =IF(G59>0,W59/G59*10000,"") -> 7.6303842 | AX59: =IF(I59>0,K59/I59*100,"") -> 11.275964 | AY59: =IF(AQ59>=100,"ok",IF(AQ59>0,"effectif faible (<100)","aucune association")) -> ok
A60: 95210 | B60: Enghien-les-Bains | C60: Montmorency | D60: liste subventions 2025 | E60: CA Plaine Vallée | F60: Grands centres urbains | G60: 11432 | H60: 8 | I60: 748 | J60: 624 | K60: 180 | L60: 14 | M60: 3 | N60: 3 | O60: 8 | P60: 769 | Q60: 602 | R60: 0 | S60: 0 | T60: 0 | U60: 9 | V60: 0 | W60: 19 | X60: 7 | Y60: 0 | Z60: 0 | AA60: 0 | AB60: 2 | AC60: 1 | AD60: 0 | AE60: 6 | AF60: 7 | AG60: 7 | AH60: 8 | AI60: 9 | AJ60: 841 | AK60: 1028 | AL60: 783 | AM60: 1055 | AN60: 1221 | AO60: 1371 | AP60: 1372 | AQ60: =I60+J60 -> 1372 | AR60: =IF(AQ60>0,I60/AQ60,"") -> 0.5451895 | AS60: =IF((P60+Q60)>0,P60/(P60+Q60),"") -> 0.56090445 | AT60: =IF(AND(ISNUMBER(AR60),ISNUMBER(AS60)),(AR60-AS60)*100,"") -> -1.5714945 | AU60: =IF(G60>0,I60/G60*1000,"") -> 65.430371 | AV60: =IF(G60>0,H60/G60*10000,"") -> 6.9979006 | AW60: =IF(G60>0,W60/G60*10000,"") -> 16.620014 | AX60: =IF(I60>0,K60/I60*100,"") -> 24.064171 | AY60: =IF(AQ60>=100,"ok",IF(AQ60>0,"effectif faible (<100)","aucune association")) -> ok
... A78: 95298 | B78: Haravilliers | C78: Pontoise | D78: liste subventions 2025 | E78: CC Vexin Centre | F78: Rural à habitat dispersé | G78: 589 | H78: 1 | I78: 158 | J78: 61 | K78: 6 | L78: 2 | M78: 0 | N78: 1 | O78: 1 | P78: 174 | Q78: 72 | R78: 0 | S78: 0 | T78: 0 | U78: 1 | V78: 0 | W78: 2 | X78: 1 | Y78: 0 | Z78: 0 | AA78: 0 | AB78: 0 | AC78: 0 | AD78: 0 | AE78: 1 | AF78: 1 | AG78: 1 | AH78: 1 | AI78: 1 | AJ78: 100 | AK78: 0 | AL78: 0 | AM78: 0 | AN78: 0 | AO78: 246 | AP78: 219 | AQ78: =I78+J78 -> 219 | AR78: =IF(AQ78>0,I78/AQ78,"") -> 0.72146119 | AS78: =IF((P78+Q78)>0,P78/(P78+Q78),"") -> 0.70731707 | AT78: =IF(AND(ISNUMBER(AR78),ISNUMBER(AS78)),(AR78-AS78)*100,"") -> 1.4144114 | AU78: =IF(G78>0,I78/G78*1000,"") -> 268.25127 | AV78: =IF(G78>0,H78/G78*10000,"") -> 16.977929 | AW78: =IF(G78>0,W78/G78*10000,"") -> 33.955857 | AX78: =IF(I78>0,K78/I78*100,"") -> 3.7974684 | AY78: =IF(AQ78>=100,"ok",IF(AQ78>0,"effectif faible (<100)","aucune association")) -> ok
A79: 95301 | B79: Haute-Isle | C79: Vauréal | D79: imputé (commune voisine la plus proche) | E79: CC du Vexin-Val de Seine | G79: 293 | H79: 0 | I79: 0 | J79: 0 | K79: 0 | L79: 0 | M79: 0 | N79: 0 | O79: 0 | P79: 0 | Q79: 0 | R79: 0 | S79: 0 | T79: 0 | U79: 0 | V79: 0 | W79: 0 | X79: 0 | Y79: 0 | Z79: 0 | AA79: 0 | AB79: 0 | AC79: 0 | AD79: 0 | AE79: 0 | AF79: 0 | AG79: 0 | AH79: 0 | AI79: 0 | AJ79: 0 | AK79: 0 | AL79: 0 | AM79: 0 | AN79: 0 | AO79: 0 | AP79: 0 | AQ79: =I79+J79 -> 0 | AR79: =IF(AQ79>0,I79/AQ79,"") | AS79: =IF((P79+Q79)>0,P79/(P79+Q79),"") | AT79: =IF(AND(ISNUMBER(AR79),ISNUMBER(AS79)),(AR79-AS79)*100,"") | AU79: =IF(G79>0,I79/G79*1000,"") -> 0 | AV79: =IF(G79>0,H79/G79*10000,"") -> 0 | AW79: =IF(G79>0,W79/G79*10000,"") -> 0 | AX79: =IF(I79>0,K79/I79*100,"") | AY79: =IF(AQ79>=100,"ok",IF(AQ79>0,"effectif faible (<100)","aucune association")) -> aucune association
A80: 95306 | B80: Herblay-sur-Seine | C80: Herblay-sur-Seine | D80: liste subventions 2025 | E80: CA Val Parisis | F80: Grands centres urbains | G80: 31779 | H80: 15 | I80: 1891 | J80: 2322 | K80: 287 | L80: 48 | M80: 2 | N80: 2 | O80: 15 | P80: 1765 | Q80: 2031 | R80: 0 | S80: 0 | T80: 0 | U80: 17 | V80: 0 | W80: 26 | X80: 14 | Y80: 1 | Z80: 0 | AA80: 1 | AB80: 0 | AC80: 1 | AD80: 0 | AE80: 13 | AF80: 14 | AG80: 13 | AH80: 13 | AI80: 15 | AJ80: 3382 | AK80: 3481 | AL80: 3385 | AM80: 3161 | AN80: 3494 | AO80: 3796 | AP80: 4213 | AQ80: =I80+J80 -> 4213 | AR80: =IF(AQ80>0,I80/AQ80,"") -> 0.4488488 | AS80: =IF((P80+Q80)>0,P80/(P80+Q80),"") -> 0.46496312 | AT80: =IF(AND(ISNUMBER(AR80),ISNUMBER(AS80)),(AR80-AS80)*100,"") -> -1.6114318 | AU80: =IF(G80>0,I80/G80*1000,"") -> 59.504704 | AV80: =IF(G80>0,H80/G80*10000,"") -> 4.7200982 | AW80: =IF(G80>0,W80/G80*10000,"") -> 8.1815035 | AX80: =IF(I80>0,K80/I80*100,"") -> 15.177155 | AY80: =IF(AQ80>=100,"ok",IF(AQ80>0,"effectif faible (<100)","aucune association")) -> ok
A81: 95309 | B81: Hodent | C81: Vauréal | D81: imputé (commune voisine la plus proche) | E81: CC du Vexin-Val de Seine | F81: Rural à habitat dispersé | G81: 225 | H81: 0 | I81: 0 | J81: 0 | K81: 0 | L81: 0 | M81: 0 | N81: 0 | O81: 0 | P81: 0 | Q81: 0 | R81: 0 | S81: 0 | T81: 0 | U81: 0 | V81: 0 | W81: 1 | X81: 0 | Y81: 0 | Z81: 0 | AA81: 0 | AB81: 0 | AC81: 0 | AD81: 0 | AE81: 0 | AF81: 0 | AG81: 0 | AH81: 0 | AI81: 0 | AJ81: 0 | AK81: 0 | AL81: 0 | AM81: 0 | AN81: 0 | AO81: 0 | AP81: 0 | AQ81: =I81+J81 -> 0 | AR81: =IF(AQ81>0,I81/AQ81,"") | AS81: =IF((P81+Q81)>0,P81/(P81+Q81),"") | AT81: =IF(AND(ISNUMBER(AR81),ISNUMBER(AS81)),(AR81-AS81)*100,"") | AU81: =IF(G81>0,I81/G81*1000,"") -> 0 | AV81: =IF(G81>0,H81/G81*10000,"") -> 0 | AW81: =IF(G81>0,W81/G81*10000,"") -> 44.444444 | AX81: =IF(I81>0,K81/I81*100,"") | AY81: =IF(AQ81>=100,"ok",IF(AQ81>0,"effectif faible (<100)","aucune association")) -> aucune association
A82: 95304 | B82: Hédouville | C82: Saint-Ouen-l'Aumône | D82: imputé (commune voisine la plus proche) | E82: CC Sausseron Impressionnistes | F82: Rural à habitat dispersé | G82: 278 | H82: 0 | I82: 0 | J82: 0 | K82: 0 | L82: 0 | M82: 0 | N82: 0 | O82: 0 | P82: 0 | Q82: 0 | R82: 0 | S82: 0 | T82: 0 | U82: 0 | V82: 0 | W82: 3 | X82: 0 | Y82: 0 | Z82: 0 | AA82: 0 | AB82: 0 | AC82: 0 | AD82: 0 | AE82: 0 | AF82: 0 | AG82: 0 | AH82: 0 | AI82: 0 | AJ82: 0 | AK82: 0 | AL82: 0 | AM82: 0 | AN82: 0 | AO82: 0 | AP82: 0 | AQ82: =I82+J82 -> 0 | AR82: =IF(AQ82>0,I82/AQ82,"") | AS82: =IF((P82+Q82)>0,P82/(P82+Q82),"") | AT82: =IF(AND(ISNUMBER(AR82),ISNUMBER(AS82)),(AR82-AS82)*100,"") | AU82: =IF(G82>0,I82/G82*1000,"") -> 0 | AV82: =IF(G82>0,H82/G82*10000,"") -> 0 | AW82: =IF(G82>0,W82/G82*10000,"") -> 107.91367 | AX82: =IF(I82>0,K82/I82*100,"") | AY82: =IF(AQ82>=100,"ok",IF(AQ82>0,"effectif faible (<100)","aucune association")) -> aucune association
A83: 95308 | B83: Hérouville-en-Vexin | C83: Saint-Ouen-l'Aumône | D83: imputé (commune voisine la plus proche) | E83: CC Sausseron Impressionnistes | F83: Bourgs ruraux | G83: 584 | H83: 0 | I83: 0 | J83: 0 | K83: 0 | L83: 0 | M83: 0 | N83: 0 | O83: 0 | P83: 0 | Q83: 0 | R83: 0 | S83: 0 | T83: 0 | U83: 0 | V83: 0 | W83: 4 | X83: 0 | Y83: 0 | Z83: 0 | AA83: 0 | AB83: 0 | AC83: 0 | AD83: 0 | AE83: 0 | AF83: 0 | AG83: 0 | AH83: 0 | AI83: 0 | AJ83: 0 | AK83: 0 | AL83: 0 | AM83: 0 | AN83: 0 | AO83: 0 | AP83: 0 | AQ83: =I83+J83 -> 0 | AR83: =IF(AQ83>0,I83/AQ83,"") | AS83: =IF((P83+Q83)>0,P83/(P83+Q83),"") | AT83: =IF(AND(ISNUMBER(AR83),ISNUMBER(AS83)),(AR83-AS83)*100,"") | AU83: =IF(G83>0,I83/G83*1000,"") -> 0 | AV83: =IF(G83>0,H83/G83*10000,"") -> 0 | AW83: =IF(G83>0,W83/G83*10000,"") -> 68.493151 | AX83: =IF(I83>0,K83/I83*100,"") | AY83: =IF(AQ83>=100,"ok",IF(AQ83>0,"effectif faible (<100)","aucune association")) -> aucune association
A84: 95316 | B84: Jagny-sous-Bois | C84: Fosses | D84: imputé (commune voisine la plus proche) | E84: CC Carnelle Pays-de-France | F84: Rural à habitat dispersé | G84: 269 | H84: 0 | I84: 0 | J84: 0 | K84: 0 | L84: 0 | M84: 0 | N84: 0 | O84: 0 | P84: 0 | Q84: 0 | R84: 0 | S84: 0 | T84: 0 | U84: 0 | V84: 0 | W84: 1 | X84: 0 | Y84: 0 | Z84: 0 | AA84: 0 | AB84: 0 | AC84: 0 | AD84: 0 | AE84: 0 | AF84: 0 | AG84: 0 | AH84: 0 | AI84: 0 | AJ84: 0 | AK84: 0 | AL84: 0 | AM84: 0 | AN84: 0 | AO84: 0 | AP84: 0 | AQ84: =I84+J84 -> 0 | AR84: =IF(AQ84>0,I84/AQ84,"") | AS84: =IF((P84+Q84)>0,P84/(P84+Q84),"") | AT84: =IF(AND(ISNUMBER(AR84),ISNUMBER(AS84)),(AR84-AS84)*100,"") | AU84: =IF(G84>0,I84/G84*1000,"") -> 0 | AV84: =IF(G84>0,H84/G84*10000,"") -> 0 | AW84: =IF(G84>0,W84/G84*10000,"") -> 37.174721 | AX84: =IF(I84>0,K84/I84*100,"") | AY84: =IF(AQ84>=100,"ok",IF(AQ84>0,"effectif faible (<100)","aucune association")) -> aucune association
A85: 95323 | B85: Jouy-le-Moutier | C85: Cergy (1-2) | D85: liste subventions 2025 | E85: CA de Cergy-Pontoise | F85: Grands centres urbains | G85: 17854 | H85: 13 | I85: 810 | J85: 1921 | K85: 200 | L85: 31 | M85: 4 | N85: 1 | O85: 13 | P85: 765 | Q85: 1792 | R85: 7 | S85: 1320 | T85: 45 | U85: 12 | V85: 8 | W85: 31 | X85: 6 | Y85: 1 | Z85: 0 | AA85: 0 | AB85: 0 | AC85: 1 | AD85: 0 | AE85: 11 | AF85: 12 | AG85: 11 | AH85: 11 | AI85: 12 | AJ85: 1838 | AK85: 1994 | AL85: 1982 | AM85: 1978 | AN85: 2038 | AO85: 2557 | AP85: 2731 | AQ85: =I85+J85 -> 2731 | AR85: =IF(AQ85>0,I85/AQ85,"") -> 0.29659465 | AS85: =IF((P85+Q85)>0,P85/(P85+Q85),"") -> 0.29917873 | AT85: =IF(AND(ISNUMBER(AR85),ISNUMBER(AS85)),(AR85-AS85)*100,"") -> -0.25840711 | AU85: =IF(G85>0,I85/G85*1000,"") -> 45.367985 | AV85: =IF(G85>0,H85/G85*10000,"") -> 7.2812815 | AW85: =IF(G85>0,W85/G85*10000,"") -> 17.363056 | AX85: =IF(I85>0,K85/I85*100,"") -> 24.691358 | AY85: =IF(AQ85>=100,"ok",IF(AQ85>0,"effectif faible (<100)","aucune association")) -> ok
A86: 95313 | B86: L'Isle-Adam | C86: L'Isle-Adam | D86: liste subventions 2025 | E86: CC de la Vallée de l'Oise et des Trois Forêts | F86: Centres urbains intermédiaires | G86: 12493 | H86: 17 | I86: 1317 | J86: 1480 | K86: 192 | L86: 28 | M86: 6 | N86: 3 | O86: 16 | P86: 1127 | Q86: 1185 | R86: 1 | S86: 40 | T86: 4 | U86: 17 | V86: 1 | W86: 19 | X86: 2 | Y86: 2 | Z86: 0 | AA86: 1 | AB86: 1 | AC86: 0 | AD86: 0 | AE86: 14 | AF86: 17 | AG86: 17 | AH86: 17 | AI86: 16 | AJ86: 2384 | AK86: 2623 | AL86: 2307 | AM86: 2433 | AN86: 2248 | AO86: 2312 | AP86: 2797 | AQ86: =I86+J86 -> 2797 | AR86: =IF(AQ86>0,I86/AQ86,"") -> 0.47086164 | AS86: =IF((P86+Q86)>0,P86/(P86+Q86),"") -> 0.48745675 | AT86: =IF(AND(ISNUMBER(AR86),ISNUMBER(AS86)),(AR86-AS86)*100,"") -> -1.659511 | AU86: =IF(G86>0,I86/G86*1000,"") -> 105.41903 | AV86: =IF(G86>0,H86/G86*10000,"") -> 13.60762 | AW86: =IF(G86>0,W86/G86*10000,"") -> 15.208517 | AX86: =IF(I86>0,K86/I86*100,"") -> 14.578588 | AY86: =IF(AQ86>=100,"ok",IF(AQ86>0,"effectif faible (<100)","aucune association")) -> ok
A87: 95139 | B87: La Chapelle-en-Vexin | C87: Vauréal | D87: imputé (commune voisine la plus proche) | E87: CC du Vexin-Val de Seine | F87: Rural à habitat dispersé | G87: 320 | H87: 0 | I87: 0 | J87: 0 | K87: 0 | L87: 0 | M87: 0 | N87: 0 | O87: 0 | P87: 0 | Q87: 0 | R87: 0 | S87: 0 | T87: 0 | U87: 0 | V87: 0 | W87: 1 | X87: 0 | Y87: 0 | Z87: 0 | AA87: 0 | AB87: 0 | AC87: 0 | AD87: 0 | AE87: 0 | AF87: 0 | AG87: 0 | AH87: 0 | AI87: 0 | AJ87: 0 | AK87: 0 | AL87: 0 | AM87: 0 | AN87: 0 | AO87: 0 | AP87: 0 | AQ87: =I87+J87 -> 0 | AR87: =IF(AQ87>0,I87/AQ87,"") | AS87: =IF((P87+Q87)>0,P87/(P87+Q87),"") | AT87: =IF(AND(ISNUMBER(AR87),ISNUMBER(AS87)),(AR87-AS87)*100,"") | AU87: =IF(G87>0,I87/G87*1000,"") -> 0 | AV87: =IF(G87>0,H87/G87*10000,"") -> 0 | AW87: =IF(G87>0,W87/G87*10000,"") -> 31.25 | AX87: =IF(I87>0,K87/I87*100,"") | AY87: =IF(AQ87>=100,"ok",IF(AQ87>0,"effectif faible (<100)","aucune association")) -> aucune association
A88: 95257 | B88: La Frette-sur-Seine | C88: Herblay-sur-Seine | D88: liste subventions 2025 | E88: CA Val Parisis | F88: Grands centres urbains | G88: 4570 | H88: 4 | I88: 386 | J88: 261 | K88: 36 | L88: 5 | M88: 0 | N88: 1 | O88: 4 | P88: 215 | Q88: 408 | R88: 0 | S88: 0 | T88: 0 | U88: 3 | V88: 0 | W88: 4 | X88: 2 | Y88: 0 | Z88: 0 | AA88: 0 | AB88: 0 | AC88: 0 | AD88: 0 | AE88: 3 | AF88: 3 | AG88: 3 | AH88: 3 | AI88: 4 | AJ88: 1012 | AK88: 505 | AL88: 445 | AM88: 486 | AN88: 560 | AO88: 623 | AP88: 647 | AQ88: =I88+J88 -> 647 | AR88: =IF(AQ88>0,I88/AQ88,"") -> 0.59659969 | AS88: =IF((P88+Q88)>0,P88/(P88+Q88),"") -> 0.34510433 | AT88: =IF(AND(ISNUMBER(AR88),ISNUMBER(AS88)),(AR88-AS88)*100,"") -> 25.149536 | AU88: =IF(G88>0,I88/G88*1000,"") -> 84.463895 | AV88: =IF(G88>0,H88/G88*10000,"") -> 8.7527352 | AW88: =IF(G88>0,W88/G88*10000,"") -> 8.7527352 | AX88: =IF(I88>0,K88/I88*100,"") -> 9.3264249 | AY88: =IF(AQ88>=100,"ok",IF(AQ88>0,"effectif faible (<100)","aucune association")) -> ok
A89: 95523 | B89: La Roche-Guyon | C89: Vauréal | D89: imputé (commune voisine la plus proche) | E89: CC du Vexin-Val de Seine | F89: Rural à habitat dispersé | G89: 399 | H89: 0 | I89: 0 | J89: 0 | K89: 0 | L89: 0 | M89: 0 | N89: 0 | O89: 0 | P89: 0 | Q89: 0 | R89: 0 | S89: 0 | T89: 0 | U89: 0 | V89: 0 | W89: 7 | X89: 1 | Y89: 0 | Z89: 0 | AA89: 0 | AB89: 0 | AC89: 0 | AD89: 0 | AE89: 0 | AF89: 0 | AG89: 0 | AH89: 0 | AI89: 0 | AJ89: 0 | AK89: 0 | AL89: 0 | AM89: 0 | AN89: 0 | AO89: 0 | AP89: 0 | AQ89: =I89+J89 -> 0 | AR89: =IF(AQ89>0,I89/AQ89,"") | AS89: =IF((P89+Q89)>0,P89/(P89+Q89),"") | AT89: =IF(AND(ISNUMBER(AR89),ISNUMBER(AS89)),(AR89-AS89)*100,"") | AU89: =IF(G89>0,I89/G89*1000,"") -> 0 | AV89: =IF(G89>0,H89/G89*10000,"") -> 0 | AW89: =IF(G89>0,W89/G89*10000,"") -> 175.4386 | AX89: =IF(I89>0,K89/I89*100,"") | AY89: =IF(AQ89>=100,"ok",IF(AQ89>0,"effectif faible (<100)","aucune association")) -> aucune association
A90: 95328 | B90: Labbeville | C90: Pontoise | D90: imputé (commune voisine la plus proche) | E90: CC Sausseron Impressionnistes | F90: Rural à habitat dispersé | G90: 641 | H90: 0 | I90: 0 | J90: 0 | K90: 0 | L90: 0 | M90: 0 | N90: 0 | O90: 0 | P90: 0 | Q90: 0 | R90: 0 | S90: 0 | T90: 0 | U90: 0 | V90: 0 | W90: 2 | X90: 0 | Y90: 0 | Z90: 0 | AA90: 0 | AB90: 0 | AC90: 0 | AD90: 0 | AE90: 0 | AF90: 0 | AG90: 0 | AH90: 0 | AI90: 0 | AJ90: 0 | AK90: 0 | AL90: 0 | AM90: 0 | AN90: 0 | AO90: 0 | AP90: 0 | AQ90: =I90+J90 -> 0 | AR90: =IF(AQ90>0,I90/AQ90,"") | AS90: =IF((P90+Q90)>0,P90/(P90+Q90),"") | AT90: =IF(AND(ISNUMBER(AR90),ISNUMBER(AS90)),(AR90-AS90)*100,"") | AU90: =IF(G90>0,I90/G90*1000,"") -> 0 | AV90: =IF(G90>0,H90/G90*10000,"") -> 0 | AW90: =IF(G90>0,W90/G90*10000,"") -> 31.201248 | AX90: =IF(I90>0,K90/I90*100,"") | AY90: =IF(AQ90>=100,"ok",IF(AQ90>0,"effectif faible (<100)","aucune association")) -> aucune association
A91: 95331 | B91: Lassy | C91: Fosses | D91: imputé (commune voisine la plus proche) | E91: CC Carnelle Pays-de-France | F91: Bourgs ruraux | G91: 196 | H91: 0 | I91: 0 | J91: 0 | K91: 0 | L91: 0 | M91: 0 | N91: 0 | O91: 0 | P91: 0 | Q91: 0 | R91: 0 | S91: 0 | T91: 0 | U91: 0 | V91: 0 | W91: 1 | X91: 0 | Y91: 0 | Z91: 0 | AA91: 0 | AB91: 0 | AC91: 0 | AD91: 0 | AE91: 0 | AF91: 0 | AG91: 0 | AH91: 0 | AI91: 0 | AJ91: 0 | AK91: 0 | AL91: 0 | AM91: 0 | AN91: 0 | AO91: 0 | AP91: 0 | AQ91: =I91+J91 -> 0 | AR91: =IF(AQ91>0,I91/AQ91,"") | AS91: =IF((P91+Q91)>0,P91/(P91+Q91),"") | AT91: =IF(AND(ISNUMBER(AR91),ISNUMBER(AS91)),(AR91-AS91)*100,"") | AU91: =IF(G91>0,I91/G91*1000,"") -> 0 | AV91: =IF(G91>0,H91/G91*10000,"") -> 0 | AW91: =IF(G91>0,W91/G91*10000,"") -> 51.020408 | AX91: =IF(I91>0,K91/I91*100,"") | AY91: =IF(AQ91>=100,"ok",IF(AQ91>0,"effectif faible (<100)","aucune association")) -> aucune association
A92: 95054 | B92: Le Bellay-en-Vexin | C92: Vauréal | D92: imputé (commune voisine la plus proche) | E92: CC Vexin Centre | F92: Rural à habitat dispersé | G92: 224 | H92: 0 | I92: 0 | J92: 0 | K92: 0 | L92: 0 | M92: 0 | N92: 0 | O92: 0 | P92: 0 | Q92: 0 | R92: 0 | S92: 0 | T92: 0 | U92: 0 | V92: 0 | W92: 2 | X92: 0 | Y92: 0 | Z92: 0 | AA92: 0 | AB92: 0 | AC92: 0 | AD92: 0 | AE92: 0 | AF92: 0 | AG92: 0 | AH92: 0 | AI92: 0 | AJ92: 0 | AK92: 0 | AL92: 0 | AM92: 0 | AN92: 0 | AO92: 0 | AP92: 0 | AQ92: =I92+J92 -> 0 | AR92: =IF(AQ92>0,I92/AQ92,"") | AS92: =IF((P92+Q92)>0,P92/(P92+Q92),"") | AT92: =IF(AND(ISNUMBER(AR92),ISNUMBER(AS92)),(AR92-AS92)*100,"") | AU92: =IF(G92>0,I92/G92*1000,"") -> 0 | AV92: =IF(G92>0,H92/G92*10000,"") -> 0 | AW92: =IF(G92>0,W92/G92*10000,"") -> 89.285714 | AX92: =IF(I92>0,K92/I92*100,"") | AY92: =IF(AQ92>=100,"ok",IF(AQ92>0,"effectif faible (<100)","aucune association")) -> aucune association
A93: 95303 | B93: Le Heaulme | C93: Pontoise | D93: imputé (commune voisine la plus proche) | E93: CC Vexin Centre | G93: 207 | H93: 0 | I93: 0 | J93: 0 | K93: 0 | L93: 0 | M93: 0 | N93: 0 | O93: 0 | P93: 0 | Q93: 0 | R93: 0 | S93: 0 | T93: 0 | U93: 0 | V93: 0 | W93: 0 | X93: 0 | Y93: 0 | Z93: 0 | AA93: 0 | AB93: 0 | AC93: 0 | AD93: 0 | AE93: 0 | AF93: 0 | AG93: 0 | AH93: 0 | AI93: 0 | AJ93: 0 | AK93: 0 | AL93: 0 | AM93: 0 | AN93: 0 | AO93: 0 | AP93: 0 | AQ93: =I93+J93 -> 0 | AR93: =IF(AQ93>0,I93/AQ93,"") | AS93: =IF((P93+Q93)>0,P93/(P93+Q93),"") | AT93: =IF(AND(ISNUMBER(AR93),ISNUMBER(AS93)),(AR93-AS93)*100,"") | AU93: =IF(G93>0,I93/G93*1000,"") -> 0 | AV93: =IF(G93>0,H93/G93*10000,"") -> 0 | AW93: =IF(G93>0,W93/G93*10000,"") -> 0 | AX93: =IF(I93>0,K93/I93*100,"") | AY93: =IF(AQ93>=100,"ok",IF(AQ93>0,"effectif faible (<100)","aucune association")) -> aucune association
A94: 95395 | B94: Le Mesnil-Aubry | C94: Fosses | D94: liste subventions 2025 | E94: CA Roissy Pays de France | F94: Bourgs ruraux | G94: 914 | H94: 1 | I94: 19 | J94: 4 | K94: 3 | L94: 1 | M94: 0 | N94: 1 | O94: 1 | P94: 15 | Q94: 3 | R94: 0 | S94: 0 | T94: 0 | U94: 1 | V94: 0 | W94: 4 | X94: 1 | Y94: 0 | Z94: 0 | AA94: 0 | AB94: 0 | AC94: 0 | AD94: 0 | AE94: 0 | AF94: 1 | AG94: 1 | AH94: 1 | AI94: 1 | AJ94: 0 | AK94: 29 | AL94: 23 | AM94: 12 | AN94: 19 | AO94: 18 | AP94: 23 | AQ94: =I94+J94 -> 23 | AR94: =IF(AQ94>0,I94/AQ94,"") -> 0.82608696 | AS94: =IF((P94+Q94)>0,P94/(P94+Q94),"") -> 0.83333333 | AT94: =IF(AND(ISNUMBER(AR94),ISNUMBER(AS94)),(AR94-AS94)*100,"") -> -0.72463768 | AU94: =IF(G94>0,I94/G94*1000,"") -> 20.787746 | AV94: =IF(G94>0,H94/G94*10000,"") -> 10.940919 | AW94: =IF(G94>0,W94/G94*10000,"") -> 43.763676 | AX94: =IF(I94>0,K94/I94*100,"") -> 15.789474 | AY94: =IF(AQ94>=100,"ok",IF(AQ94>0,"effectif faible (<100)","aucune association")) -> effectif faible (<100)
A95: 95483 | B95: Le Perchay | C95: Pontoise | D95: imputé (commune voisine la plus proche) | E95: CC Vexin Centre | F95: Rural à habitat dispersé | G95: 504 | H95: 0 | I95: 0 | J95: 0 | K95: 0 | L95: 0 | M95: 0 | N95: 0 | O95: 0 | P95: 0 | Q95: 0 | R95: 0 | S95: 0 | T95: 0 | U95: 0 | V95: 0 | W95: 2 | X95: 0 | Y95: 0 | Z95: 0 | AA95: 0 | AB95: 0 | AC95: 0 | AD95: 0 | AE95: 0 | AF95: 0 | AG95: 0 | AH95: 0 | AI95: 0 | AJ95: 0 | AK95: 0 | AL95: 0 | AM95: 0 | AN95: 0 | AO95: 0 | AP95: 0 | AQ95: =I95+J95 -> 0 | AR95: =IF(AQ95>0,I95/AQ95,"") | AS95: =IF((P95+Q95)>0,P95/(P95+Q95),"") | AT95: =IF(AND(ISNUMBER(AR95),ISNUMBER(AS95)),(AR95-AS95)*100,"") | AU95: =IF(G95>0,I95/G95*1000,"") -> 0 | AV95: =IF(G95>0,H95/G95*10000,"") -> 0 | AW95: =IF(G95>0,W95/G95*10000,"") -> 39.68254 | AX95: =IF(I95>0,K95/I95*100,"") | AY95: =IF(AQ95>=100,"ok",IF(AQ95>0,"effectif faible (<100)","aucune association")) -> aucune association
A96: 95491 | B96: Le Plessis-Bouchard | C96: Domont | D96: liste subventions 2025 | E96: CA Val Parisis | F96: Grands centres urbains | G96: 8518 | H96: 6 | I96: 1003 | J96: 606 | K96: 103 | L96: 21 | M96: 0 | N96: 2 | O96: 8 | P96: 999 | Q96: 692 | R96: 1 | S96: 96 | T96: 2 | U96: 6 | V96: 1 | W96: 11 | X96: 4 | Y96: 0 | Z96: 1 | AA96: 0 | AB96: 1 | AC96: 0 | AD96: 0 | AE96: 6 | AF96: 6 | AG96: 7 | AH96: 8 | AI96: 8 | AJ96: 533 | AK96: 1083 | AL96: 1413 | AM96: 1521 | AN96: 1650 | AO96: 1691 | AP96: 1609 | AQ96: =I96+J96 -> 1609 | AR96: =IF(AQ96>0,I96/AQ96,"") -> 0.62336855 | AS96: =IF((P96+Q96)>0,P96/(P96+Q96),"") -> 0.59077469 | AT96: =IF(AND(ISNUMBER(AR96),ISNUMBER(AS96)),(AR96-AS96)*100,"") -> 3.2593862 | AU96: =IF(G96>0,I96/G96*1000,"") -> 117.75065 | AV96: =IF(G96>0,H96/G96*10000,"") -> 7.043907 | AW96: =IF(G96>0,W96/G96*10000,"") -> 12.91383 | AX96: =IF(I96>0,K96/I96*100,"") -> 10.269192 | AY96: =IF(AQ96>=100,"ok",IF(AQ96>0,"effectif faible (<100)","aucune association")) -> ok
A97: 95492 | B97: Le Plessis-Gassot | C97: Villiers-le-Bel | D97: imputé (commune voisine la plus proche) | E97: CA Roissy Pays de France | G97: 102 | H97: 0 | I97: 0 | J97: 0 | K97: 0 | L97: 0 | M97: 0 | N97: 0 | O97: 0 | P97: 0 | Q97: 0 | R97: 0 | S97: 0 | T97: 0 | U97: 0 | V97: 0 | W97: 0 | X97: 0 | Y97: 0 | Z97: 0 | AA97: 0 | AB97: 0 | AC97: 0 | AD97: 0 | AE97: 0 | AF97: 0 | AG97: 0 | AH97: 0 | AI97: 0 | AJ97: 0 | AK97: 0 | AL97: 0 | AM97: 0 | AN97: 0 | AO97: 0 | AP97: 0 | AQ97: =I97+J97 -> 0 | AR97: =IF(AQ97>0,I97/AQ97,"") | AS97: =IF((P97+Q97)>0,P97/(P97+Q97),"") | AT97: =IF(AND(ISNUMBER(AR97),ISNUMBER(AS97)),(AR97-AS97)*100,"") | AU97: =IF(G97>0,I97/G97*1000,"") -> 0 | AV97: =IF(G97>0,H97/G97*10000,"") -> 0 | AW97: =IF(G97>0,W97/G97*10000,"") -> 0 | AX97: =IF(I97>0,K97/I97*100,"") | AY97: =IF(AQ97>=100,"ok",IF(AQ97>0,"effectif faible (<100)","aucune association")) -> aucune association
A98: 95493 | B98: Le Plessis-Luzarches | C98: Fosses | D98: imputé (commune voisine la plus proche) | E98: CC Carnelle Pays-de-France | G98: 152 | H98: 1 | I98: 22 | J98: 83 | K98: 7 | L98: 0 | M98: 0 | N98: 0 | O98: 1 | P98: 108 | Q98: 300 | R98: 0 | S98: 0 | T98: 0 | U98: 0 | V98: 0 | W98: 0 | X98: 0 | Y98: 0 | Z98: 0 | AA98: 0 | AB98: 0 | AC98: 0 | AD98: 0 | AE98: 1 | AF98: 1 | AG98: 1 | AH98: 1 | AI98: 1 | AJ98: 550 | AK98: 620 | AL98: 413 | AM98: 414 | AN98: 630 | AO98: 408 | AP98: 105 | AQ98: =I98+J98 -> 105 | AR98: =IF(AQ98>0,I98/AQ98,"") -> 0.20952381 | AS98: =IF((P98+Q98)>0,P98/(P98+Q98),"") -> 0.26470588 | AT98: =IF(AND(ISNUMBER(AR98),ISNUMBER(AS98)),(AR98-AS98)*100,"") -> -5.5182073 | AU98: =IF(G98>0,I98/G98*1000,"") -> 144.73684 | AV98: =IF(G98>0,H98/G98*10000,"") -> 65.789474 | AW98: =IF(G98>0,W98/G98*10000,"") -> 0 | AX98: =IF(I98>0,K98/I98*100,"") -> 31.818182 | AY98: =IF(AQ98>=100,"ok",IF(AQ98>0,"effectif faible (<100)","aucune association")) -> ok
A99: 95612 | B99: Le Thillay | C99: Villiers-le-Bel | D99: liste subventions 2025 | E99: CA Roissy Pays de France | F99: Ceintures urbaines | G99: 4560 | H99: 2 | I99: 52 | J99: 65 | K99: 73 | L99: 0 | M99: 0 | N99: 0 | O99: 2 | P99: 56 | Q99: 71 | R99: 0 | S99: 0 | T99: 0 | U99: 2 | V99: 0 | W99: 4 | X99: 0 | Y99: 0 | Z99: 0 | AA99: 0 | AB99: 0 | AC99: 0 | AD99: 0 | AE99: 0 | AF99: 1 | AG99: 1 | AH99: 1 | AI99: 2 | AJ99: 0 | AK99: 38 | AL99: 32 | AM99: 40 | AN99: 38 | AO99: 127 | AP99: 117 | AQ99: =I99+J99 -> 117 | AR99: =IF(AQ99>0,I99/AQ99,"") -> 0.44444444 | AS99: =IF((P99+Q99)>0,P99/(P99+Q99),"") -> 0.44094488 | AT99: =IF(AND(ISNUMBER(AR99),ISNUMBER(AS99)),(AR99-AS99)*100,"") -> 0.34995626 | AU99: =IF(G99>0,I99/G99*1000,"") -> 11.403509 | AV99: =IF(G99>0,H99/G99*10000,"") -> 4.3859649 | AW99: =IF(G99>0,W99/G99*10000,"") -> 8.7719298 | AX99: =IF(I99>0,K99/I99*100,"") -> 140.38462 | AY99: =IF(AQ99>=100,"ok",IF(AQ99>0,"effectif faible (<100)","aucune association")) -> ok
A100: 95341 | B100: Livilliers | C100: Pontoise | D100: imputé (commune voisine la plus proche) | E100: CC Sausseron Impressionnistes | F100: Rural à habitat dispersé | G100: 389 | H100: 0 | I100: 0 | J100: 0 | K100: 0 | L100: 0 | M100: 0 | N100: 0 | O100: 0 | P100: 0 | Q100: 0 | R100: 0 | S100: 0 | T100: 0 | U100: 0 | V100: 0 | W100: 2 | X100: 0 | Y100: 0 | Z100: 0 | AA100: 0 | AB100: 0 | AC100: 0 | AD100: 0 | AE100: 0 | AF100: 0 | AG100: 0 | AH100: 0 | AI100: 0 | AJ100: 0 | AK100: 0 | AL100: 0 | AM100: 0 | AN100: 0 | AO100: 0 | AP100: 0 | AQ100: =I100+J100 -> 0 | AR100: =IF(AQ100>0,I100/AQ100,"") | AS100: =IF((P100+Q100)>0,P100/(P100+Q100),"") | AT100: =IF(AND(ISNUMBER(AR100),ISNUMBER(AS100)),(AR100-AS100)*100,"") | AU100: =IF(G100>0,I100/G100*1000,"") -> 0 | AV100: =IF(G100>0,H100/G100*10000,"") -> 0 | AW100: =IF(G100>0,W100/G100*10000,"") -> 51.413882 | AX100: =IF(I100>0,K100/I100*100,"") | AY100: =IF(AQ100>=100,"ok",IF(AQ100>0,"effectif faible (<100)","aucune association")) -> aucune association
A101: 95348 | B101: Longuesse | C101: Vauréal | D101: imputé (commune voisine la plus proche) | E101: CC Vexin Centre | F101: Bourgs ruraux | G101: 496 | H101: 0 | I101: 0 | J101: 0 | K101: 0 | L101: 0 | M101: 0 | N101: 0 | O101: 0 | P101: 0 | Q101: 0 | R101: 0 | S101: 0 | T101: 0 | U101: 0 | V101: 0 | W101: 3 | X101: 0 | Y101: 0 | Z101: 0 | AA101: 0 | AB101: 0 | AC101: 0 | AD101: 0 | AE101: 0 | AF101: 0 | AG101: 0 | AH101: 0 | AI101: 0 | AJ101: 0 | AK101: 0 | AL101: 0 | AM101: 0 | AN101: 0 | AO101: 0 | AP101: 0 | AQ101: =I101+J101 -> 0 | AR101: =IF(AQ101>0,I101/AQ101,"") | AS101: =IF((P101+Q101)>0,P101/(P101+Q101),"") | AT101: =IF(AND(ISNUMBER(AR101),ISNUMBER(AS101)),(AR101-AS101)*100,"") | AU101: =IF(G101>0,I101/G101*1000,"") -> 0 | AV101: =IF(G101>0,H101/G101*10000,"") -> 0 | AW101: =IF(G101>0,W101/G101*10000,"") -> 60.483871 | AX101: =IF(I101>0,K101/I101*100,"") | AY101: =IF(AQ101>=100,"ok",IF(AQ101>0,"effectif faible (<100)","aucune association")) -> aucune association
A102: 95351 | B102: Louvres | C102: Goussainville | D102: liste subventions 2025 | E102: CA Roissy Pays de France | F102: Centres urbains intermédiaires | G102: 12560 | H102: 3 | I102: 446 | J102: 184 | K102: 44 | L102: 2 | M102: 1 | N102: 1 | O102: 4 | P102: 427 | Q102: 594 | R102: 1 | S102: 160 | T102: 4 | U102: 3 | V102: 1 | W102: 15 | X102: 0 | Y102: 1 | Z102: 0 | AA102: 0 | AB102: 0 | AC102: 1 | AD102: 0 | AE102: 3 | AF102: 3 | AG102: 3 | AH102: 3 | AI102: 3 | AJ102: 860 | AK102: 753 | AL102: 1037 | AM102: 1137 | AN102: 547 | AO102: 1021 | AP102: 630 | AQ102: =I102+J102 -> 630 | AR102: =IF(AQ102>0,I102/AQ102,"") -> 0.70793651 | AS102: =IF((P102+Q102)>0,P102/(P102+Q102),"") -> 0.41821743 | AT102: =IF(AND(ISNUMBER(AR102),ISNUMBER(AS102)),(AR102-AS102)*100,"") -> 28.971907 | AU102: =IF(G102>0,I102/G102*1000,"") -> 35.509554 | AV102: =IF(G102>0,H102/G102*10000,"") -> 2.388535 | AW102: =IF(G102>0,W102/G102*10000,"") -> 11.942675 | AX102: =IF(I102>0,K102/I102*100,"") -> 9.8654709 | AY102: =IF(AQ102>=100,"ok",IF(AQ102>0,"effectif faible (<100)","aucune association")) -> ok
A103: 95352 | B103: Luzarches | C103: Fosses | D103: liste subventions 2025 | E103: CC Carnelle Pays-de-France | F103: Petites villes | G103: 5008 | H103: 3 | I103: 236 | J103: 407 | K103: 60 | L103: 1 | M103: 0 | N103: 1 | O103: 4 | P103: 268 | Q103: 382 | R103: 2 | S103: 269 | T103: 9 | U103: 4 | V103: 2 | W103: 13 | X103: 0 | Y103: 0 | Z103: 1 | AA103: 0 | AB103: 0 | AC103: 1 | AD103: 0 | AE103: 3 | AF103: 3 | AG103: 3 | AH103: 4 | AI103: 4 | AJ103: 330 | AK103: 367 | AL103: 370 | AM103: 441 | AN103: 457 | AO103: 650 | AP103: 643 | AQ103: =I103+J103 -> 643 | AR103: =IF(AQ103>0,I103/AQ103,"") -> 0.36702955 | AS103: =IF((P103+Q103)>0,P103/(P103+Q103),"") -> 0.41230769 | AT103: =IF(AND(ISNUMBER(AR103),ISNUMBER(AS103)),(AR103-AS103)*100,"") -> -4.5278143 | AU103: =IF(G103>0,I103/G103*1000,"") -> 47.124601 | AV103: =IF(G103>0,H103/G103*10000,"") -> 5.9904153 | AW103: =IF(G103>0,W103/G103*10000,"") -> 25.958466 | AX103: =IF(I103>0,K103/I103*100,"") -> 25.423729 | AY103: =IF(AQ103>=100,"ok",IF(AQ103>0,"effectif faible (<100)","aucune association")) -> ok
A104: 95353 | B104: Maffliers | C104: Fosses | D104: liste subventions 2025 | E104: CC Carnelle Pays-de-France | F104: Ceintures urbaines | G104: 1856 | H104: 1 | I104: 301 | J104: 48 | K104: 12 | L104: 9 | M104: 0 | N104: 1 | O104: 1 | P104: 276 | Q104: 66 | R104: 0 | S104: 0 | T104: 0 | U104: 1 | V104: 0 | W104: 4 | X104: 1 | Y104: 0 | Z104: 0 | AA104: 0 | AB104: 0 | AC104: 0 | AD104: 0 | AE104: 1 | AF104: 1 | AG104: 1 | AH104: 1 | AI104: 1 | AJ104: 222 | AK104: 253 | AL104: 199 | AM104: 191 | AN104: 241 | AO104: 342 | AP104: 349 | AQ104: =I104+J104 -> 349 | AR104: =IF(AQ104>0,I104/AQ104,"") -> 0.86246418 | AS104: =IF((P104+Q104)>0,P104/(P104+Q104),"") -> 0.80701754 | AT104: =IF(AND(ISNUMBER(AR104),ISNUMBER(AS104)),(AR104-AS104)*100,"") -> 5.544664 | AU104: =IF(G104>0,I104/G104*1000,"") -> 162.17672 | AV104: =IF(G104>0,H104/G104*10000,"") -> 5.387931 | AW104: =IF(G104>0,W104/G104*10000,"") -> 21.551724 | AX104: =IF(I104>0,K104/I104*100,"") -> 3.986711 | AY104: =IF(AQ104>=100,"ok",IF(AQ104>0,"effectif faible (<100)","aucune association")) -> ok
A105: 95355 | B105: Magny-en-Vexin | C105: Vauréal | D105: liste subventions 2025 | E105: CC du Vexin-Val de Seine | F105: Petites villes | G105: 5779 | H105: 2 | I105: 152 | J105: 37 | K105: 12 | L105: 4 | M105: 1 | N105: 1 | O105: 2 | P105: 142 | Q105: 31 | R105: 0 | S105: 0 | T105: 0 | U105: 2 | V105: 0 | W105: 14 | X105: 5 | Y105: 0 | Z105: 0 | AA105: 0 | AB105: 0 | AC105: 0 | AD105: 0 | AE105: 1 | AF105: 1 | AG105: 1 | AH105: 1 | AI105: 2 | AJ105: 29 | AK105: 37 | AL105: 20 | AM105: 33 | AN105: 157 | AO105: 173 | AP105: 189 | AQ105: =I105+J105 -> 189 | AR105: =IF(AQ105>0,I105/AQ105,"") -> 0.8042328 | AS105: =IF((P105+Q105)>0,P105/(P105+Q105),"") -> 0.82080925 | AT105: =IF(AND(ISNUMBER(AR105),ISNUMBER(AS105)),(AR105-AS105)*100,"") -> -1.6576444 | AU105: =IF(G105>0,I105/G105*1000,"") -> 26.302128 | AV105: =IF(G105>0,H105/G105*10000,"") -> 3.4608064 | AW105: =IF(G105>0,W105/G105*10000,"") -> 24.225645 | AX105: =IF(I105>0,K105/I105*100,"") -> 7.8947368 | AY105: =IF(AQ105>=100,"ok",IF(AQ105>0,"effectif faible (<100)","aucune association")) -> ok
A106: 95365 | B106: Mareil-en-France | C106: Fosses | D106: imputé (commune voisine la plus proche) | E106: CC Carnelle Pays-de-France | F106: Bourgs ruraux | G106: 734 | H106: 0 | I106: 0 | J106: 0 | K106: 0 | L106: 0 | M106: 0 | N106: 0 | O106: 0 | P106: 0 | Q106: 0 | R106: 0 | S106: 0 | T106: 0 | U106: 0 | V106: 0 | W106: 2 | X106: 0 | Y106: 0 | Z106: 0 | AA106: 0 | AB106: 0 | AC106: 0 | AD106: 0 | AE106: 0 | AF106: 0 | AG106: 0 | AH106: 0 | AI106: 0 | AJ106: 0 | AK106: 0 | AL106: 0 | AM106: 0 | AN106: 0 | AO106: 0 | AP106: 0 | AQ106: =I106+J106 -> 0 | AR106: =IF(AQ106>0,I106/AQ106,"") | AS106: =IF((P106+Q106)>0,P106/(P106+Q106),"") | AT106: =IF(AND(ISNUMBER(AR106),ISNUMBER(AS106)),(AR106-AS106)*100,"") | AU106: =IF(G106>0,I106/G106*1000,"") -> 0 | AV106: =IF(G106>0,H106/G106*10000,"") -> 0 | AW106: =IF(G106>0,W106/G106*10000,"") -> 27.247956 | AX106: =IF(I106>0,K106/I106*100,"") | AY106: =IF(AQ106>=100,"ok",IF(AQ106>0,"effectif faible (<100)","aucune association")) -> aucune association
A107: 95369 | B107: Margency | C107: Montmorency | D107: liste subventions 2025 | E107: CA Plaine Vallée | F107: Grands centres urbains | G107: 3012 | H107: 2 | I107: 126 | J107: 283 | K107: 107 | L107: 1 | M107: 0 | N107: 0 | O107: 2 | P107: 127 | Q107: 276 | R107: 0 | S107: 0 | T107: 0 | U107: 2 | V107: 0 | W107: 4 | X107: 1 | Y107: 0 | Z107: 0 | AA107: 0 | AB107: 0 | AC107: 0 | AD107: 0 | AE107: 2 | AF107: 2 | AG107: 2 | AH107: 2 | AI107: 2 | AJ107: 189 | AK107: 193 | AL107: 202 | AM107: 226 | AN107: 282 | AO107: 403 | AP107: 409 | AQ107: =I107+J107 -> 409 | AR107: =IF(AQ107>0,I107/AQ107,"") -> 0.30806846 | AS107: =IF((P107+Q107)>0,P107/(P107+Q107),"") -> 0.31513648 | AT107: =IF(AND(ISNUMBER(AR107),ISNUMBER(AS107)),(AR107-AS107)*100,"") -> -0.70680168 | AU107: =IF(G107>0,I107/G107*1000,"") -> 41.832669 | AV107: =IF(G107>0,H107/G107*10000,"") -> 6.6401062 | AW107: =IF(G107>0,W107/G107*10000,"") -> 13.280212 | AX107: =IF(I107>0,K107/I107*100,"") -> 84.920635 | AY107: =IF(AQ107>=100,"ok",IF(AQ107>0,"effectif faible (<100)","aucune association")) -> ok
A108: 95370 | B108: Marines | C108: Pontoise | D108: liste subventions 2025 | E108: CC Vexin Centre | F108: Bourgs ruraux | G108: 3594 | H108: 8 | I108: 239 | J108: 693 | K108: 67 | L108: 4 | M108: 3 | N108: 0 | O108: 9 | P108: 210 | Q108: 966 | R108: 0 | S108: 0 | T108: 0 | U108: 9 | V108: 0 | W108: 8 | X108: 2 | Y108: 0 | Z108: 0 | AA108: 0 | AB108: 0 | AC108: 0 | AD108: 0 | AE108: 10 | AF108: 9 | AG108: 8 | AH108: 8 | AI108: 8 | AJ108: 906 | AK108: 815 | AL108: 674 | AM108: 715 | AN108: 770 | AO108: 1176 | AP108: 932 | AQ108: =I108+J108 -> 932 | AR108: =IF(AQ108>0,I108/AQ108,"") -> 0.25643777 | AS108: =IF((P108+Q108)>0,P108/(P108+Q108),"") -> 0.17857143 | AT108: =IF(AND(ISNUMBER(AR108),ISNUMBER(AS108)),(AR108-AS108)*100,"") -> 7.786634 | AU108: =IF(G108>0,I108/G108*1000,"") -> 66.499722 | AV108: =IF(G108>0,H108/G108*10000,"") -> 22.259321 | AW108: =IF(G108>0,W108/G108*10000,"") -> 22.259321 | AX108: =IF(I108>0,K108/I108*100,"") -> 28.033473 | AY108: =IF(AQ108>=100,"ok",IF(AQ108>0,"effectif faible (<100)","aucune association")) -> ok
A109: 95371 | B109: Marly-la-Ville | C109: Goussainville | D109: liste subventions 2025 | E109: CA Roissy Pays de France | F109: Centres urbains intermédiaires | G109: 6022 | H109: 5 | I109: 171 | J109: 642 | K109: 96 | L109: 1 | M109: 1 | N109: 1 | O109: 3 | P109: 140 | Q109: 568 | R109: 0 | S109: 0 | T109: 0 | U109: 5 | V109: 0 | W109: 11 | X109: 4 | Y109: 0 | Z109: 0 | AA109: 1 | AB109: 0 | AC109: 0 | AD109: 0 | AE109: 5 | AF109: 3 | AG109: 4 | AH109: 2 | AI109: 2 | AJ109: 648 | AK109: 467 | AL109: 424 | AM109: 387 | AN109: 559 | AO109: 708 | AP109: 813 | AQ109: =I109+J109 -> 813 | AR109: =IF(AQ109>0,I109/AQ109,"") -> 0.2103321 | AS109: =IF((P109+Q109)>0,P109/(P109+Q109),"") -> 0.19774011 | AT109: =IF(AND(ISNUMBER(AR109),ISNUMBER(AS109)),(AR109-AS109)*100,"") -> 1.259199 | AU109: =IF(G109>0,I109/G109*1000,"") -> 28.395882 | AV109: =IF(G109>0,H109/G109*10000,"") -> 8.3028894 | AW109: =IF(G109>0,W109/G109*10000,"") -> 18.266357 | AX109: =IF(I109>0,K109/I109*100,"") -> 56.140351 | AY109: =IF(AQ109>=100,"ok",IF(AQ109>0,"effectif faible (<100)","aucune association")) -> ok
A110: 95379 | B110: Maudétour-en-Vexin | C110: Vauréal | D110: imputé (commune voisine la plus proche) | E110: CC du Vexin-Val de Seine | F110: Rural à habitat dispersé | G110: 208 | H110: 1 | I110: 65 | J110: 147 | K110: 2 | L110: 1 | M110: 0 | N110: 0 | O110: 0 | P110: 0 | Q110: 0 | R110: 0 | S110: 0 | T110: 0 | U110: 0 | V110: 0 | W110: 1 | X110: 0 | Y110: 0 | Z110: 0 | AA110: 0 | AB110: 0 | AC110: 0 | AD110: 0 | AE110: 0 | AF110: 0 | AG110: 0 | AH110: 0 | AI110: 0 | AJ110: 0 | AK110: 0 | AL110: 0 | AM110: 0 | AN110: 0 | AO110: 0 | AP110: 212 | AQ110: =I110+J110 -> 212 | AR110: =IF(AQ110>0,I110/AQ110,"") -> 0.30660377 | AS110: =IF((P110+Q110)>0,P110/(P110+Q110),"") | AT110: =IF(AND(ISNUMBER(AR110),ISNUMBER(AS110)),(AR110-AS110)*100,"") | AU110: =IF(G110>0,I110/G110*1000,"") -> 312.5 | AV110: =IF(G110>0,H110/G110*10000,"") -> 48.076923 | AW110: =IF(G110>0,W110/G110*10000,"") -> 48.076923 | AX110: =IF(I110>0,K110/I110*100,"") -> 3.0769231 | AY110: =IF(AQ110>=100,"ok",IF(AQ110>0,"effectif faible (<100)","aucune association")) -> ok
... A121: 95436 | B121: Mours | C121: L'Isle-Adam | D121: imputé (commune voisine la plus proche) | E121: CC du Haut Val d'Oise | F121: Ceintures urbaines | G121: 1693 | H121: 0 | I121: 0 | J121: 0 | K121: 0 | L121: 0 | M121: 0 | N121: 0 | O121: 0 | P121: 0 | Q121: 0 | R121: 0 | S121: 0 | T121: 0 | U121: 0 | V121: 0 | W121: 5 | X121: 0 | Y121: 0 | Z121: 0 | AA121: 0 | AB121: 0 | AC121: 0 | AD121: 0 | AE121: 1 | AF121: 1 | AG121: 1 | AH121: 1 | AI121: 1 | AJ121: 10 | AK121: 8 | AL121: 10 | AM121: 10 | AN121: 9 | AO121: 0 | AP121: 0 | AQ121: =I121+J121 -> 0 | AR121: =IF(AQ121>0,I121/AQ121,"") | AS121: =IF((P121+Q121)>0,P121/(P121+Q121),"") | AT121: =IF(AND(ISNUMBER(AR121),ISNUMBER(AS121)),(AR121-AS121)*100,"") | AU121: =IF(G121>0,I121/G121*1000,"") -> 0 | AV121: =IF(G121>0,H121/G121*10000,"") -> 0 | AW121: =IF(G121>0,W121/G121*10000,"") -> 29.533373 | AX121: =IF(I121>0,K121/I121*100,"") | AY121: =IF(AQ121>=100,"ok",IF(AQ121>0,"effectif faible (<100)","aucune association")) -> aucune association
A122: 95438 | B122: Moussy | C122: Pontoise | D122: imputé (commune voisine la plus proche) | E122: CC Vexin Centre | G122: 108 | H122: 0 | I122: 0 | J122: 0 | K122: 0 | L122: 0 | M122: 0 | N122: 0 | O122: 0 | P122: 0 | Q122: 0 | R122: 0 | S122: 0 | T122: 0 | U122: 0 | V122: 0 | W122: 0 | X122: 0 | Y122: 0 | Z122: 0 | AA122: 0 | AB122: 0 | AC122: 0 | AD122: 0 | AE122: 0 | AF122: 0 | AG122: 0 | AH122: 0 | AI122: 0 | AJ122: 0 | AK122: 0 | AL122: 0 | AM122: 0 | AN122: 0 | AO122: 0 | AP122: 0 | AQ122: =I122+J122 -> 0 | AR122: =IF(AQ122>0,I122/AQ122,"") | AS122: =IF((P122+Q122)>0,P122/(P122+Q122),"") | AT122: =IF(AND(ISNUMBER(AR122),ISNUMBER(AS122)),(AR122-AS122)*100,"") | AU122: =IF(G122>0,I122/G122*1000,"") -> 0 | AV122: =IF(G122>0,H122/G122*10000,"") -> 0 | AW122: =IF(G122>0,W122/G122*10000,"") -> 0 | AX122: =IF(I122>0,K122/I122*100,"") | AY122: =IF(AQ122>=100,"ok",IF(AQ122>0,"effectif faible (<100)","aucune association")) -> aucune association
A123: 95392 | B123: Mériel | C123: Saint-Ouen-l'Aumône | D123: liste subventions 2025 | E123: CC de la Vallée de l'Oise et des Trois Forêts | F123: Ceintures urbaines | G123: 5347 | H123: 4 | I123: 450 | J123: 503 | K123: 75 | L123: 12 | M123: 0 | N123: 1 | O123: 4 | P123: 462 | Q123: 509 | R123: 1 | S123: 84 | T123: 4 | U123: 4 | V123: 1 | W123: 13 | X123: 4 | Y123: 0 | Z123: 0 | AA123: 0 | AB123: 0 | AC123: 0 | AD123: 0 | AE123: 4 | AF123: 4 | AG123: 4 | AH123: 4 | AI123: 4 | AJ123: 930 | AK123: 948 | AL123: 785 | AM123: 817 | AN123: 991 | AO123: 971 | AP123: 953 | AQ123: =I123+J123 -> 953 | AR123: =IF(AQ123>0,I123/AQ123,"") -> 0.47219307 | AS123: =IF((P123+Q123)>0,P123/(P123+Q123),"") -> 0.47579815 | AT123: =IF(AND(ISNUMBER(AR123),ISNUMBER(AS123)),(AR123-AS123)*100,"") -> -0.36050717 | AU123: =IF(G123>0,I123/G123*1000,"") -> 84.159342 | AV123: =IF(G123>0,H123/G123*10000,"") -> 7.4808304 | AW123: =IF(G123>0,W123/G123*10000,"") -> 24.312699 | AX123: =IF(I123>0,K123/I123*100,"") -> 16.666667 | AY123: =IF(AQ123>=100,"ok",IF(AQ123>0,"effectif faible (<100)","aucune association")) -> ok
A124: 95394 | B124: Méry-sur-Oise | C124: Saint-Ouen-l'Aumône | D124: liste subventions 2025 | E124: CC de la Vallée de l'Oise et des Trois Forêts | F124: Grands centres urbains | G124: 9983 | H124: 7 | I124: 1742 | J124: 3393 | K124: 133 | L124: 9 | M124: 1 | N124: 0 | O124: 8 | P124: 1809 | Q124: 3452 | R124: 1 | S124: 78 | T124: 4 | U124: 8 | V124: 1 | W124: 14 | X124: 1 | Y124: 0 | Z124: 0 | AA124: 0 | AB124: 0 | AC124: 0 | AD124: 0 | AE124: 5 | AF124: 7 | AG124: 8 | AH124: 6 | AI124: 6 | AJ124: 1313 | AK124: 4882 | AL124: 3795 | AM124: 4400 | AN124: 4452 | AO124: 5261 | AP124: 5135 | AQ124: =I124+J124 -> 5135 | AR124: =IF(AQ124>0,I124/AQ124,"") -> 0.33924051 | AS124: =IF((P124+Q124)>0,P124/(P124+Q124),"") -> 0.34385098 | AT124: =IF(AND(ISNUMBER(AR124),ISNUMBER(AS124)),(AR124-AS124)*100,"") -> -0.46104726 | AU124: =IF(G124>0,I124/G124*1000,"") -> 174.49664 | AV124: =IF(G124>0,H124/G124*10000,"") -> 7.0119203 | AW124: =IF(G124>0,W124/G124*10000,"") -> 14.023841 | AX124: =IF(I124>0,K124/I124*100,"") -> 7.6349024 | AY124: =IF(AQ124>=100,"ok",IF(AQ124>0,"effectif faible (<100)","aucune association")) -> ok
A125: 95445 | B125: Nerville-la-Forêt | C125: L'Isle-Adam | D125: liste subventions 2025 | E125: CC de la Vallée de l'Oise et des Trois Forêts | F125: Rural à habitat dispersé | G125: 756 | H125: 1 | I125: 30 | J125: 1 | K125: 0 | L125: 0 | M125: 0 | N125: 1 | O125: 1 | P125: 33 | Q125: 1 | R125: 0 | S125: 0 | T125: 0 | U125: 1 | V125: 0 | W125: 2 | X125: 0 | Y125: 0 | Z125: 0 | AA125: 0 | AB125: 0 | AC125: 0 | AD125: 0 | AE125: 1 | AF125: 1 | AG125: 1 | AH125: 0 | AI125: 1 | AJ125: 12 | AK125: 33 | AL125: 35 | AM125: 0 | AN125: 33 | AO125: 34 | AP125: 31 | AQ125: =I125+J125 -> 31 | AR125: =IF(AQ125>0,I125/AQ125,"") -> 0.96774194 | AS125: =IF((P125+Q125)>0,P125/(P125+Q125),"") -> 0.97058824 | AT125: =IF(AND(ISNUMBER(AR125),ISNUMBER(AS125)),(AR125-AS125)*100,"") -> -0.28462998 | AU125: =IF(G125>0,I125/G125*1000,"") -> 39.68254 | AV125: =IF(G125>0,H125/G125*10000,"") -> 13.227513 | AW125: =IF(G125>0,W125/G125*10000,"") -> 26.455026 | AX125: =IF(I125>0,K125/I125*100,"") -> 0 | AY125: =IF(AQ125>=100,"ok",IF(AQ125>0,"effectif faible (<100)","aucune association")) -> effectif faible (<100)
A126: 95446 | B126: Nesles-la-Vallée | C126: Saint-Ouen-l'Aumône | D126: liste subventions 2025 | E126: CC Sausseron Impressionnistes | F126: Ceintures urbaines | G126: 1842 | H126: 2 | I126: 51 | J126: 101 | K126: 21 | L126: 3 | M126: 0 | N126: 0 | O126: 2 | P126: 55 | Q126: 102 | R126: 0 | S126: 0 | T126: 0 | U126: 2 | V126: 0 | W126: 7 | X126: 1 | Y126: 0 | Z126: 0 | AA126: 0 | AB126: 0 | AC126: 0 | AD126: 0 | AE126: 2 | AF126: 2 | AG126: 2 | AH126: 1 | AI126: 2 | AJ126: 239 | AK126: 192 | AL126: 143 | AM126: 128 | AN126: 133 | AO126: 157 | AP126: 152 | AQ126: =I126+J126 -> 152 | AR126: =IF(AQ126>0,I126/AQ126,"") -> 0.33552632 | AS126: =IF((P126+Q126)>0,P126/(P126+Q126),"") -> 0.35031847 | AT126: =IF(AND(ISNUMBER(AR126),ISNUMBER(AS126)),(AR126-AS126)*100,"") -> -1.4792156 | AU126: =IF(G126>0,I126/G126*1000,"") -> 27.687296 | AV126: =IF(G126>0,H126/G126*10000,"") -> 10.857763 | AW126: =IF(G126>0,W126/G126*10000,"") -> 38.002172 | AX126: =IF(I126>0,K126/I126*100,"") -> 41.176471 | AY126: =IF(AQ126>=100,"ok",IF(AQ126>0,"effectif faible (<100)","aucune association")) -> ok
A127: 95447 | B127: Neuilly-en-Vexin | C127: Pontoise | D127: imputé (commune voisine la plus proche) | E127: CC Vexin Centre | F127: Rural à habitat dispersé | G127: 240 | H127: 0 | I127: 0 | J127: 0 | K127: 0 | L127: 0 | M127: 0 | N127: 0 | O127: 0 | P127: 0 | Q127: 0 | R127: 0 | S127: 0 | T127: 0 | U127: 0 | V127: 0 | W127: 1 | X127: 0 | Y127: 0 | Z127: 0 | AA127: 0 | AB127: 0 | AC127: 0 | AD127: 0 | AE127: 0 | AF127: 0 | AG127: 0 | AH127: 0 | AI127: 0 | AJ127: 0 | AK127: 0 | AL127: 0 | AM127: 0 | AN127: 0 | AO127: 0 | AP127: 0 | AQ127: =I127+J127 -> 0 | AR127: =IF(AQ127>0,I127/AQ127,"") | AS127: =IF((P127+Q127)>0,P127/(P127+Q127),"") | AT127: =IF(AND(ISNUMBER(AR127),ISNUMBER(AS127)),(AR127-AS127)*100,"") | AU127: =IF(G127>0,I127/G127*1000,"") -> 0 | AV127: =IF(G127>0,H127/G127*10000,"") -> 0 | AW127: =IF(G127>0,W127/G127*10000,"") -> 41.666667 | AX127: =IF(I127>0,K127/I127*100,"") | AY127: =IF(AQ127>=100,"ok",IF(AQ127>0,"effectif faible (<100)","aucune association")) -> aucune association
A128: 95450 | B128: Neuville-sur-Oise | C128: Cergy (1-2) | D128: liste subventions 2025 | E128: CA de Cergy-Pontoise | F128: Grands centres urbains | G128: 2058 | H128: 2 | I128: 27 | J128: 361 | K128: 48 | L128: 1 | M128: 1 | N128: 0 | O128: 2 | P128: 32 | Q128: 346 | R128: 0 | S128: 0 | T128: 0 | U128: 3 | V128: 0 | W128: 3 | X128: 0 | Y128: 0 | Z128: 1 | AA128: 3 | AB128: 0 | AC128: 0 | AD128: 0 | AE128: 3 | AF128: 4 | AG128: 4 | AH128: 2 | AI128: 3 | AJ128: 248 | AK128: 313 | AL128: 743 | AM128: 534 | AN128: 309 | AO128: 378 | AP128: 388 | AQ128: =I128+J128 -> 388 | AR128: =IF(AQ128>0,I128/AQ128,"") -> 0.069587629 | AS128: =IF((P128+Q128)>0,P128/(P128+Q128),"") -> 0.084656085 | AT128: =IF(AND(ISNUMBER(AR128),ISNUMBER(AS128)),(AR128-AS128)*100,"") -> -1.5068456 | AU128: =IF(G128>0,I128/G128*1000,"") -> 13.119534 | AV128: =IF(G128>0,H128/G128*10000,"") -> 9.718173 | AW128: =IF(G128>0,W128/G128*10000,"") -> 14.577259 | AX128: =IF(I128>0,K128/I128*100,"") -> 177.77778 | AY128: =IF(AQ128>=100,"ok",IF(AQ128>0,"effectif faible (<100)","aucune association")) -> ok
A129: 95452 | B129: Nointel | C129: L'Isle-Adam | D129: imputé (commune voisine la plus proche) | E129: CC du Haut Val d'Oise | G129: 903 | H129: 0 | I129: 0 | J129: 0 | K129: 0 | L129: 0 | M129: 0 | N129: 0 | O129: 0 | P129: 0 | Q129: 0 | R129: 0 | S129: 0 | T129: 0 | U129: 0 | V129: 0 | W129: 0 | X129: 0 | Y129: 0 | Z129: 0 | AA129: 0 | AB129: 0 | AC129: 0 | AD129: 0 | AE129: 0 | AF129: 0 | AG129: 0 | AH129: 0 | AI129: 0 | AJ129: 0 | AK129: 0 | AL129: 0 | AM129: 0 | AN129: 0 | AO129: 0 | AP129: 0 | AQ129: =I129+J129 -> 0 | AR129: =IF(AQ129>0,I129/AQ129,"") | AS129: =IF((P129+Q129)>0,P129/(P129+Q129),"") | AT129: =IF(AND(ISNUMBER(AR129),ISNUMBER(AS129)),(AR129-AS129)*100,"") | AU129: =IF(G129>0,I129/G129*1000,"") -> 0 | AV129: =IF(G129>0,H129/G129*10000,"") -> 0 | AW129: =IF(G129>0,W129/G129*10000,"") -> 0 | AX129: =IF(I129>0,K129/I129*100,"") | AY129: =IF(AQ129>=100,"ok",IF(AQ129>0,"effectif faible (<100)","aucune association")) -> aucune association
A130: 95456 | B130: Noisy-sur-Oise | C130: L'Isle-Adam | D130: imputé (commune voisine la plus proche) | E130: CC du Haut Val d'Oise | G130: 549 | H130: 0 | I130: 0 | J130: 0 | K130: 0 | L130: 0 | M130: 0 | N130: 0 | O130: 0 | P130: 0 | Q130: 0 | R130: 0 | S130: 0 | T130: 0 | U130: 0 | V130: 0 | W130: 0 | X130: 0 | Y130: 0 | Z130: 0 | AA130: 0 | AB130: 0 | AC130: 0 | AD130: 0 | AE130: 0 | AF130: 0 | AG130: 0 | AH130: 0 | AI130: 0 | AJ130: 0 | AK130: 0 | AL130: 0 | AM130: 0 | AN130: 0 | AO130: 0 | AP130: 0 | AQ130: =I130+J130 -> 0 | AR130: =IF(AQ130>0,I130/AQ130,"") | AS130: =IF((P130+Q130)>0,P130/(P130+Q130),"") | AT130: =IF(AND(ISNUMBER(AR130),ISNUMBER(AS130)),(AR130-AS130)*100,"") | AU130: =IF(G130>0,I130/G130*1000,"") -> 0 | AV130: =IF(G130>0,H130/G130*10000,"") -> 0 | AW130: =IF(G130>0,W130/G130*10000,"") -> 0 | AX130: =IF(I130>0,K130/I130*100,"") | AY130: =IF(AQ130>=100,"ok",IF(AQ130>0,"effectif faible (<100)","aucune association")) -> aucune association
A131: 95459 | B131: Nucourt | C131: Vauréal | D131: imputé (commune voisine la plus proche) | E131: CC Vexin Centre | F131: Rural à habitat dispersé | G131: 719 | H131: 0 | I131: 0 | J131: 0 | K131: 0 | L131: 0 | M131: 0 | N131: 0 | O131: 0 | P131: 0 | Q131: 0 | R131: 0 | S131: 0 | T131: 0 | U131: 0 | V131: 0 | W131: 6 | X131: 0 | Y131: 0 | Z131: 0 | AA131: 0 | AB131: 0 | AC131: 0 | AD131: 0 | AE131: 0 | AF131: 0 | AG131: 0 | AH131: 0 | AI131: 0 | AJ131: 0 | AK131: 0 | AL131: 0 | AM131: 0 | AN131: 0 | AO131: 0 | AP131: 0 | AQ131: =I131+J131 -> 0 | AR131: =IF(AQ131>0,I131/AQ131,"") | AS131: =IF((P131+Q131)>0,P131/(P131+Q131),"") | AT131: =IF(AND(ISNUMBER(AR131),ISNUMBER(AS131)),(AR131-AS131)*100,"") | AU131: =IF(G131>0,I131/G131*1000,"") -> 0 | AV131: =IF(G131>0,H131/G131*10000,"") -> 0 | AW131: =IF(G131>0,W131/G131*10000,"") -> 83.449235 | AX131: =IF(I131>0,K131/I131*100,"") | AY131: =IF(AQ131>=100,"ok",IF(AQ131>0,"effectif faible (<100)","aucune association")) -> aucune association
A132: 95462 | B132: Omerville | C132: Vauréal | D132: imputé (commune voisine la plus proche) | E132: CC du Vexin-Val de Seine | F132: Rural à habitat dispersé | G132: 327 | H132: 0 | I132: 0 | J132: 0 | K132: 0 | L132: 0 | M132: 0 | N132: 0 | O132: 0 | P132: 0 | Q132: 0 | R132: 0 | S132: 0 | T132: 0 | U132: 0 | V132: 0 | W132: 2 | X132: 0 | Y132: 0 | Z132: 0 | AA132: 0 | AB132: 0 | AC132: 0 | AD132: 0 | AE132: 0 | AF132: 0 | AG132: 0 | AH132: 0 | AI132: 0 | AJ132: 0 | AK132: 0 | AL132: 0 | AM132: 0 | AN132: 0 | AO132: 0 | AP132: 0 | AQ132: =I132+J132 -> 0 | AR132: =IF(AQ132>0,I132/AQ132,"") | AS132: =IF((P132+Q132)>0,P132/(P132+Q132),"") | AT132: =IF(AND(ISNUMBER(AR132),ISNUMBER(AS132)),(AR132-AS132)*100,"") | AU132: =IF(G132>0,I132/G132*1000,"") -> 0 | AV132: =IF(G132>0,H132/G132*10000,"") -> 0 | AW132: =IF(G132>0,W132/G132*10000,"") -> 61.16208 | AX132: =IF(I132>0,K132/I132*100,"") | AY132: =IF(AQ132>=100,"ok",IF(AQ132>0,"effectif faible (<100)","aucune association")) -> aucune association
A133: 95476 | B133: Osny | C133: Cergy (1-2) | D133: liste subventions 2025 | E133: CA de Cergy-Pontoise | F133: Grands centres urbains | G133: 17954 | H133: 6 | I133: 277 | J133: 1164 | K133: 111 | L133: 4 | M133: 2 | N133: 1 | O133: 6 | P133: 193 | Q133: 1087 | R133: 6 | S133: 1133 | T133: 35 | U133: 6 | V133: 6 | W133: 25 | X133: 8 | Y133: 0 | Z133: 0 | AA133: 0 | AB133: 0 | AC133: 1 | AD133: 0 | AE133: 6 | AF133: 7 | AG133: 7 | AH133: 8 | AI133: 6 | AJ133: 1188 | AK133: 1281 | AL133: 1137 | AM133: 1740 | AN133: 1296 | AO133: 1280 | AP133: 1441 | AQ133: =I133+J133 -> 1441 | AR133: =IF(AQ133>0,I133/AQ133,"") -> 0.19222762 | AS133: =IF((P133+Q133)>0,P133/(P133+Q133),"") -> 0.15078125 | AT133: =IF(AND(ISNUMBER(AR133),ISNUMBER(AS133)),(AR133-AS133)*100,"") -> 4.144637 | AU133: =IF(G133>0,I133/G133*1000,"") -> 15.428317 | AV133: =IF(G133>0,H133/G133*10000,"") -> 3.3418737 | AW133: =IF(G133>0,W133/G133*10000,"") -> 13.924474 | AX133: =IF(I133>0,K133/I133*100,"") -> 40.072202 | AY133: =IF(AQ133>=100,"ok",IF(AQ133>0,"effectif faible (<100)","aucune association")) -> ok
A134: 95480 | B134: Parmain | C134: L'Isle-Adam | D134: liste subventions 2025 | E134: CC de la Vallée de l'Oise et des Trois Forêts | F134: Ceintures urbaines | G134: 5655 | H134: 2 | I134: 563 | J134: 277 | K134: 23 | L134: 5 | M134: 1 | N134: 1 | O134: 1 | P134: 363 | Q134: 242 | R134: 0 | S134: 0 | T134: 0 | U134: 2 | V134: 0 | W134: 14 | X134: 2 | Y134: 0 | Z134: 0 | AA134: 0 | AB134: 0 | AC134: 0 | AD134: 0 | AE134: 3 | AF134: 2 | AG134: 2 | AH134: 1 | AI134: 1 | AJ134: 316 | AK134: 181 | AL134: 152 | AM134: 67 | AN134: 86 | AO134: 605 | AP134: 840 | AQ134: =I134+J134 -> 840 | AR134: =IF(AQ134>0,I134/AQ134,"") -> 0.6702381 | AS134: =IF((P134+Q134)>0,P134/(P134+Q134),"") -> 0.6 | AT134: =IF(AND(ISNUMBER(AR134),ISNUMBER(AS134)),(AR134-AS134)*100,"") -> 7.0238095 | AU134: =IF(G134>0,I134/G134*1000,"") -> 99.557913 | AV134: =IF(G134>0,H134/G134*10000,"") -> 3.5366932 | AW134: =IF(G134>0,W134/G134*10000,"") -> 24.756852 | AX134: =IF(I134>0,K134/I134*100,"") -> 4.0852575 | AY134: =IF(AQ134>=100,"ok",IF(AQ134>0,"effectif faible (<100)","aucune association")) -> ok
A135: 95487 | B135: Persan | C135: L'Isle-Adam | D135: liste subventions 2025 | E135: CC du Haut Val d'Oise | F135: Centres urbains intermédiaires | G135: 14359 | H135: 8 | I135: 334 | J135: 769 | K135: 143 | L135: 0 | M135: 3 | N135: 2 | O135: 10 | P135: 441 | Q135: 995 | R135: 5 | S135: 1311 | T135: 37 | U135: 9 | V135: 5 | W135: 9 | X135: 1 | Y135: 0 | Z135: 1 | AA135: 1 | AB135: 1 | AC135: 2 | AD135: 0 | AE135: 7 | AF135: 11 | AG135: 10 | AH135: 11 | AI135: 11 | AJ135: 878 | AK135: 1473 | AL135: 1137 | AM135: 1708 | AN135: 1513 | AO135: 1436 | AP135: 1103 | AQ135: =I135+J135 -> 1103 | AR135: =IF(AQ135>0,I135/AQ135,"") -> 0.30281052 | AS135: =IF((P135+Q135)>0,P135/(P135+Q135),"") -> 0.30710306 | AT135: =IF(AND(ISNUMBER(AR135),ISNUMBER(AS135)),(AR135-AS135)*100,"") -> -0.42925473 | AU135: =IF(G135>0,I135/G135*1000,"") -> 23.260673 | AV135: =IF(G135>0,H135/G135*10000,"") -> 5.5714186 | AW135: =IF(G135>0,W135/G135*10000,"") -> 6.267846 | AX135: =IF(I135>0,K135/I135*100,"") -> 42.814371 | AY135: =IF(AQ135>=100,"ok",IF(AQ135>0,"effectif faible (<100)","aucune association")) -> ok
A136: 95488 | B136: Pierrelaye | C136: Taverny | D136: liste subventions 2025 | E136: CA Val Parisis | F136: Grands centres urbains | G136: 10130 | H136: 4 | I136: 440 | J136: 551 | K136: 59 | L136: 8 | M136: 1 | N136: 1 | O136: 4 | P136: 381 | Q136: 489 | R136: 1 | S136: 96 | T136: 6 | U136: 3 | V136: 1 | W136: 16 | X136: 5 | Y136: 1 | Z136: 0 | AA136: 0 | AB136: 0 | AC136: 0 | AD136: 0 | AE136: 4 | AF136: 4 | AG136: 4 | AH136: 4 | AI136: 4 | AJ136: 836 | AK136: 991 | AL136: 731 | AM136: 804 | AN136: 904 | AO136: 870 | AP136: 991 | AQ136: =I136+J136 -> 991 | AR136: =IF(AQ136>0,I136/AQ136,"") -> 0.44399596 | AS136: =IF((P136+Q136)>0,P136/(P136+Q136),"") -> 0.43793103 | AT136: =IF(AND(ISNUMBER(AR136),ISNUMBER(AS136)),(AR136-AS136)*100,"") -> 0.60649292 | AU136: =IF(G136>0,I136/G136*1000,"") -> 43.435341 | AV136: =IF(G136>0,H136/G136*10000,"") -> 3.9486673 | AW136: =IF(G136>0,W136/G136*10000,"") -> 15.794669 | AX136: =IF(I136>0,K136/I136*100,"") -> 13.409091 | AY136: =IF(AQ136>=100,"ok",IF(AQ136>0,"effectif faible (<100)","aucune association")) -> ok
A137: 95489 | B137: Piscop | C137: Deuil-la-Barre | D137: imputé (commune voisine la plus proche) | E137: CA Plaine Vallée | F137: Grands centres urbains | G137: 768 | H137: 0 | I137: 0 | J137: 0 | K137: 0 | L137: 0 | M137: 0 | N137: 0 | O137: 0 | P137: 0 | Q137: 0 | R137: 0 | S137: 0 | T137: 0 | U137: 0 | V137: 0 | W137: 4 | X137: 1 | Y137: 0 | Z137: 0 | AA137: 0 | AB137: 0 | AC137: 0 | AD137: 0 | AE137: 0 | AF137: 0 | AG137: 0 | AH137: 0 | AI137: 0 | AJ137: 0 | AK137: 0 | AL137: 0 | AM137: 0 | AN137: 0 | AO137: 0 | AP137: 0 | AQ137: =I137+J137 -> 0 | AR137: =IF(AQ137>0,I137/AQ137,"") | AS137: =IF((P137+Q137)>0,P137/(P137+Q137),"") | AT137: =IF(AND(ISNUMBER(AR137),ISNUMBER(AS137)),(AR137-AS137)*100,"") | AU137: =IF(G137>0,I137/G137*1000,"") -> 0 | AV137: =IF(G137>0,H137/G137*10000,"") -> 0 | AW137: =IF(G137>0,W137/G137*10000,"") -> 52.083333 | AX137: =IF(I137>0,K137/I137*100,"") | AY137: =IF(AQ137>=100,"ok",IF(AQ137>0,"effectif faible (<100)","aucune association")) -> aucune association
A138: 95500 | B138: Pontoise | C138: Pontoise | D138: liste subventions 2025 | E138: CA de Cergy-Pontoise | F138: Grands centres urbains | G138: 31970 | H138: 16 | I138: 3122 | J138: 4007 | K138: 520 | L138: 75 | M138: 4 | N138: 4 | O138: 16 | P138: 2854 | Q138: 4113 | R138: 4 | S138: 560 | T138: 23 | U138: 15 | V138: 3 | W138: 49 | X138: 15 | Y138: 1 | Z138: 4 | AA138: 3 | AB138: 3 | AC138: 1 | AD138: 0 | AE138: 15 | AF138: 17 | AG138: 16 | AH138: 16 | AI138: 15 | AJ138: 5652 | AK138: 6561 | AL138: 5548 | AM138: 5019 | AN138: 5698 | AO138: 6967 | AP138: 7129 | AQ138: =I138+J138 -> 7129 | AR138: =IF(AQ138>0,I138/AQ138,"") -> 0.43792958 | AS138: =IF((P138+Q138)>0,P138/(P138+Q138),"") -> 0.40964547 | AT138: =IF(AND(ISNUMBER(AR138),ISNUMBER(AS138)),(AR138-AS138)*100,"") -> 2.8284112 | AU138: =IF(G138>0,I138/G138*1000,"") -> 97.654051 | AV138: =IF(G138>0,H138/G138*10000,"") -> 5.0046919 | AW138: =IF(G138>0,W138/G138*10000,"") -> 15.326869 | AX138: =IF(I138>0,K138/I138*100,"") -> 16.65599 | AY138: =IF(AQ138>=100,"ok",IF(AQ138>0,"effectif faible (<100)","aucune association")) -> ok
A139: 95504 | B139: Presles | C139: L'Isle-Adam | D139: liste subventions 2025 | E139: CC de la Vallée de l'Oise et des Trois Forêts | F139: Ceintures urbaines | G139: 4017 | H139: 3 | I139: 148 | J139: 114 | K139: 23 | L139: 7 | M139: 1 | N139: 1 | O139: 3 | P139: 126 | Q139: 94 | R139: 0 | S139: 0 | T139: 0 | U139: 3 | V139: 0 | W139: 6 | X139: 1 | Y139: 0 | Z139: 0 | AA139: 0 | AB139: 0 | AC139: 0 | AD139: 0 | AE139: 2 | AF139: 3 | AG139: 3 | AH139: 3 | AI139: 3 | AJ139: 250 | AK139: 204 | AL139: 171 | AM139: 158 | AN139: 182 | AO139: 220 | AP139: 262 | AQ139: =I139+J139 -> 262 | AR139: =IF(AQ139>0,I139/AQ139,"") -> 0.5648855 | AS139: =IF((P139+Q139)>0,P139/(P139+Q139),"") -> 0.57272727 | AT139: =IF(AND(ISNUMBER(AR139),ISNUMBER(AS139)),(AR139-AS139)*100,"") -> -0.78417765 | AU139: =IF(G139>0,I139/G139*1000,"") -> 36.843415 | AV139: =IF(G139>0,H139/G139*10000,"") -> 7.4682599 | AW139: =IF(G139>0,W139/G139*10000,"") -> 14.93652 | AX139: =IF(I139>0,K139/I139*100,"") -> 15.540541 | AY139: =IF(AQ139>=100,"ok",IF(AQ139>0,"effectif faible (<100)","aucune association")) -> ok
A140: 95510 | B140: Puiseux-Pontoise | C140: Pontoise | D140: imputé (commune voisine la plus proche) | E140: CA de Cergy-Pontoise | F140: Ceintures urbaines | G140: 603 | H140: 0 | I140: 0 | J140: 0 | K140: 0 | L140: 0 | M140: 0 | N140: 0 | O140: 0 | P140: 0 | Q140: 0 | R140: 0 | S140: 0 | T140: 0 | U140: 0 | V140: 0 | W140: 3 | X140: 0 | Y140: 0 | Z140: 0 | AA140: 0 | AB140: 0 | AC140: 0 | AD140: 0 | AE140: 1 | AF140: 1 | AG140: 0 | AH140: 0 | AI140: 0 | AJ140: 15 | AK140: 10 | AL140: 0 | AM140: 0 | AN140: 0 | AO140: 0 | AP140: 0 | AQ140: =I140+J140 -> 0 | AR140: =IF(AQ140>0,I140/AQ140,"") | AS140: =IF((P140+Q140)>0,P140/(P140+Q140),"") | AT140: =IF(AND(ISNUMBER(AR140),ISNUMBER(AS140)),(AR140-AS140)*100,"") | AU140: =IF(G140>0,I140/G140*1000,"") -> 0 | AV140: =IF(G140>0,H140/G140*10000,"") -> 0 | AW140: =IF(G140>0,W140/G140*10000,"") -> 49.751244 | AX140: =IF(I140>0,K140/I140*100,"") | AY140: =IF(AQ140>=100,"ok",IF(AQ140>0,"effectif faible (<100)","aucune association")) -> aucune association
A141: 95509 | B141: Puiseux-en-France | C141: Fosses | D141: liste subventions 2025 | E141: CA Roissy Pays de France | F141: Centres urbains intermédiaires | G141: 3765 | H141: 3 | I141: 135 | J141: 227 | K141: 15 | L141: 3 | M141: 0 | N141: 1 | O141: 1 | P141: 68 | Q141: 128 | R141: 0 | S141: 0 | T141: 0 | U141: 3 | V141: 0 | W141: 6 | X141: 0 | Y141: 0 | Z141: 0 | AA141: 0 | AB141: 0 | AC141: 0 | AD141: 0 | AE141: 2 | AF141: 1 | AG141: 2 | AH141: 0 | AI141: 0 | AJ141: 245 | AK141: 112 | AL141: 214 | AM141: 0 | AN141: 0 | AO141: 196 | AP141: 362 | AQ141: =I141+J141 -> 362 | AR141: =IF(AQ141>0,I141/AQ141,"") -> 0.37292818 | AS141: =IF((P141+Q141)>0,P141/(P141+Q141),"") -> 0.34693878 | AT141: =IF(AND(ISNUMBER(AR141),ISNUMBER(AS141)),(AR141-AS141)*100,"") -> 2.5989401 | AU141: =IF(G141>0,I141/G141*1000,"") -> 35.856574 | AV141: =IF(G141>0,H141/G141*10000,"") -> 7.9681275 | AW141: =IF(G141>0,W141/G141*10000,"") -> 15.936255 | AX141: =IF(I141>0,K141/I141*100,"") -> 11.111111 | AY141: =IF(AQ141>=100,"ok",IF(AQ141>0,"effectif faible (<100)","aucune association")) -> ok
A142: 95527 | B142: Roissy-en-France | C142: Villiers-le-Bel | D142: liste subventions 2025 | E142: CA Roissy Pays de France | F142: Bourgs ruraux | G142: 2674 | H142: 2 | I142: 115 | J142: 261 | K142: 35 | L142: 1 | M142: 0 | N142: 0 | O142: 2 | P142: 106 | Q142: 260 | R142: 0 | S142: 0 | T142: 0 | U142: 2 | V142: 0 | W142: 10 | X142: 0 | Y142: 2 | Z142: 0 | AA142: 0 | AB142: 0 | AC142: 0 | AD142: 0 | AE142: 3 | AF142: 3 | AG142: 3 | AH142: 3 | AI142: 2 | AJ142: 1367 | AK142: 1297 | AL142: 1534 | AM142: 720 | AN142: 486 | AO142: 366 | AP142: 376 | AQ142: =I142+J142 -> 376 | AR142: =IF(AQ142>0,I142/AQ142,"") -> 0.30585106 | AS142: =IF((P142+Q142)>0,P142/(P142+Q142),"") -> 0.28961749 | AT142: =IF(AND(ISNUMBER(AR142),ISNUMBER(AS142)),(AR142-AS142)*100,"") -> 1.6233577 | AU142: =IF(G142>0,I142/G142*1000,"") -> 43.006731 | AV142: =IF(G142>0,H142/G142*10000,"") -> 7.4794316 | AW142: =IF(G142>0,W142/G142*10000,"") -> 37.397158 | AX142: =IF(I142>0,K142/I142*100,"") -> 30.434783 | AY142: =IF(AQ142>=100,"ok",IF(AQ142>0,"effectif faible (<100)","aucune association")) -> ok
... A162: 95607 | B162: Taverny | C162: Taverny | D162: liste subventions 2025 | E162: CA Val Parisis | F162: Grands centres urbains | G162: 27593 | H162: 14 | I162: 2405 | J162: 2978 | K162: 384 | L162: 48 | M162: 2 | N162: 3 | O162: 17 | P162: 2444 | Q162: 3134 | R162: 1 | S162: 123 | T162: 6 | U162: 13 | V162: 1 | W162: 19 | X162: 0 | Y162: 2 | Z162: 0 | AA162: 0 | AB162: 0 | AC162: 1 | AD162: 0 | AE162: 15 | AF162: 15 | AG162: 13 | AH162: 13 | AI162: 17 | AJ162: 3785 | AK162: 4850 | AL162: 4000 | AM162: 4105 | AN162: 4966 | AO162: 5578 | AP162: 5383 | AQ162: =I162+J162 -> 5383 | AR162: =IF(AQ162>0,I162/AQ162,"") -> 0.44677689 | AS162: =IF((P162+Q162)>0,P162/(P162+Q162),"") -> 0.43814987 | AT162: =IF(AND(ISNUMBER(AR162),ISNUMBER(AS162)),(AR162-AS162)*100,"") -> 0.86270157 | AU162: =IF(G162>0,I162/G162*1000,"") -> 87.159787 | AV162: =IF(G162>0,H162/G162*10000,"") -> 5.0737506 | AW162: =IF(G162>0,W162/G162*10000,"") -> 6.8858044 | AX162: =IF(I162>0,K162/I162*100,"") -> 15.966736 | AY162: =IF(AQ162>=100,"ok",IF(AQ162>0,"effectif faible (<100)","aucune association")) -> ok
A163: 95611 | B163: Theuville | C163: Pontoise | D163: imputé (commune voisine la plus proche) | E163: CC Vexin Centre | G163: 53 | H163: 0 | I163: 0 | J163: 0 | K163: 0 | L163: 0 | M163: 0 | N163: 0 | O163: 0 | P163: 0 | Q163: 0 | R163: 0 | S163: 0 | T163: 0 | U163: 0 | V163: 0 | W163: 0 | X163: 0 | Y163: 0 | Z163: 0 | AA163: 0 | AB163: 0 | AC163: 0 | AD163: 0 | AE163: 0 | AF163: 0 | AG163: 0 | AH163: 0 | AI163: 0 | AJ163: 0 | AK163: 0 | AL163: 0 | AM163: 0 | AN163: 0 | AO163: 0 | AP163: 0 | AQ163: =I163+J163 -> 0 | AR163: =IF(AQ163>0,I163/AQ163,"") | AS163: =IF((P163+Q163)>0,P163/(P163+Q163),"") | AT163: =IF(AND(ISNUMBER(AR163),ISNUMBER(AS163)),(AR163-AS163)*100,"") | AU163: =IF(G163>0,I163/G163*1000,"") -> 0 | AV163: =IF(G163>0,H163/G163*10000,"") -> 0 | AW163: =IF(G163>0,W163/G163*10000,"") -> 0 | AX163: =IF(I163>0,K163/I163*100,"") | AY163: =IF(AQ163>=100,"ok",IF(AQ163>0,"effectif faible (<100)","aucune association")) -> aucune association
A164: 95610 | B164: Théméricourt | C164: Vauréal | D164: imputé (commune voisine la plus proche) | E164: CC Vexin Centre | F164: Rural à habitat dispersé | G164: 283 | H164: 0 | I164: 0 | J164: 0 | K164: 0 | L164: 0 | M164: 0 | N164: 0 | O164: 0 | P164: 0 | Q164: 0 | R164: 0 | S164: 0 | T164: 0 | U164: 0 | V164: 0 | W164: 2 | X164: 0 | Y164: 0 | Z164: 0 | AA164: 0 | AB164: 0 | AC164: 0 | AD164: 0 | AE164: 0 | AF164: 0 | AG164: 0 | AH164: 0 | AI164: 0 | AJ164: 0 | AK164: 0 | AL164: 0 | AM164: 0 | AN164: 0 | AO164: 0 | AP164: 0 | AQ164: =I164+J164 -> 0 | AR164: =IF(AQ164>0,I164/AQ164,"") | AS164: =IF((P164+Q164)>0,P164/(P164+Q164),"") | AT164: =IF(AND(ISNUMBER(AR164),ISNUMBER(AS164)),(AR164-AS164)*100,"") | AU164: =IF(G164>0,I164/G164*1000,"") -> 0 | AV164: =IF(G164>0,H164/G164*10000,"") -> 0 | AW164: =IF(G164>0,W164/G164*10000,"") -> 70.671378 | AX164: =IF(I164>0,K164/I164*100,"") | AY164: =IF(AQ164>=100,"ok",IF(AQ164>0,"effectif faible (<100)","aucune association")) -> aucune association
A165: 95625 | B165: Us | C165: Pontoise | D165: liste subventions 2025 | E165: CC Vexin Centre | F165: Bourgs ruraux | G165: 1374 | H165: 1 | I165: 17 | J165: 59 | K165: 8 | L165: 1 | M165: 0 | N165: 0 | O165: 1 | P165: 24 | Q165: 70 | R165: 0 | S165: 0 | T165: 0 | U165: 1 | V165: 0 | W165: 7 | X165: 1 | Y165: 0 | Z165: 0 | AA165: 0 | AB165: 0 | AC165: 0 | AD165: 0 | AE165: 1 | AF165: 1 | AG165: 1 | AH165: 1 | AI165: 1 | AJ165: 360 | AK165: 89 | AL165: 111 | AM165: 123 | AN165: 111 | AO165: 94 | AP165: 76 | AQ165: =I165+J165 -> 76 | AR165: =IF(AQ165>0,I165/AQ165,"") -> 0.22368421 | AS165: =IF((P165+Q165)>0,P165/(P165+Q165),"") -> 0.25531915 | AT165: =IF(AND(ISNUMBER(AR165),ISNUMBER(AS165)),(AR165-AS165)*100,"") -> -3.1634938 | AU165: =IF(G165>0,I165/G165*1000,"") -> 12.372635 | AV165: =IF(G165>0,H165/G165*10000,"") -> 7.2780204 | AW165: =IF(G165>0,W165/G165*10000,"") -> 50.946143 | AX165: =IF(I165>0,K165/I165*100,"") -> 47.058824 | AY165: =IF(AQ165>=100,"ok",IF(AQ165>0,"effectif faible (<100)","aucune association")) -> effectif faible (<100)
A166: 95627 | B166: Vallangoujard | C166: Pontoise | D166: liste subventions 2025 | E166: CC Sausseron Impressionnistes | F166: Rural à habitat dispersé | G166: 625 | H166: 0 | I166: 0 | J166: 0 | K166: 0 | L166: 0 | M166: 0 | N166: 0 | O166: 0 | P166: 0 | Q166: 0 | R166: 1 | S166: 85 | T166: 6 | U166: 0 | V166: 1 | W166: 6 | X166: 0 | Y166: 0 | Z166: 0 | AA166: 0 | AB166: 0 | AC166: 0 | AD166: 0 | AE166: 1 | AF166: 1 | AG166: 0 | AH166: 0 | AI166: 0 | AJ166: 119 | AK166: 144 | AL166: 0 | AM166: 0 | AN166: 0 | AO166: 0 | AP166: 0 | AQ166: =I166+J166 -> 0 | AR166: =IF(AQ166>0,I166/AQ166,"") | AS166: =IF((P166+Q166)>0,P166/(P166+Q166),"") | AT166: =IF(AND(ISNUMBER(AR166),ISNUMBER(AS166)),(AR166-AS166)*100,"") | AU166: =IF(G166>0,I166/G166*1000,"") -> 0 | AV166: =IF(G166>0,H166/G166*10000,"") -> 0 | AW166: =IF(G166>0,W166/G166*10000,"") -> 96 | AX166: =IF(I166>0,K166/I166*100,"") | AY166: =IF(AQ166>=100,"ok",IF(AQ166>0,"effectif faible (<100)","aucune association")) -> aucune association
A167: 95628 | B167: Valmondois | C167: Saint-Ouen-l'Aumône | D167: imputé (commune voisine la plus proche) | E167: CC Sausseron Impressionnistes | F167: Ceintures urbaines | G167: 1208 | H167: 0 | I167: 0 | J167: 0 | K167: 0 | L167: 0 | M167: 0 | N167: 0 | O167: 0 | P167: 0 | Q167: 0 | R167: 0 | S167: 0 | T167: 0 | U167: 0 | V167: 0 | W167: 5 | X167: 0 | Y167: 0 | Z167: 0 | AA167: 0 | AB167: 0 | AC167: 0 | AD167: 0 | AE167: 0 | AF167: 0 | AG167: 0 | AH167: 0 | AI167: 0 | AJ167: 0 | AK167: 0 | AL167: 0 | AM167: 0 | AN167: 0 | AO167: 0 | AP167: 0 | AQ167: =I167+J167 -> 0 | AR167: =IF(AQ167>0,I167/AQ167,"") | AS167: =IF((P167+Q167)>0,P167/(P167+Q167),"") | AT167: =IF(AND(ISNUMBER(AR167),ISNUMBER(AS167)),(AR167-AS167)*100,"") | AU167: =IF(G167>0,I167/G167*1000,"") -> 0 | AV167: =IF(G167>0,H167/G167*10000,"") -> 0 | AW167: =IF(G167>0,W167/G167*10000,"") -> 41.390728 | AX167: =IF(I167>0,K167/I167*100,"") | AY167: =IF(AQ167>=100,"ok",IF(AQ167>0,"effectif faible (<100)","aucune association")) -> aucune association
A168: 95633 | B168: Vaudherland | C168: Villiers-le-Bel | D168: imputé (commune voisine la plus proche) | E168: CA Roissy Pays de France | G168: 104 | H168: 0 | I168: 0 | J168: 0 | K168: 0 | L168: 0 | M168: 0 | N168: 0 | O168: 0 | P168: 0 | Q168: 0 | R168: 0 | S168: 0 | T168: 0 | U168: 0 | V168: 0 | W168: 0 | X168: 0 | Y168: 0 | Z168: 0 | AA168: 0 | AB168: 0 | AC168: 0 | AD168: 0 | AE168: 0 | AF168: 0 | AG168: 0 | AH168: 0 | AI168: 0 | AJ168: 0 | AK168: 0 | AL168: 0 | AM168: 0 | AN168: 0 | AO168: 0 | AP168: 0 | AQ168: =I168+J168 -> 0 | AR168: =IF(AQ168>0,I168/AQ168,"") | AS168: =IF((P168+Q168)>0,P168/(P168+Q168),"") | AT168: =IF(AND(ISNUMBER(AR168),ISNUMBER(AS168)),(AR168-AS168)*100,"") | AU168: =IF(G168>0,I168/G168*1000,"") -> 0 | AV168: =IF(G168>0,H168/G168*10000,"") -> 0 | AW168: =IF(G168>0,W168/G168*10000,"") -> 0 | AX168: =IF(I168>0,K168/I168*100,"") | AY168: =IF(AQ168>=100,"ok",IF(AQ168>0,"effectif faible (<100)","aucune association")) -> aucune association
...

Sheet Cantons
A1: Indicateurs par canton
A2: Sommes calculées par SUMIFS sur l'onglet Communes ; ratios par formule.
A4: Canton | B4: Nb communes | C4: Communes sans asso. civile aidée | D4: Population | E4: Asso. civiles 2025 | F4: Adhérentes F 2025 | G4: Adhérents H 2025 | H4: Bénévoles F 2025 | I4: Salariées F 2025 | J4: Asso. <20 % F (2025) | K4: Asso. ≥60 % F (2025) | L4: Asso. civiles 2024 | M4: Adhérentes F 2024 | N4: Adhérents H 2024 | O4: Asso. scolaires 2025 | P4: Licencié·es scolaires 2025 (libellé F) | Q4: Sections scolaires 2025 | R4: Asso. civiles subventionnées 2025 | S4: Asso. scolaires subventionnées 2025 | T4: Lieux de pratique | U4: dont établissements scolaires | V4: dont piscines | W4: Manifestations 2023 | X4: Manifestations 2024 | Y4: Manifestations 2025 | Z4: Sections sportives scolaires 2026-27 | AA4: dont sections féminines | AB4: Asso. civiles 2019 | AC4: Asso. civiles 2020 | AD4: Asso. civiles 2021 | AE4: Asso. civiles 2022 | AF4: Asso. civiles 2023 | AG4: Licencié·es / adhérent·es 2019 | AH4: Licencié·es / adhérent·es 2020 | AI4: Licencié·es / adhérent·es 2021 | AJ4: Licencié·es / adhérent·es 2022 | AK4: Licencié·es / adhérent·es 2023 | AL4: Licencié·es / adhérent·es 2024 | AM4: Licencié·es / adhérent·es 2025 | AN4: Adhérent·es total 2025 | AO4: Part F 2025 | AP4: Part F 2024 | AQ4: Évolution part F (points) | AR4: Adhérentes F pour 1 000 hab. | AS4: Asso. civiles pour 10 000 hab. | AT4: Lieux pour 10 000 hab. | AU4: Bénévoles F pour 100 adhérentes | AV4: Fiabilité part F
A5: Argenteuil (1-2-3) | B5: =COUNTIF(Communes!$C$5:$C$187,A5) -> 4 | C5: =COUNTIFS(Communes!$C$5:$C$187,A5,Communes!$H$5:$H$187,0) -> 0 | D5: =SUMIFS(Communes!$G$5:$G$187,Communes!$C$5:$C$187,A5) -> 190824 | E5: =SUMIFS(Communes!$H$5:$H$187,Communes!$C$5:$C$187,A5) -> 37 | F5: =SUMIFS(Communes!$I$5:$I$187,Communes!$C$5:$C$187,A5) -> 5781 | G5: =SUMIFS(Communes!$J$5:$J$187,Communes!$C$5:$C$187,A5) -> 8420 | H5: =SUMIFS(Communes!$K$5:$K$187,Communes!$C$5:$C$187,A5) -> 1158 | I5: =SUMIFS(Communes!$L$5:$L$187,Communes!$C$5:$C$187,A5) -> 130 | J5: =SUMIFS(Communes!$M$5:$M$187,Communes!$C$5:$C$187,A5) -> 10 | K5: =SUMIFS(Communes!$N$5:$N$187,Communes!$C$5:$C$187,A5) -> 8 | L5: =SUMIFS(Communes!$O$5:$O$187,Communes!$C$5:$C$187,A5) -> 33 | M5: =SUMIFS(Communes!$P$5:$P$187,Communes!$C$5:$C$187,A5) -> 5481 | N5: =SUMIFS(Communes!$Q$5:$Q$187,Communes!$C$5:$C$187,A5) -> 6561 | O5: =SUMIFS(Communes!$R$5:$R$187,Communes!$C$5:$C$187,A5) -> 8 | P5: =SUMIFS(Communes!$S$5:$S$187,Communes!$C$5:$C$187,A5) -> 1058 | Q5: =SUMIFS(Communes!$T$5:$T$187,Communes!$C$5:$C$187,A5) -> 36 | R5: =SUMIFS(Communes!$U$5:$U$187,Communes!$C$5:$C$187,A5) -> 37 | S5: =SUMIFS(Communes!$V$5:$V$187,Communes!$C$5:$C$187,A5) -> 8 | T5: =SUMIFS(Communes!$W$5:$W$187,Communes!$C$5:$C$187,A5) -> 161 | U5: =SUMIFS(Communes!$X$5:$X$187,Communes!$C$5:$C$187,A5) -> 47 | V5: =SUMIFS(Communes!$Y$5:$Y$187,Communes!$C$5:$C$187,A5) -> 2 | W5: =SUMIFS(Communes!$Z$5:$Z$187,Communes!$C$5:$C$187,A5) -> 5 | X5: =SUMIFS(Communes!$AA$5:$AA$187,Communes!$C$5:$C$187,A5) -> 5 | Y5: =SUMIFS(Communes!$AB$5:$AB$187,Communes!$C$5:$C$187,A5) -> 4 | Z5: =SUMIFS(Communes!$AC$5:$AC$187,Communes!$C$5:$C$187,A5) -> 7 | AA5: =SUMIFS(Communes!$AD$5:$AD$187,Communes!$C$5:$C$187,A5) -> 0 | AB5: =SUMIFS(Communes!$AE$5:$AE$187,Communes!$C$5:$C$187,A5) -> 35 | AC5: =SUMIFS(Communes!$AF$5:$AF$187,Communes!$C$5:$C$187,A5) -> 40 | AD5: =SUMIFS(Communes!$AG$5:$AG$187,Communes!$C$5:$C$187,A5) -> 38 | AE5: =SUMIFS(Communes!$AH$5:$AH$187,Communes!$C$5:$C$187,A5) -> 36 | AF5: =SUMIFS(Communes!$AI$5:$AI$187,Communes!$C$5:$C$187,A5) -> 34 | AG5: =SUMIFS(Communes!$AJ$5:$AJ$187,Communes!$C$5:$C$187,A5) -> 12104 | AH5: =SUMIFS(Communes!$AK$5:$AK$187,Communes!$C$5:$C$187,A5) -> 13474 | AI5: =SUMIFS(Communes!$AL$5:$AL$187,Communes!$C$5:$C$187,A5) -> 12159 | AJ5: =SUMIFS(Communes!$AM$5:$AM$187,Communes!$C$5:$C$187,A5) -> 10325 | AK5: =SUMIFS(Communes!$AN$5:$AN$187,Communes!$C$5:$C$187,A5) -> 10715 | AL5: =SUMIFS(Communes!$AO$5:$AO$187,Communes!$C$5:$C$187,A5) -> 12042 | AM5: =SUMIFS(Communes!$AP$5:$AP$187,Communes!$C$5:$C$187,A5) -> 14201 | AN5: =F5+G5 -> 14201 | AO5: =IF(AN5>0,F5/AN5,"") -> 0.40708401 | AP5: =IF((M5+N5)>0,M5/(M5+N5),"") -> 0.45515695 | AQ5: =IF(AND(ISNUMBER(AO5),ISNUMBER(AP5)),(AO5-AP5)*100,"") -> -4.8072943 | AR5: =IF(D5>0,F5/D5*1000,"") -> 30.294931 | AS5: =IF(D5>0,E5/D5*10000,"") -> 1.9389595 | AT5: =IF(D5>0,T5/D5*10000,"") -> 8.4370939 | AU5: =IF(F5>0,H5/F5*100,"") -> 20.031136 | AV5: =IF(AN5>=100,"ok",IF(AN5>0,"effectif faible (<100)","aucune association")) -> ok
A6: Cergy (1-2) | B6: =COUNTIF(Communes!$C$5:$C$187,A6) -> 5 | C6: =COUNTIFS(Communes!$C$5:$C$187,A6,Communes!$H$5:$H$187,0) -> 0 | D6: =SUMIFS(Communes!$G$5:$G$187,Communes!$C$5:$C$187,A6) -> 127208 | E6: =SUMIFS(Communes!$H$5:$H$187,Communes!$C$5:$C$187,A6) -> 59 | F6: =SUMIFS(Communes!$I$5:$I$187,Communes!$C$5:$C$187,A6) -> 7360 | G6: =SUMIFS(Communes!$J$5:$J$187,Communes!$C$5:$C$187,A6) -> 9308 | H6: =SUMIFS(Communes!$K$5:$K$187,Communes!$C$5:$C$187,A6) -> 994 | I6: =SUMIFS(Communes!$L$5:$L$187,Communes!$C$5:$C$187,A6) -> 118 | J6: =SUMIFS(Communes!$M$5:$M$187,Communes!$C$5:$C$187,A6) -> 13 | K6: =SUMIFS(Communes!$N$5:$N$187,Communes!$C$5:$C$187,A6) -> 11 | L6: =SUMIFS(Communes!$O$5:$O$187,Communes!$C$5:$C$187,A6) -> 62 | M6: =SUMIFS(Communes!$P$5:$P$187,Communes!$C$5:$C$187,A6) -> 6792 | N6: =SUMIFS(Communes!$Q$5:$Q$187,Communes!$C$5:$C$187,A6) -> 8855 | O6: =SUMIFS(Communes!$R$5:$R$187,Communes!$C$5:$C$187,A6) -> 21 | P6: =SUMIFS(Communes!$S$5:$S$187,Communes!$C$5:$C$187,A6) -> 3659 | Q6: =SUMIFS(Communes!$T$5:$T$187,Communes!$C$5:$C$187,A6) -> 134 | R6: =SUMIFS(Communes!$U$5:$U$187,Communes!$C$5:$C$187,A6) -> 62 | S6: =SUMIFS(Communes!$V$5:$V$187,Communes!$C$5:$C$187,A6) -> 23 | T6: =SUMIFS(Communes!$W$5:$W$187,Communes!$C$5:$C$187,A6) -> 144 | U6: =SUMIFS(Communes!$X$5:$X$187,Communes!$C$5:$C$187,A6) -> 43 | V6: =SUMIFS(Communes!$Y$5:$Y$187,Communes!$C$5:$C$187,A6) -> 4 | W6: =SUMIFS(Communes!$Z$5:$Z$187,Communes!$C$5:$C$187,A6) -> 2 | X6: =SUMIFS(Communes!$AA$5:$AA$187,Communes!$C$5:$C$187,A6) -> 5 | Y6: =SUMIFS(Communes!$AB$5:$AB$187,Communes!$C$5:$C$187,A6) -> 5 | Z6: =SUMIFS(Communes!$AC$5:$AC$187,Communes!$C$5:$C$187,A6) -> 6 | AA6: =SUMIFS(Communes!$AD$5:$AD$187,Communes!$C$5:$C$187,A6) -> 0 | AB6: =SUMIFS(Communes!$AE$5:$AE$187,Communes!$C$5:$C$187,A6) -> 56 | AC6: =SUMIFS(Communes!$AF$5:$AF$187,Communes!$C$5:$C$187,A6) -> 62 | AD6: =SUMIFS(Communes!$AG$5:$AG$187,Communes!$C$5:$C$187,A6) -> 59 | AE6: =SUMIFS(Communes!$AH$5:$AH$187,Communes!$C$5:$C$187,A6) -> 60 | AF6: =SUMIFS(Communes!$AI$5:$AI$187,Communes!$C$5:$C$187,A6) -> 58 | AG6: =SUMIFS(Communes!$AJ$5:$AJ$187,Communes!$C$5:$C$187,A6) -> 10575 | AH6: =SUMIFS(Communes!$AK$5:$AK$187,Communes!$C$5:$C$187,A6) -> 11173 | AI6: =SUMIFS(Communes!$AL$5:$AL$187,Communes!$C$5:$C$187,A6) -> 10256 | AJ6: =SUMIFS(Communes!$AM$5:$AM$187,Communes!$C$5:$C$187,A6) -> 10592 | AK6: =SUMIFS(Communes!$AN$5:$AN$187,Communes!$C$5:$C$187,A6) -> 11871 | AL6: =SUMIFS(Communes!$AO$5:$AO$187,Communes!$C$5:$C$187,A6) -> 15647 | AM6: =SUMIFS(Communes!$AP$5:$AP$187,Communes!$C$5:$C$187,A6) -> 16668 | AN6: =F6+G6 -> 16668 | AO6: =IF(AN6>0,F6/AN6,"") -> 0.44156467 | AP6: =IF((M6+N6)>0,M6/(M6+N6),"") -> 0.43407682 | AQ6: =IF(AND(ISNUMBER(AO6),ISNUMBER(AP6)),(AO6-AP6)*100,"") -> 0.7487855 | AR6: =IF(D6>0,F6/D6*1000,"") -> 57.857996 | AS6: =IF(D6>0,E6/D6*10000,"") -> 4.6380731 | AT6: =IF(D6>0,T6/D6*10000,"") -> 11.320043 | AU6: =IF(F6>0,H6/F6*100,"") -> 13.505435 | AV6: =IF(AN6>=100,"ok",IF(AN6>0,"effectif faible (<100)","aucune association")) -> ok
A7: Deuil-la-Barre | B7: =COUNTIF(Communes!$C$5:$C$187,A7) -> 5 | C7: =COUNTIFS(Communes!$C$5:$C$187,A7,Communes!$H$5:$H$187,0) -> 1 | D7: =SUMIFS(Communes!$G$5:$G$187,Communes!$C$5:$C$187,A7) -> 62488 | E7: =SUMIFS(Communes!$H$5:$H$187,Communes!$C$5:$C$187,A7) -> 14 | F7: =SUMIFS(Communes!$I$5:$I$187,Communes!$C$5:$C$187,A7) -> 2199 | G7: =SUMIFS(Communes!$J$5:$J$187,Communes!$C$5:$C$187,A7) -> 3574 | H7: =SUMIFS(Communes!$K$5:$K$187,Communes!$C$5:$C$187,A7) -> 374 | I7: =SUMIFS(Communes!$L$5:$L$187,Communes!$C$5:$C$187,A7) -> 37 | J7: =SUMIFS(Communes!$M$5:$M$187,Communes!$C$5:$C$187,A7) -> 5 | K7: =SUMIFS(Communes!$N$5:$N$187,Communes!$C$5:$C$187,A7) -> 4 | L7: =SUMIFS(Communes!$O$5:$O$187,Communes!$C$5:$C$187,A7) -> 18 | M7: =SUMIFS(Communes!$P$5:$P$187,Communes!$C$5:$C$187,A7) -> 2675 | N7: =SUMIFS(Communes!$Q$5:$Q$187,Communes!$C$5:$C$187,A7) -> 4042 | O7: =SUMIFS(Communes!$R$5:$R$187,Communes!$C$5:$C$187,A7) -> 4 | P7: =SUMIFS(Communes!$S$5:$S$187,Communes!$C$5:$C$187,A7) -> 589 | Q7: =SUMIFS(Communes!$T$5:$T$187,Communes!$C$5:$C$187,A7) -> 15 | R7: =SUMIFS(Communes!$U$5:$U$187,Communes!$C$5:$C$187,A7) -> 16 | S7: =SUMIFS(Communes!$V$5:$V$187,Communes!$C$5:$C$187,A7) -> 4 | T7: =SUMIFS(Communes!$W$5:$W$187,Communes!$C$5:$C$187,A7) -> 51 | U7: =SUMIFS(Communes!$X$5:$X$187,Communes!$C$5:$C$187,A7) -> 13 | V7: =SUMIFS(Communes!$Y$5:$Y$187,Communes!$C$5:$C$187,A7) -> 0 | W7: =SUMIFS(Communes!$Z$5:$Z$187,Communes!$C$5:$C$187,A7) -> 0 | X7: =SUMIFS(Communes!$AA$5:$AA$187,Communes!$C$5:$C$187,A7) -> 1 | Y7: =SUMIFS(Communes!$AB$5:$AB$187,Communes!$C$5:$C$187,A7) -> 0 | Z7: =SUMIFS(Communes!$AC$5:$AC$187,Communes!$C$5:$C$187,A7) -> 1 | AA7: =SUMIFS(Communes!$AD$5:$AD$187,Communes!$C$5:$C$187,A7) -> 0 | AB7: =SUMIFS(Communes!$AE$5:$AE$187,Communes!$C$5:$C$187,A7) -> 22 | AC7: =SUMIFS(Communes!$AF$5:$AF$187,Communes!$C$5:$C$187,A7) -> 21 | AD7: =SUMIFS(Communes!$AG$5:$AG$187,Communes!$C$5:$C$187,A7) -> 21 | AE7: =SUMIFS(Communes!$AH$5:$AH$187,Communes!$C$5:$C$187,A7) -> 18 | AF7: =SUMIFS(Communes!$AI$5:$AI$187,Communes!$C$5:$C$187,A7) -> 17 | AG7: =SUMIFS(Communes!$AJ$5:$AJ$187,Communes!$C$5:$C$187,A7) -> 6928 | AH7: =SUMIFS(Communes!$AK$5:$AK$187,Communes!$C$5:$C$187,A7) -> 6664 | AI7: =SUMIFS(Communes!$AL$5:$AL$187,Communes!$C$5:$C$187,A7) -> 6225 | AJ7: =SUMIFS(Communes!$AM$5:$AM$187,Communes!$C$5:$C$187,A7) -> 5732 | AK7: =SUMIFS(Communes!$AN$5:$AN$187,Communes!$C$5:$C$187,A7) -> 5844 | AL7: =SUMIFS(Communes!$AO$5:$AO$187,Communes!$C$5:$C$187,A7) -> 6717 | AM7: =SUMIFS(Communes!$AP$5:$AP$187,Communes!$C$5:$C$187,A7) -> 5773 | AN7: =F7+G7 -> 5773 | AO7: =IF(AN7>0,F7/AN7,"") -> 0.38091114 | AP7: =IF((M7+N7)>0,M7/(M7+N7),"") -> 0.39824326 | AQ7: =IF(AND(ISNUMBER(AO7),ISNUMBER(AP7)),(AO7-AP7)*100,"") -> -1.7332125 | AR7: =IF(D7>0,F7/D7*1000,"") -> 35.190757 | AS7: =IF(D7>0,E7/D7*10000,"") -> 2.2404302 | AT7: =IF(D7>0,T7/D7*10000,"") -> 8.161567 | AU7: =IF(F7>0,H7/F7*100,"") -> 17.007731 | AV7: =IF(AN7>=100,"ok",IF(AN7>0,"effectif faible (<100)","aucune association")) -> ok
A8: Domont | B8: =COUNTIF(Communes!$C$5:$C$187,A8) -> 9 | C8: =COUNTIFS(Communes!$C$5:$C$187,A8,Communes!$H$5:$H$187,0) -> 2 | D8: =SUMIFS(Communes!$G$5:$G$187,Communes!$C$5:$C$187,A8) -> 64305 | E8: =SUMIFS(Communes!$H$5:$H$187,Communes!$C$5:$C$187,A8) -> 47 | F8: =SUMIFS(Communes!$I$5:$I$187,Communes!$C$5:$C$187,A8) -> 5164 | G8: =SUMIFS(Communes!$J$5:$J$187,Communes!$C$5:$C$187,A8) -> 6592 | H8: =SUMIFS(Communes!$K$5:$K$187,Communes!$C$5:$C$187,A8) -> 845 | I8: =SUMIFS(Communes!$L$5:$L$187,Communes!$C$5:$C$187,A8) -> 111 | J8: =SUMIFS(Communes!$M$5:$M$187,Communes!$C$5:$C$187,A8) -> 7 | K8: =SUMIFS(Communes!$N$5:$N$187,Communes!$C$5:$C$187,A8) -> 10 | L8: =SUMIFS(Communes!$O$5:$O$187,Communes!$C$5:$C$187,A8) -> 45 | M8: =SUMIFS(Communes!$P$5:$P$187,Communes!$C$5:$C$187,A8) -> 4839 | N8: =SUMIFS(Communes!$Q$5:$Q$187,Communes!$C$5:$C$187,A8) -> 5860 | O8: =SUMIFS(Communes!$R$5:$R$187,Communes!$C$5:$C$187,A8) -> 5 | P8: =SUMIFS(Communes!$S$5:$S$187,Communes!$C$5:$C$187,A8) -> 693 | Q8: =SUMIFS(Communes!$T$5:$T$187,Communes!$C$5:$C$187,A8) -> 20 | R8: =SUMIFS(Communes!$U$5:$U$187,Communes!$C$5:$C$187,A8) -> 45 | S8: =SUMIFS(Communes!$V$5:$V$187,Communes!$C$5:$C$187,A8) -> 5 | T8: =SUMIFS(Communes!$W$5:$W$187,Communes!$C$5:$C$187,A8) -> 74 | U8: =SUMIFS(Communes!$X$5:$X$187,Communes!$C$5:$C$187,A8) -> 15 | V8: =SUMIFS(Communes!$Y$5:$Y$187,Communes!$C$5:$C$187,A8) -> 1 | W8: =SUMIFS(Communes!$Z$5:$Z$187,Communes!$C$5:$C$187,A8) -> 6 | X8: =SUMIFS(Communes!$AA$5:$AA$187,Communes!$C$5:$C$187,A8) -> 0 | Y8: =SUMIFS(Communes!$AB$5:$AB$187,Communes!$C$5:$C$187,A8) -> 3 | Z8: =SUMIFS(Communes!$AC$5:$AC$187,Communes!$C$5:$C$187,A8) -> 1 | AA8: =SUMIFS(Communes!$AD$5:$AD$187,Communes!$C$5:$C$187,A8) -> 0 | AB8: =SUMIFS(Communes!$AE$5:$AE$187,Communes!$C$5:$C$187,A8) -> 43 | AC8: =SUMIFS(Communes!$AF$5:$AF$187,Communes!$C$5:$C$187,A8) -> 41 | AD8: =SUMIFS(Communes!$AG$5:$AG$187,Communes!$C$5:$C$187,A8) -> 46 | AE8: =SUMIFS(Communes!$AH$5:$AH$187,Communes!$C$5:$C$187,A8) -> 46 | AF8: =SUMIFS(Communes!$AI$5:$AI$187,Communes!$C$5:$C$187,A8) -> 44 | AG8: =SUMIFS(Communes!$AJ$5:$AJ$187,Communes!$C$5:$C$187,A8) -> 8032 | AH8: =SUMIFS(Communes!$AK$5:$AK$187,Communes!$C$5:$C$187,A8) -> 8520 | AI8: =SUMIFS(Communes!$AL$5:$AL$187,Communes!$C$5:$C$187,A8) -> 9187 | AJ8: =SUMIFS(Communes!$AM$5:$AM$187,Communes!$C$5:$C$187,A8) -> 9320 | AK8: =SUMIFS(Communes!$AN$5:$AN$187,Communes!$C$5:$C$187,A8) -> 9994 | AL8: =SUMIFS(Communes!$AO$5:$AO$187,Communes!$C$5:$C$187,A8) -> 10699 | AM8: =SUMIFS(Communes!$AP$5:$AP$187,Communes!$C$5:$C$187,A8) -> 11756 | AN8: =F8+G8 -> 11756 | AO8: =IF(AN8>0,F8/AN8,"") -> 0.43926506 | AP8: =IF((M8+N8)>0,M8/(M8+N8),"") -> 0.45228526 | AQ8: =IF(AND(ISNUMBER(AO8),ISNUMBER(AP8)),(AO8-AP8)*100,"") -> -1.3020204 | AR8: =IF(D8>0,F8/D8*1000,"") -> 80.304797 | AS8: =IF(D8>0,E8/D8*10000,"") -> 7.3089184 | AT8: =IF(D8>0,T8/D8*10000,"") -> 11.507659 | AU8: =IF(F8>0,H8/F8*100,"") -> 16.363284 | AV8: =IF(AN8>=100,"ok",IF(AN8>0,"effectif faible (<100)","aucune association")) -> ok
A9: Ermont | B9: =COUNTIF(Communes!$C$5:$C$187,A9) -> 2 | C9: =COUNTIFS(Communes!$C$5:$C$187,A9,Communes!$H$5:$H$187,0) -> 0 | D9: =SUMIFS(Communes!$G$5:$G$187,Communes!$C$5:$C$187,A9) -> 55700 | E9: =SUMIFS(Communes!$H$5:$H$187,Communes!$C$5:$C$187,A9) -> 22 | F9: =SUMIFS(Communes!$I$5:$I$187,Communes!$C$5:$C$187,A9) -> 3418 | G9: =SUMIFS(Communes!$J$5:$J$187,Communes!$C$5:$C$187,A9) -> 2871 | H9: =SUMIFS(Communes!$K$5:$K$187,Communes!$C$5:$C$187,A9) -> 381 | I9: =SUMIFS(Communes!$L$5:$L$187,Communes!$C$5:$C$187,A9) -> 67 | J9: =SUMIFS(Communes!$M$5:$M$187,Communes!$C$5:$C$187,A9) -> 5 | K9: =SUMIFS(Communes!$N$5:$N$187,Communes!$C$5:$C$187,A9) -> 6 | L9: =SUMIFS(Communes!$O$5:$O$187,Communes!$C$5:$C$187,A9) -> 22 | M9: =SUMIFS(Communes!$P$5:$P$187,Communes!$C$5:$C$187,A9) -> 2870 | N9: =SUMIFS(Communes!$Q$5:$Q$187,Communes!$C$5:$C$187,A9) -> 2846 | O9: =SUMIFS(Communes!$R$5:$R$187,Communes!$C$5:$C$187,A9) -> 3 | P9: =SUMIFS(Communes!$S$5:$S$187,Communes!$C$5:$C$187,A9) -> 454 | Q9: =SUMIFS(Communes!$T$5:$T$187,Communes!$C$5:$C$187,A9) -> 15 | R9: =SUMIFS(Communes!$U$5:$U$187,Communes!$C$5:$C$187,A9) -> 24 | S9: =SUMIFS(Communes!$V$5:$V$187,Communes!$C$5:$C$187,A9) -> 3 | T9: =SUMIFS(Communes!$W$5:$W$187,Communes!$C$5:$C$187,A9) -> 39 | U9: =SUMIFS(Communes!$X$5:$X$187,Communes!$C$5:$C$187,A9) -> 3 | V9: =SUMIFS(Communes!$Y$5:$Y$187,Communes!$C$5:$C$187,A9) -> 1 | W9: =SUMIFS(Communes!$Z$5:$Z$187,Communes!$C$5:$C$187,A9) -> 5 | X9: =SUMIFS(Communes!$AA$5:$AA$187,Communes!$C$5:$C$187,A9) -> 1 | Y9: =SUMIFS(Communes!$AB$5:$AB$187,Communes!$C$5:$C$187,A9) -> 5 | Z9: =SUMIFS(Communes!$AC$5:$AC$187,Communes!$C$5:$C$187,A9) -> 1 | AA9: =SUMIFS(Communes!$AD$5:$AD$187,Communes!$C$5:$C$187,A9) -> 0 | AB9: =SUMIFS(Communes!$AE$5:$AE$187,Communes!$C$5:$C$187,A9) -> 22 | AC9: =SUMIFS(Communes!$AF$5:$AF$187,Communes!$C$5:$C$187,A9) -> 22 | AD9: =SUMIFS(Communes!$AG$5:$AG$187,Communes!$C$5:$C$187,A9) -> 21 | AE9: =SUMIFS(Communes!$AH$5:$AH$187,Communes!$C$5:$C$187,A9) -> 21 | AF9: =SUMIFS(Communes!$AI$5:$AI$187,Communes!$C$5:$C$187,A9) -> 21 | AG9: =SUMIFS(Communes!$AJ$5:$AJ$187,Communes!$C$5:$C$187,A9) -> 8111 | AH9: =SUMIFS(Communes!$AK$5:$AK$187,Communes!$C$5:$C$187,A9) -> 8955 | AI9: =SUMIFS(Communes!$AL$5:$AL$187,Communes!$C$5:$C$187,A9) -> 7629 | AJ9: =SUMIFS(Communes!$AM$5:$AM$187,Communes!$C$5:$C$187,A9) -> 5004 | AK9: =SUMIFS(Communes!$AN$5:$AN$187,Communes!$C$5:$C$187,A9) -> 5010 | AL9: =SUMIFS(Communes!$AO$5:$AO$187,Communes!$C$5:$C$187,A9) -> 5716 | AM9: =SUMIFS(Communes!$AP$5:$AP$187,Communes!$C$5:$C$187,A9) -> 6289 | AN9: =F9+G9 -> 6289 | AO9: =IF(AN9>0,F9/AN9,"") -> 0.54348863 | AP9: =IF((M9+N9)>0,M9/(M9+N9),"") -> 0.50209937 | AQ9: =IF(AND(ISNUMBER(AO9),ISNUMBER(AP9)),(AO9-AP9)*100,"") -> 4.1389261 | AR9: =IF(D9>0,F9/D9*1000,"") -> 61.364452 | AS9: =IF(D9>0,E9/D9*10000,"") -> 3.9497307 | AT9: =IF(D9>0,T9/D9*10000,"") -> 7.0017953 | AU9: =IF(F9>0,H9/F9*100,"") -> 11.14687 | AV9: =IF(AN9>=100,"ok",IF(AN9>0,"effectif faible (<100)","aucune association")) -> ok
A10: Fosses | B10: =COUNTIF(Communes!$C$5:$C$187,A10) -> 25 | C10: =COUNTIFS(Communes!$C$5:$C$187,A10,Communes!$H$5:$H$187,0) -> 10 | D10: =SUMIFS(Communes!$G$5:$G$187,Communes!$C$5:$C$187,A10) -> 65490 | E10: =SUMIFS(Communes!$H$5:$H$187,Communes!$C$5:$C$187,A10) -> 42 | F10: =SUMIFS(Communes!$I$5:$I$187,Communes!$C$5:$C$187,A10) -> 3569 | G10: =SUMIFS(Communes!$J$5:$J$187,Communes!$C$5:$C$187,A10) -> 6061 | H10: =SUMIFS(Communes!$K$5:$K$187,Communes!$C$5:$C$187,A10) -> 1161 | I10: =SUMIFS(Communes!$L$5:$L$187,Communes!$C$5:$C$187,A10) -> 82 | J10: =SUMIFS(Communes!$M$5:$M$187,Communes!$C$5:$C$187,A10) -> 13 | K10: =SUMIFS(Communes!$N$5:$N$187,Communes!$C$5:$C$187,A10) -> 14 | L10: =SUMIFS(Communes!$O$5:$O$187,Communes!$C$5:$C$187,A10) -> 43 | M10: =SUMIFS(Communes!$P$5:$P$187,Communes!$C$5:$C$187,A10) -> 4725 | N10: =SUMIFS(Communes!$Q$5:$Q$187,Communes!$C$5:$C$187,A10) -> 6294 | O10: =SUMIFS(Communes!$R$5:$R$187,Communes!$C$5:$C$187,A10) -> 4 | P10: =SUMIFS(Communes!$S$5:$S$187,Communes!$C$5:$C$187,A10) -> 653 | Q10: =SUMIFS(Communes!$T$5:$T$187,Communes!$C$5:$C$187,A10) -> 19 | R10: =SUMIFS(Communes!$U$5:$U$187,Communes!$C$5:$C$187,A10) -> 42 | S10: =SUMIFS(Communes!$V$5:$V$187,Communes!$C$5:$C$187,A10) -> 4 | T10: =SUMIFS(Communes!$W$5:$W$187,Communes!$C$5:$C$187,A10) -> 127 | U10: =SUMIFS(Communes!$X$5:$X$187,Communes!$C$5:$C$187,A10) -> 15 | V10: =SUMIFS(Communes!$Y$5:$Y$187,Communes!$C$5:$C$187,A10) -> 2 | W10: =SUMIFS(Communes!$Z$5:$Z$187,Communes!$C$5:$C$187,A10) -> 1 | X10: =SUMIFS(Communes!$AA$5:$AA$187,Communes!$C$5:$C$187,A10) -> 1 | Y10: =SUMIFS(Communes!$AB$5:$AB$187,Communes!$C$5:$C$187,A10) -> 2 | Z10: =SUMIFS(Communes!$AC$5:$AC$187,Communes!$C$5:$C$187,A10) -> 2 | AA10: =SUMIFS(Communes!$AD$5:$AD$187,Communes!$C$5:$C$187,A10) -> 0 | AB10: =SUMIFS(Communes!$AE$5:$AE$187,Communes!$C$5:$C$187,A10) -> 38 | AC10: =SUMIFS(Communes!$AF$5:$AF$187,Communes!$C$5:$C$187,A10) -> 41 | AD10: =SUMIFS(Communes!$AG$5:$AG$187,Communes!$C$5:$C$187,A10) -> 45 | AE10: =SUMIFS(Communes!$AH$5:$AH$187,Communes!$C$5:$C$187,A10) -> 42 | AF10: =SUMIFS(Communes!$AI$5:$AI$187,Communes!$C$5:$C$187,A10) -> 40 | AG10: =SUMIFS(Communes!$AJ$5:$AJ$187,Communes!$C$5:$C$187,A10) -> 8495 | AH10: =SUMIFS(Communes!$AK$5:$AK$187,Communes!$C$5:$C$187,A10) -> 8124 | AI10: =SUMIFS(Communes!$AL$5:$AL$187,Communes!$C$5:$C$187,A10) -> 7403 | AJ10: =SUMIFS(Communes!$AM$5:$AM$187,Communes!$C$5:$C$187,A10) -> 7197 | AK10: =SUMIFS(Communes!$AN$5:$AN$187,Communes!$C$5:$C$187,A10) -> 7683 | AL10: =SUMIFS(Communes!$AO$5:$AO$187,Communes!$C$5:$C$187,A10) -> 11019 | AM10: =SUMIFS(Communes!$AP$5:$AP$187,Communes!$C$5:$C$187,A10) -> 9630 | AN10: =F10+G10 -> 9630 | AO10: =IF(AN10>0,F10/AN10,"") -> 0.37061267 | AP10: =IF((M10+N10)>0,M10/(M10+N10),"") -> 0.42880479 | AQ10: =IF(AND(ISNUMBER(AO10),ISNUMBER(AP10)),(AO10-AP10)*100,"") -> -5.8192123 | AR10: =IF(D10>0,F10/D10*1000,"") -> 54.49687 | AS10: =IF(D10>0,E10/D10*10000,"") -> 6.4131929 | AT10: =IF(D10>0,T10/D10*10000,"") -> 19.392274 | AU10: =IF(F10>0,H10/F10*100,"") -> 32.53012 | AV10: =IF(AN10>=100,"ok",IF(AN10>0,"effectif faible (<100)","aucune association")) -> ok
A11: Franconville | B11: =COUNTIF(Communes!$C$5:$C$187,A11) -> 2 | C11: =COUNTIFS(Communes!$C$5:$C$187,A11,Communes!$H$5:$H$187,0) -> 0 | D11: =SUMIFS(Communes!$G$5:$G$187,Communes!$C$5:$C$187,A11) -> 65046 | E11: =SUMIFS(Communes!$H$5:$H$187,Communes!$C$5:$C$187,A11) -> 14 | F11: =SUMIFS(Communes!$I$5:$I$187,Communes!$C$5:$C$187,A11) -> 5263 | G11: =SUMIFS(Communes!$J$5:$J$187,Communes!$C$5:$C$187,A11) -> 5165 | H11: =SUMIFS(Communes!$K$5:$K$187,Communes!$C$5:$C$187,A11) -> 564 | I11: =SUMIFS(Communes!$L$5:$L$187,Communes!$C$5:$C$187,A11) -> 84 | J11: =SUMIFS(Communes!$M$5:$M$187,Communes!$C$5:$C$187,A11) -> 5 | K11: =SUMIFS(Communes!$N$5:$N$187,Communes!$C$5:$C$187,A11) -> 3 | L11: =SUMIFS(Communes!$O$5:$O$187,Communes!$C$5:$C$187,A11) -> 17 | M11: =SUMIFS(Communes!$P$5:$P$187,Communes!$C$5:$C$187,A11) -> 5053 | N11: =SUMIFS(Communes!$Q$5:$Q$187,Communes!$C$5:$C$187,A11) -> 5216 | O11: =SUMIFS(Communes!$R$5:$R$187,Communes!$C$5:$C$187,A11) -> 4 | P11: =SUMIFS(Communes!$S$5:$S$187,Communes!$C$5:$C$187,A11) -> 624 | Q11: =SUMIFS(Communes!$T$5:$T$187,Communes!$C$5:$C$187,A11) -> 15 | R11: =SUMIFS(Communes!$U$5:$U$187,Communes!$C$5:$C$187,A11) -> 14 | S11: =SUMIFS(Communes!$V$5:$V$187,Communes!$C$5:$C$187,A11) -> 4 | T11: =SUMIFS(Communes!$W$5:$W$187,Communes!$C$5:$C$187,A11) -> 53 | U11: =SUMIFS(Communes!$X$5:$X$187,Communes!$C$5:$C$187,A11) -> 13 | V11: =SUMIFS(Communes!$Y$5:$Y$187,Communes!$C$5:$C$187,A11) -> 2 | W11: =SUMIFS(Communes!$Z$5:$Z$187,Communes!$C$5:$C$187,A11) -> 1 | X11: =SUMIFS(Communes!$AA$5:$AA$187,Communes!$C$5:$C$187,A11) -> 0 | Y11: =SUMIFS(Communes!$AB$5:$AB$187,Communes!$C$5:$C$187,A11) -> 1 | Z11: =SUMIFS(Communes!$AC$5:$AC$187,Communes!$C$5:$C$187,A11) -> 4 | AA11: =SUMIFS(Communes!$AD$5:$AD$187,Communes!$C$5:$C$187,A11) -> 1 | AB11: =SUMIFS(Communes!$AE$5:$AE$187,Communes!$C$5:$C$187,A11) -> 15 | AC11: =SUMIFS(Communes!$AF$5:$AF$187,Communes!$C$5:$C$187,A11) -> 18 | AD11: =SUMIFS(Communes!$AG$5:$AG$187,Communes!$C$5:$C$187,A11) -> 17 | AE11: =SUMIFS(Communes!$AH$5:$AH$187,Communes!$C$5:$C$187,A11) -> 18 | AF11: =SUMIFS(Communes!$AI$5:$AI$187,Communes!$C$5:$C$187,A11) -> 18 | AG11: =SUMIFS(Communes!$AJ$5:$AJ$187,Communes!$C$5:$C$187,A11) -> 7547 | AH11: =SUMIFS(Communes!$AK$5:$AK$187,Communes!$C$5:$C$187,A11) -> 8893 | AI11: =SUMIFS(Communes!$AL$5:$AL$187,Communes!$C$5:$C$187,A11) -> 8210 | AJ11: =SUMIFS(Communes!$AM$5:$AM$187,Communes!$C$5:$C$187,A11) -> 7595 | AK11: =SUMIFS(Communes!$AN$5:$AN$187,Communes!$C$5:$C$187,A11) -> 9916 | AL11: =SUMIFS(Communes!$AO$5:$AO$187,Communes!$C$5:$C$187,A11) -> 10269 | AM11: =SUMIFS(Communes!$AP$5:$AP$187,Communes!$C$5:$C$187,A11) -> 10428 | AN11: =F11+G11 -> 10428 | AO11: =IF(AN11>0,F11/AN11,"") -> 0.50469889 | AP11: =IF((M11+N11)>0,M11/(M11+N11),"") -> 0.49206349 | AQ11: =IF(AND(ISNUMBER(AO11),ISNUMBER(AP11)),(AO11-AP11)*100,"") -> 1.2635396 | AR11: =IF(D11>0,F11/D11*1000,"") -> 80.91197 | AS11: =IF(D11>0,E11/D11*10000,"") -> 2.152323 | AT11: =IF(D11>0,T11/D11*10000,"") -> 8.1480798 | AU11: =IF(F11>0,H11/F11*100,"") -> 10.716321 | AV11: =IF(AN11>=100,"ok",IF(AN11>0,"effectif faible (<100)","aucune association")) -> ok
A12: Garges-lès-Gonesse | B12: =COUNTIF(Communes!$C$5:$C$187,A12) -> 3 | C12: =COUNTIFS(Communes!$C$5:$C$187,A12,Communes!$H$5:$H$187,0) -> 1 | D12: =SUMIFS(Communes!$G$5:$G$187,Communes!$C$5:$C$187,A12) -> 57999 | E12: =SUMIFS(Communes!$H$5:$H$187,Communes!$C$5:$C$187,A12) -> 9 | F12: =SUMIFS(Communes!$I$5:$I$187,Communes!$C$5:$C$187,A12) -> 1232 | G12: =SUMIFS(Communes!$J$5:$J$187,Communes!$C$5:$C$187,A12) -> 1057 | H12: =SUMIFS(Communes!$K$5:$K$187,Communes!$C$5:$C$187,A12) -> 149 | I12: =SUMIFS(Communes!$L$5:$L$187,Communes!$C$5:$C$187,A12) -> 25 | J12: =SUMIFS(Communes!$M$5:$M$187,Communes!$C$5:$C$187,A12) -> 2 | K12: =SUMIFS(Communes!$N$5:$N$187,Communes!$C$5:$C$187,A12) -> 2 | L12: =SUMIFS(Communes!$O$5:$O$187,Communes!$C$5:$C$187,A12) -> 9 | M12: =SUMIFS(Communes!$P$5:$P$187,Communes!$C$5:$C$187,A12) -> 1283 | N12: =SUMIFS(Communes!$Q$5:$Q$187,Communes!$C$5:$C$187,A12) -> 935 | O12: =SUMIFS(Communes!$R$5:$R$187,Communes!$C$5:$C$187,A12) -> 3 | P12: =SUMIFS(Communes!$S$5:$S$187,Communes!$C$5:$C$187,A12) -> 523 | Q12: =SUMIFS(Communes!$T$5:$T$187,Communes!$C$5:$C$187,A12) -> 19 | R12: =SUMIFS(Communes!$U$5:$U$187,Communes!$C$5:$C$187,A12) -> 8 | S12: =SUMIFS(Communes!$V$5:$V$187,Communes!$C$5:$C$187,A12) -> 2 | T12: =SUMIFS(Communes!$W$5:$W$187,Communes!$C$5:$C$187,A12) -> 55 | U12: =SUMIFS(Communes!$X$5:$X$187,Communes!$C$5:$C$187,A12) -> 22 | V12: =SUMIFS(Communes!$Y$5:$Y$187,Communes!$C$5:$C$187,A12) -> 1 | W12: =SUMIFS(Communes!$Z$5:$Z$187,Communes!$C$5:$C$187,A12) -> 0 | X12: =SUMIFS(Communes!$AA$5:$AA$187,Communes!$C$5:$C$187,A12) -> 0 | Y12: =SUMIFS(Communes!$AB$5:$AB$187,Communes!$C$5:$C$187,A12) -> 0 | Z12: =SUMIFS(Communes!$AC$5:$AC$187,Communes!$C$5:$C$187,A12) -> 1 | AA12: =SUMIFS(Communes!$AD$5:$AD$187,Communes!$C$5:$C$187,A12) -> 0 | AB12: =SUMIFS(Communes!$AE$5:$AE$187,Communes!$C$5:$C$187,A12) -> 12 | AC12: =SUMIFS(Communes!$AF$5:$AF$187,Communes!$C$5:$C$187,A12) -> 11 | AD12: =SUMIFS(Communes!$AG$5:$AG$187,Communes!$C$5:$C$187,A12) -> 9 | AE12: =SUMIFS(Communes!$AH$5:$AH$187,Communes!$C$5:$C$187,A12) -> 8 | AF12: =SUMIFS(Communes!$AI$5:$AI$187,Communes!$C$5:$C$187,A12) -> 9 | AG12: =SUMIFS(Communes!$AJ$5:$AJ$187,Communes!$C$5:$C$187,A12) -> 2697 | AH12: =SUMIFS(Communes!$AK$5:$AK$187,Communes!$C$5:$C$187,A12) -> 2651 | AI12: =SUMIFS(Communes!$AL$5:$AL$187,Communes!$C$5:$C$187,A12) -> 2591 | AJ12: =SUMIFS(Communes!$AM$5:$AM$187,Communes!$C$5:$C$187,A12) -> 881 | AK12: =SUMIFS(Communes!$AN$5:$AN$187,Communes!$C$5:$C$187,A12) -> 770 | AL12: =SUMIFS(Communes!$AO$5:$AO$187,Communes!$C$5:$C$187,A12) -> 2218 | AM12: =SUMIFS(Communes!$AP$5:$AP$187,Communes!$C$5:$C$187,A12) -> 2289 | AN12: =F12+G12 -> 2289 | AO12: =IF(AN12>0,F12/AN12,"") -> 0.5382263 | AP12: =IF((M12+N12)>0,M12/(M12+N12),"") -> 0.57844905 | AQ12: =IF(AND(ISNUMBER(AO12),ISNUMBER(AP12)),(AO12-AP12)*100,"") -> -4.0222754 | AR12: =IF(D12>0,F12/D12*1000,"") -> 21.241746 | AS12: =IF(D12>0,E12/D12*10000,"") -> 1.5517509 | AT12: =IF(D12>0,T12/D12*10000,"") -> 9.4829221 | AU12: =IF(F12>0,H12/F12*100,"") -> 12.094156 | AV12: =IF(AN12>=100,"ok",IF(AN12>0,"effectif faible (<100)","aucune association")) -> ok
A13: Goussainville | B13: =COUNTIF(Communes!$C$5:$C$187,A13) -> 9 | C13: =COUNTIFS(Communes!$C$5:$C$187,A13,Communes!$H$5:$H$187,0) -> 4 | D13: =SUMIFS(Communes!$G$5:$G$187,Communes!$C$5:$C$187,A13) -> 62026 | E13: =SUMIFS(Communes!$H$5:$H$187,Communes!$C$5:$C$187,A13) -> 19 | F13: =SUMIFS(Communes!$I$5:$I$187,Communes!$C$5:$C$187,A13) -> 1544 | G13: =SUMIFS(Communes!$J$5:$J$187,Communes!$C$5:$C$187,A13) -> 1407 | H13: =SUMIFS(Communes!$K$5:$K$187,Communes!$C$5:$C$187,A13) -> 245 | I13: =SUMIFS(Communes!$L$5:$L$187,Communes!$C$5:$C$187,A13) -> 14 | J13: =SUMIFS(Communes!$M$5:$M$187,Communes!$C$5:$C$187,A13) -> 2 | K13: =SUMIFS(Communes!$N$5:$N$187,Communes!$C$5:$C$187,A13) -> 7 | L13: =SUMIFS(Communes!$O$5:$O$187,Communes!$C$5:$C$187,A13) -> 22 | M13: =SUMIFS(Communes!$P$5:$P$187,Communes!$C$5:$C$187,A13) -> 2852 | N13: =SUMIFS(Communes!$Q$5:$Q$187,Communes!$C$5:$C$187,A13) -> 3244 | O13: =SUMIFS(Communes!$R$5:$R$187,Communes!$C$5:$C$187,A13) -> 3 | P13: =SUMIFS(Communes!$S$5:$S$187,Communes!$C$5:$C$187,A13) -> 386 | Q13: =SUMIFS(Communes!$T$5:$T$187,Communes!$C$5:$C$187,A13) -> 11 | R13: =SUMIFS(Communes!$U$5:$U$187,Communes!$C$5:$C$187,A13) -> 19 | S13: =SUMIFS(Communes!$V$5:$V$187,Communes!$C$5:$C$187,A13) -> 3 | T13: =SUMIFS(Communes!$W$5:$W$187,Communes!$C$5:$C$187,A13) -> 87 | U13: =SUMIFS(Communes!$X$5:$X$187,Communes!$C$5:$C$187,A13) -> 22 | V13: =SUMIFS(Communes!$Y$5:$Y$187,Communes!$C$5:$C$187,A13) -> 4 | W13: =SUMIFS(Communes!$Z$5:$Z$187,Communes!$C$5:$C$187,A13) -> 0 | X13: =SUMIFS(Communes!$AA$5:$AA$187,Communes!$C$5:$C$187,A13) -> 1 | Y13: =SUMIFS(Communes!$AB$5:$AB$187,Communes!$C$5:$C$187,A13) -> 0 | Z13: =SUMIFS(Communes!$AC$5:$AC$187,Communes!$C$5:$C$187,A13) -> 4 | AA13: =SUMIFS(Communes!$AD$5:$AD$187,Communes!$C$5:$C$187,A13) -> 0 | AB13: =SUMIFS(Communes!$AE$5:$AE$187,Communes!$C$5:$C$187,A13) -> 20 | AC13: =SUMIFS(Communes!$AF$5:$AF$187,Communes!$C$5:$C$187,A13) -> 21 | AD13: =SUMIFS(Communes!$AG$5:$AG$187,Communes!$C$5:$C$187,A13) -> 22 | AE13: =SUMIFS(Communes!$AH$5:$AH$187,Communes!$C$5:$C$187,A13) -> 19 | AF13: =SUMIFS(Communes!$AI$5:$AI$187,Communes!$C$5:$C$187,A13) -> 17 | AG13: =SUMIFS(Communes!$AJ$5:$AJ$187,Communes!$C$5:$C$187,A13) -> 4410 | AH13: =SUMIFS(Communes!$AK$5:$AK$187,Communes!$C$5:$C$187,A13) -> 4772 | AI13: =SUMIFS(Communes!$AL$5:$AL$187,Communes!$C$5:$C$187,A13) -> 4489 | AJ13: =SUMIFS(Communes!$AM$5:$AM$187,Communes!$C$5:$C$187,A13) -> 4505 | AK13: =SUMIFS(Communes!$AN$5:$AN$187,Communes!$C$5:$C$187,A13) -> 4888 | AL13: =SUMIFS(Communes!$AO$5:$AO$187,Communes!$C$5:$C$187,A13) -> 6096 | AM13: =SUMIFS(Communes!$AP$5:$AP$187,Communes!$C$5:$C$187,A13) -> 2951 | AN13: =F13+G13 -> 2951 | AO13: =IF(AN13>0,F13/AN13,"") -> 0.52321247 | AP13: =IF((M13+N13)>0,M13/(M13+N13),"") -> 0.46784777 | AQ13: =IF(AND(ISNUMBER(AO13),ISNUMBER(AP13)),(AO13-AP13)*100,"") -> 5.5364701 | AR13: =IF(D13>0,F13/D13*1000,"") -> 24.892787 | AS13: =IF(D13>0,E13/D13*10000,"") -> 3.0632315 | AT13: =IF(D13>0,T13/D13*10000,"") -> 14.026376 | AU13: =IF(F13>0,H13/F13*100,"") -> 15.867876 | AV13: =IF(AN13>=100,"ok",IF(AN13>0,"effectif faible (<100)","aucune association")) -> ok
A14: Herblay-sur-Seine | B14: =COUNTIF(Communes!$C$5:$C$187,A14) -> 3 | C14: =COUNTIFS(Communes!$C$5:$C$187,A14,Communes!$H$5:$H$187,0) -> 0 | D14: =SUMIFS(Communes!$G$5:$G$187,Communes!$C$5:$C$187,A14) -> 58806 | E14: =SUMIFS(Communes!$H$5:$H$187,Communes!$C$5:$C$187,A14) -> 26 | F14: =SUMIFS(Communes!$I$5:$I$187,Communes!$C$5:$C$187,A14) -> 2671 | G14: =SUMIFS(Communes!$J$5:$J$187,Communes!$C$5:$C$187,A14) -> 2981 | H14: =SUMIFS(Communes!$K$5:$K$187,Communes!$C$5:$C$187,A14) -> 392 | I14: =SUMIFS(Communes!$L$5:$L$187,Communes!$C$5:$C$187,A14) -> 62 | J14: =SUMIFS(Communes!$M$5:$M$187,Communes!$C$5:$C$187,A14) -> 3 | K14: =SUMIFS(Communes!$N$5:$N$187,Communes!$C$5:$C$187,A14) -> 5 | L14: =SUMIFS(Communes!$O$5:$O$187,Communes!$C$5:$C$187,A14) -> 25 | M14: =SUMIFS(Communes!$P$5:$P$187,Communes!$C$5:$C$187,A14) -> 2309 | N14: =SUMIFS(Communes!$Q$5:$Q$187,Communes!$C$5:$C$187,A14) -> 2768 | O14: =SUMIFS(Communes!$R$5:$R$187,Communes!$C$5:$C$187,A14) -> 1 | P14: =SUMIFS(Communes!$S$5:$S$187,Communes!$C$5:$C$187,A14) -> 88 | Q14: =SUMIFS(Communes!$T$5:$T$187,Communes!$C$5:$C$187,A14) -> 4 | R14: =SUMIFS(Communes!$U$5:$U$187,Communes!$C$5:$C$187,A14) -> 27 | S14: =SUMIFS(Communes!$V$5:$V$187,Communes!$C$5:$C$187,A14) -> 1 | T14: =SUMIFS(Communes!$W$5:$W$187,Communes!$C$5:$C$187,A14) -> 38 | U14: =SUMIFS(Communes!$X$5:$X$187,Communes!$C$5:$C$187,A14) -> 17 | V14: =SUMIFS(Communes!$Y$5:$Y$187,Communes!$C$5:$C$187,A14) -> 1 | W14: =SUMIFS(Communes!$Z$5:$Z$187,Communes!$C$5:$C$187,A14) -> 0 | X14: =SUMIFS(Communes!$AA$5:$AA$187,Communes!$C$5:$C$187,A14) -> 1 | Y14: =SUMIFS(Communes!$AB$5:$AB$187,Communes!$C$5:$C$187,A14) -> 1 | Z14: =SUMIFS(Communes!$AC$5:$AC$187,Communes!$C$5:$C$187,A14) -> 1 | AA14: =SUMIFS(Communes!$AD$5:$AD$187,Communes!$C$5:$C$187,A14) -> 0 | AB14: =SUMIFS(Communes!$AE$5:$AE$187,Communes!$C$5:$C$187,A14) -> 22 | AC14: =SUMIFS(Communes!$AF$5:$AF$187,Communes!$C$5:$C$187,A14) -> 22 | AD14: =SUMIFS(Communes!$AG$5:$AG$187,Communes!$C$5:$C$187,A14) -> 22 | AE14: =SUMIFS(Communes!$AH$5:$AH$187,Communes!$C$5:$C$187,A14) -> 21 | AF14: =SUMIFS(Communes!$AI$5:$AI$187,Communes!$C$5:$C$187,A14) -> 24 | AG14: =SUMIFS(Communes!$AJ$5:$AJ$187,Communes!$C$5:$C$187,A14) -> 5344 | AH14: =SUMIFS(Communes!$AK$5:$AK$187,Communes!$C$5:$C$187,A14) -> 4792 | AI14: =SUMIFS(Communes!$AL$5:$AL$187,Communes!$C$5:$C$187,A14) -> 4600 | AJ14: =SUMIFS(Communes!$AM$5:$AM$187,Communes!$C$5:$C$187,A14) -> 3947 | AK14: =SUMIFS(Communes!$AN$5:$AN$187,Communes!$C$5:$C$187,A14) -> 4495 | AL14: =SUMIFS(Communes!$AO$5:$AO$187,Communes!$C$5:$C$187,A14) -> 5077 | AM14: =SUMIFS(Communes!$AP$5:$AP$187,Communes!$C$5:$C$187,A14) -> 5652 | AN14: =F14+G14 -> 5652 | AO14: =IF(AN14>0,F14/AN14,"") -> 0.47257608 | AP14: =IF((M14+N14)>0,M14/(M14+N14),"") -> 0.45479614 | AQ14: =IF(AND(ISNUMBER(AO14),ISNUMBER(AP14)),(AO14-AP14)*100,"") -> 1.777994 | AR14: =IF(D14>0,F14/D14*1000,"") -> 45.420535 | AS14: =IF(D14>0,E14/D14*10000,"") -> 4.4213176 | AT14: =IF(D14>0,T14/D14*10000,"") -> 6.4619257 | AU14: =IF(F14>0,H14/F14*100,"") -> 14.676151 | AV14: =IF(AN14>=100,"ok",IF(AN14>0,"effectif faible (<100)","aucune association")) -> ok
A15: L'Isle-Adam | B15: =COUNTIF(Communes!$C$5:$C$187,A15) -> 15 | C15: =COUNTIFS(Communes!$C$5:$C$187,A15,Communes!$H$5:$H$187,0) -> 5 | D15: =SUMIFS(Communes!$G$5:$G$187,Communes!$C$5:$C$187,A15) -> 65498 | E15: =SUMIFS(Communes!$H$5:$H$187,Communes!$C$5:$C$187,A15) -> 51 | F15: =SUMIFS(Communes!$I$5:$I$187,Communes!$C$5:$C$187,A15) -> 3616 | G15: =SUMIFS(Communes!$J$5:$J$187,Communes!$C$5:$C$187,A15) -> 5060 | H15: =SUMIFS(Communes!$K$5:$K$187,Communes!$C$5:$C$187,A15) -> 852 | I15: =SUMIFS(Communes!$L$5:$L$187,Communes!$C$5:$C$187,A15) -> 61 | J15: =SUMIFS(Communes!$M$5:$M$187,Communes!$C$5:$C$187,A15) -> 17 | K15: =SUMIFS(Communes!$N$5:$N$187,Communes!$C$5:$C$187,A15) -> 9 | L15: =SUMIFS(Communes!$O$5:$O$187,Communes!$C$5:$C$187,A15) -> 50 | M15: =SUMIFS(Communes!$P$5:$P$187,Communes!$C$5:$C$187,A15) -> 3373 | N15: =SUMIFS(Communes!$Q$5:$Q$187,Communes!$C$5:$C$187,A15) -> 4993 | O15: =SUMIFS(Communes!$R$5:$R$187,Communes!$C$5:$C$187,A15) -> 8 | P15: =SUMIFS(Communes!$S$5:$S$187,Communes!$C$5:$C$187,A15) -> 1509 | Q15: =SUMIFS(Communes!$T$5:$T$187,Communes!$C$5:$C$187,A15) -> 48 | R15: =SUMIFS(Communes!$U$5:$U$187,Communes!$C$5:$C$187,A15) -> 53 | S15: =SUMIFS(Communes!$V$5:$V$187,Communes!$C$5:$C$187,A15) -> 8 | T15: =SUMIFS(Communes!$W$5:$W$187,Communes!$C$5:$C$187,A15) -> 115 | U15: =SUMIFS(Communes!$X$5:$X$187,Communes!$C$5:$C$187,A15) -> 21 | V15: =SUMIFS(Communes!$Y$5:$Y$187,Communes!$C$5:$C$187,A15) -> 3 | W15: =SUMIFS(Communes!$Z$5:$Z$187,Communes!$C$5:$C$187,A15) -> 1 | X15: =SUMIFS(Communes!$AA$5:$AA$187,Communes!$C$5:$C$187,A15) -> 3 | Y15: =SUMIFS(Communes!$AB$5:$AB$187,Communes!$C$5:$C$187,A15) -> 3 | Z15: =SUMIFS(Communes!$AC$5:$AC$187,Communes!$C$5:$C$187,A15) -> 2 | AA15: =SUMIFS(Communes!$AD$5:$AD$187,Communes!$C$5:$C$187,A15) -> 0 | AB15: =SUMIFS(Communes!$AE$5:$AE$187,Communes!$C$5:$C$187,A15) -> 46 | AC15: =SUMIFS(Communes!$AF$5:$AF$187,Communes!$C$5:$C$187,A15) -> 53 | AD15: =SUMIFS(Communes!$AG$5:$AG$187,Communes!$C$5:$C$187,A15) -> 54 | AE15: =SUMIFS(Communes!$AH$5:$AH$187,Communes!$C$5:$C$187,A15) -> 51 | AF15: =SUMIFS(Communes!$AI$5:$AI$187,Communes!$C$5:$C$187,A15) -> 53 | AG15: =SUMIFS(Communes!$AJ$5:$AJ$187,Communes!$C$5:$C$187,A15) -> 6565 | AH15: =SUMIFS(Communes!$AK$5:$AK$187,Communes!$C$5:$C$187,A15) -> 7253 | AI15: =SUMIFS(Communes!$AL$5:$AL$187,Communes!$C$5:$C$187,A15) -> 6680 | AJ15: =SUMIFS(Communes!$AM$5:$AM$187,Communes!$C$5:$C$187,A15) -> 7184 | AK15: =SUMIFS(Communes!$AN$5:$AN$187,Communes!$C$5:$C$187,A15) -> 7194 | AL15: =SUMIFS(Communes!$AO$5:$AO$187,Communes!$C$5:$C$187,A15) -> 8366 | AM15: =SUMIFS(Communes!$AP$5:$AP$187,Communes!$C$5:$C$187,A15) -> 8676 | AN15: =F15+G15 -> 8676 | AO15: =IF(AN15>0,F15/AN15,"") -> 0.41678193 | AP15: =IF((M15+N15)>0,M15/(M15+N15),"") -> 0.40317954 | AQ15: =IF(AND(ISNUMBER(AO15),ISNUMBER(AP15)),(AO15-AP15)*100,"") -> 1.3602391 | AR15: =IF(D15>0,F15/D15*1000,"") -> 55.207793 | AS15: =IF(D15>0,E15/D15*10000,"") -> 7.7864973 | AT15: =IF(D15>0,T15/D15*10000,"") -> 17.557788 | AU15: =IF(F15>0,H15/F15*100,"") -> 23.561947 | AV15: =IF(AN15>=100,"ok",IF(AN15>0,"effectif faible (<100)","aucune association")) -> ok
A16: Montmorency | B16: =COUNTIF(Communes!$C$5:$C$187,A16) -> 5 | C16: =COUNTIFS(Communes!$C$5:$C$187,A16,Communes!$H$5:$H$187,0) -> 1 | D16: =SUMIFS(Communes!$G$5:$G$187,Communes!$C$5:$C$187,A16) -> 56957 | E16: =SUMIFS(Communes!$H$5:$H$187,Communes!$C$5:$C$187,A16) -> 28 | F16: =SUMIFS(Communes!$I$5:$I$187,Communes!$C$5:$C$187,A16) -> 2251 | G16: =SUMIFS(Communes!$J$5:$J$187,Communes!$C$5:$C$187,A16) -> 3644 | H16: =SUMIFS(Communes!$K$5:$K$187,Communes!$C$5:$C$187,A16) -> 641 | I16: =SUMIFS(Communes!$L$5:$L$187,Communes!$C$5:$C$187,A16) -> 38 | J16: =SUMIFS(Communes!$M$5:$M$187,Communes!$C$5:$C$187,A16) -> 6 | K16: =SUMIFS(Communes!$N$5:$N$187,Communes!$C$5:$C$187,A16) -> 5 | L16: =SUMIFS(Communes!$O$5:$O$187,Communes!$C$5:$C$187,A16) -> 28 | M16: =SUMIFS(Communes!$P$5:$P$187,Communes!$C$5:$C$187,A16) -> 2332 | N16: =SUMIFS(Communes!$Q$5:$Q$187,Communes!$C$5:$C$187,A16) -> 4002 | O16: =SUMIFS(Communes!$R$5:$R$187,Communes!$C$5:$C$187,A16) -> 2 | P16: =SUMIFS(Communes!$S$5:$S$187,Communes!$C$5:$C$187,A16) -> 276 | Q16: =SUMIFS(Communes!$T$5:$T$187,Communes!$C$5:$C$187,A16) -> 7 | R16: =SUMIFS(Communes!$U$5:$U$187,Communes!$C$5:$C$187,A16) -> 29 | S16: =SUMIFS(Communes!$V$5:$V$187,Communes!$C$5:$C$187,A16) -> 2 | T16: =SUMIFS(Communes!$W$5:$W$187,Communes!$C$5:$C$187,A16) -> 59 | U16: =SUMIFS(Communes!$X$5:$X$187,Communes!$C$5:$C$187,A16) -> 21 | V16: =SUMIFS(Communes!$Y$5:$Y$187,Communes!$C$5:$C$187,A16) -> 2 | W16: =SUMIFS(Communes!$Z$5:$Z$187,Communes!$C$5:$C$187,A16) -> 1 | X16: =SUMIFS(Communes!$AA$5:$AA$187,Communes!$C$5:$C$187,A16) -> 2 | Y16: =SUMIFS(Communes!$AB$5:$AB$187,Communes!$C$5:$C$187,A16) -> 3 | Z16: =SUMIFS(Communes!$AC$5:$AC$187,Communes!$C$5:$C$187,A16) -> 1 | AA16: =SUMIFS(Communes!$AD$5:$AD$187,Communes!$C$5:$C$187,A16) -> 0 | AB16: =SUMIFS(Communes!$AE$5:$AE$187,Communes!$C$5:$C$187,A16) -> 22 | AC16: =SUMIFS(Communes!$AF$5:$AF$187,Communes!$C$5:$C$187,A16) -> 25 | AD16: =SUMIFS(Communes!$AG$5:$AG$187,Communes!$C$5:$C$187,A16) -> 26 | AE16: =SUMIFS(Communes!$AH$5:$AH$187,Communes!$C$5:$C$187,A16) -> 28 | AF16: =SUMIFS(Communes!$AI$5:$AI$187,Communes!$C$5:$C$187,A16) -> 29 | AG16: =SUMIFS(Communes!$AJ$5:$AJ$187,Communes!$C$5:$C$187,A16) -> 4206 | AH16: =SUMIFS(Communes!$AK$5:$AK$187,Communes!$C$5:$C$187,A16) -> 5029 | AI16: =SUMIFS(Communes!$AL$5:$AL$187,Communes!$C$5:$C$187,A16) -> 4642 | AJ16: =SUMIFS(Communes!$AM$5:$AM$187,Communes!$C$5:$C$187,A16) -> 5276 | AK16: =SUMIFS(Communes!$AN$5:$AN$187,Communes!$C$5:$C$187,A16) -> 5969 | AL16: =SUMIFS(Communes!$AO$5:$AO$187,Communes!$C$5:$C$187,A16) -> 6334 | AM16: =SUMIFS(Communes!$AP$5:$AP$187,Communes!$C$5:$C$187,A16) -> 5895 | AN16: =F16+G16 -> 5895 | AO16: =IF(AN16>0,F16/AN16,"") -> 0.38184902 | AP16: =IF((M16+N16)>0,M16/(M16+N16),"") -> 0.36817177 | AQ16: =IF(AND(ISNUMBER(AO16),ISNUMBER(AP16)),(AO16-AP16)*100,"") -> 1.3677253 | AR16: =IF(D16>0,F16/D16*1000,"") -> 39.521042 | AS16: =IF(D16>0,E16/D16*10000,"") -> 4.9159893 | AT16: =IF(D16>0,T16/D16*10000,"") -> 10.358692 | AU16: =IF(F16>0,H16/F16*100,"") -> 28.476233 | AV16: =IF(AN16>=100,"ok",IF(AN16>0,"effectif faible (<100)","aucune association")) -> ok
... A22: Villiers-le-Bel | B22: =COUNTIF(Communes!$C$5:$C$187,A22) -> 7 | C22: =COUNTIFS(Communes!$C$5:$C$187,A22,Communes!$H$5:$H$187,0) -> 2 | D22: =SUMIFS(Communes!$G$5:$G$187,Communes!$C$5:$C$187,A22) -> 65514 | E22: =SUMIFS(Communes!$H$5:$H$187,Communes!$C$5:$C$187,A22) -> 22 | F22: =SUMIFS(Communes!$I$5:$I$187,Communes!$C$5:$C$187,A22) -> 1606 | G22: =SUMIFS(Communes!$J$5:$J$187,Communes!$C$5:$C$187,A22) -> 2688 | H22: =SUMIFS(Communes!$K$5:$K$187,Communes!$C$5:$C$187,A22) -> 292 | I22: =SUMIFS(Communes!$L$5:$L$187,Communes!$C$5:$C$187,A22) -> 39 | J22: =SUMIFS(Communes!$M$5:$M$187,Communes!$C$5:$C$187,A22) -> 3 | K22: =SUMIFS(Communes!$N$5:$N$187,Communes!$C$5:$C$187,A22) -> 3 | L22: =SUMIFS(Communes!$O$5:$O$187,Communes!$C$5:$C$187,A22) -> 23 | M22: =SUMIFS(Communes!$P$5:$P$187,Communes!$C$5:$C$187,A22) -> 1424 | N22: =SUMIFS(Communes!$Q$5:$Q$187,Communes!$C$5:$C$187,A22) -> 1836 | O22: =SUMIFS(Communes!$R$5:$R$187,Communes!$C$5:$C$187,A22) -> 5 | P22: =SUMIFS(Communes!$S$5:$S$187,Communes!$C$5:$C$187,A22) -> 693 | Q22: =SUMIFS(Communes!$T$5:$T$187,Communes!$C$5:$C$187,A22) -> 31 | R22: =SUMIFS(Communes!$U$5:$U$187,Communes!$C$5:$C$187,A22) -> 23 | S22: =SUMIFS(Communes!$V$5:$V$187,Communes!$C$5:$C$187,A22) -> 5 | T22: =SUMIFS(Communes!$W$5:$W$187,Communes!$C$5:$C$187,A22) -> 86 | U22: =SUMIFS(Communes!$X$5:$X$187,Communes!$C$5:$C$187,A22) -> 35 | V22: =SUMIFS(Communes!$Y$5:$Y$187,Communes!$C$5:$C$187,A22) -> 4 | W22: =SUMIFS(Communes!$Z$5:$Z$187,Communes!$C$5:$C$187,A22) -> 3 | X22: =SUMIFS(Communes!$AA$5:$AA$187,Communes!$C$5:$C$187,A22) -> 2 | Y22: =SUMIFS(Communes!$AB$5:$AB$187,Communes!$C$5:$C$187,A22) -> 2 | Z22: =SUMIFS(Communes!$AC$5:$AC$187,Communes!$C$5:$C$187,A22) -> 4 | AA22: =SUMIFS(Communes!$AD$5:$AD$187,Communes!$C$5:$C$187,A22) -> 0 | AB22: =SUMIFS(Communes!$AE$5:$AE$187,Communes!$C$5:$C$187,A22) -> 20 | AC22: =SUMIFS(Communes!$AF$5:$AF$187,Communes!$C$5:$C$187,A22) -> 19 | AD22: =SUMIFS(Communes!$AG$5:$AG$187,Communes!$C$5:$C$187,A22) -> 22 | AE22: =SUMIFS(Communes!$AH$5:$AH$187,Communes!$C$5:$C$187,A22) -> 24 | AF22: =SUMIFS(Communes!$AI$5:$AI$187,Communes!$C$5:$C$187,A22) -> 22 | AG22: =SUMIFS(Communes!$AJ$5:$AJ$187,Communes!$C$5:$C$187,A22) -> 3784 | AH22: =SUMIFS(Communes!$AK$5:$AK$187,Communes!$C$5:$C$187,A22) -> 4079 | AI22: =SUMIFS(Communes!$AL$5:$AL$187,Communes!$C$5:$C$187,A22) -> 4664 | AJ22: =SUMIFS(Communes!$AM$5:$AM$187,Communes!$C$5:$C$187,A22) -> 3505 | AK22: =SUMIFS(Communes!$AN$5:$AN$187,Communes!$C$5:$C$187,A22) -> 3733 | AL22: =SUMIFS(Communes!$AO$5:$AO$187,Communes!$C$5:$C$187,A22) -> 3260 | AM22: =SUMIFS(Communes!$AP$5:$AP$187,Communes!$C$5:$C$187,A22) -> 4294 | AN22: =F22+G22 -> 4294 | AO22: =IF(AN22>0,F22/AN22,"") -> 0.37401025 | AP22: =IF((M22+N22)>0,M22/(M22+N22),"") -> 0.43680982 | AQ22: =IF(AND(ISNUMBER(AO22),ISNUMBER(AP22)),(AO22-AP22)*100,"") -> -6.2799569 | AR22: =IF(D22>0,F22/D22*1000,"") -> 24.513844 | AS22: =IF(D22>0,E22/D22*10000,"") -> 3.3580609 | AT22: =IF(D22>0,T22/D22*10000,"") -> 13.126965 | AU22: =IF(F22>0,H22/F22*100,"") -> 18.181818 | AV22: =IF(AN22>=100,"ok",IF(AN22>0,"effectif faible (<100)","aucune association")) -> ok
A23: Total Val d'Oise | B23: =SUM(B5:B22) -> 183 | C23: =SUM(C5:C22) -> 78 | D23: =SUM(D5:D22) -> 1281653 | E23: =SUM(E5:E22) -> 551 | F23: =SUM(F5:F22) -> 68623 | G23: =SUM(G5:G22) -> 91352 | H23: =SUM(H5:H22) -> 11261 | I23: =SUM(I5:I22) -> 1285 | ... AM23: =SUM(AM5:AM22) -> 159975 | AN23: =F23+G23 -> 159975 | AO23: =IF(AN23>0,F23/AN23,"") -> 0.42896078 | AP23: =IF((M23+N23)>0,M23/(M23+N23),"") -> 0.42882683 | AQ23: =IF(AND(ISNUMBER(AO23),ISNUMBER(AP23)),(AO23-AP23)*100,"") -> 0.01339426 | AR23: =IF(D23>0,F23/D23*1000,"") -> 53.542574 | AS23: =IF(D23>0,E23/D23*10000,"") -> 4.2991356 | AT23: =IF(D23>0,T23/D23*10000,"") -> 12.03914 | AU23: =IF(F23>0,H23/F23*100,"") -> 16.40995 | AV23: =IF(AN23>=100,"ok",IF(AN23>0,"effectif faible (<100)","aucune association")) -> ok

Sheet EPCI
A1: Indicateurs par EPCI
A2: Sommes calculées par SUMIFS sur l'onglet Communes ; ratios par formule.
A4: EPCI | B4: Nb communes | C4: Communes sans asso. civile aidée | D4: Population | E4: Asso. civiles 2025 | F4: Adhérentes F 2025 | G4: Adhérents H 2025 | H4: Bénévoles F 2025 | I4: Salariées F 2025 | J4: Asso. <20 % F (2025) | K4: Asso. ≥60 % F (2025) | L4: Asso. civiles 2024 | M4: Adhérentes F 2024 | N4: Adhérents H 2024 | O4: Asso. scolaires 2025 | P4: Licencié·es scolaires 2025 (libellé F) | Q4: Sections scolaires 2025 | R4: Asso. civiles subventionnées 2025 | S4: Asso. scolaires subventionnées 2025 | T4: Lieux de pratique | U4: dont établissements scolaires | V4: dont piscines | W4: Manifestations 2023 | X4: Manifestations 2024 | Y4: Manifestations 2025 | Z4: Sections sportives scolaires 2026-27 | AA4: dont sections féminines | AB4: Asso. civiles 2019 | AC4: Asso. civiles 2020 | AD4: Asso. civiles 2021 | AE4: Asso. civiles 2022 | AF4: Asso. civiles 2023 | AG4: Licencié·es / adhérent·es 2019 | AH4: Licencié·es / adhérent·es 2020 | AI4: Licencié·es / adhérent·es 2021 | AJ4: Licencié·es / adhérent·es 2022 | AK4: Licencié·es / adhérent·es 2023 | AL4: Licencié·es / adhérent·es 2024 | AM4: Licencié·es / adhérent·es 2025 | AN4: Adhérent·es total 2025 | AO4: Part F 2025 | AP4: Part F 2024 | AQ4: Évolution part F (points) | AR4: Adhérentes F pour 1 000 hab. | AS4: Asso. civiles pour 10 000 hab. | AT4: Lieux pour 10 000 hab. | AU4: Bénévoles F pour 100 adhérentes | AV4: Fiabilité part F
A5: CA Plaine Vallée | B5: =COUNTIF(Communes!$E$5:$E$187,A5) -> 18 | C5: =COUNTIFS(Communes!$E$5:$E$187,A5,Communes!$H$5:$H$187,0) -> 4 | D5: =SUMIFS(Communes!$G$5:$G$187,Communes!$E$5:$E$187,A5) -> 187112 | E5: =SUMIFS(Communes!$H$5:$H$187,Communes!$E$5:$E$187,A5) -> 74 | F5: =SUMIFS(Communes!$I$5:$I$187,Communes!$E$5:$E$187,A5) -> 8116 | G5: =SUMIFS(Communes!$J$5:$J$187,Communes!$E$5:$E$187,A5) -> 13316 | H5: =SUMIFS(Communes!$K$5:$K$187,Communes!$E$5:$E$187,A5) -> 1829 | I5: =SUMIFS(Communes!$L$5:$L$187,Communes!$E$5:$E$187,A5) -> 177 | J5: =SUMIFS(Communes!$M$5:$M$187,Communes!$E$5:$E$187,A5) -> 17 | K5: =SUMIFS(Communes!$N$5:$N$187,Communes!$E$5:$E$187,A5) -> 14 | L5: =SUMIFS(Communes!$O$5:$O$187,Communes!$E$5:$E$187,A5) -> 76 | M5: =SUMIFS(Communes!$P$5:$P$187,Communes!$E$5:$E$187,A5) -> 8463 | N5: =SUMIFS(Communes!$Q$5:$Q$187,Communes!$E$5:$E$187,A5) -> 13423 | O5: =SUMIFS(Communes!$R$5:$R$187,Communes!$E$5:$E$187,A5) -> 11 | P5: =SUMIFS(Communes!$S$5:$S$187,Communes!$E$5:$E$187,A5) -> 1603 | Q5: =SUMIFS(Communes!$T$5:$T$187,Communes!$E$5:$E$187,A5) -> 43 | R5: =SUMIFS(Communes!$U$5:$U$187,Communes!$E$5:$E$187,A5) -> 78 | S5: =SUMIFS(Communes!$V$5:$V$187,Communes!$E$5:$E$187,A5) -> 11 | T5: =SUMIFS(Communes!$W$5:$W$187,Communes!$E$5:$E$187,A5) -> 185 | U5: =SUMIFS(Communes!$X$5:$X$187,Communes!$E$5:$E$187,A5) -> 48 | V5: =SUMIFS(Communes!$Y$5:$Y$187,Communes!$E$5:$E$187,A5) -> 3 | W5: =SUMIFS(Communes!$Z$5:$Z$187,Communes!$E$5:$E$187,A5) -> 5 | X5: =SUMIFS(Communes!$AA$5:$AA$187,Communes!$E$5:$E$187,A5) -> 4 | Y5: =SUMIFS(Communes!$AB$5:$AB$187,Communes!$E$5:$E$187,A5) -> 7 | Z5: =SUMIFS(Communes!$AC$5:$AC$187,Communes!$E$5:$E$187,A5) -> 4 | AA5: =SUMIFS(Communes!$AD$5:$AD$187,Communes!$E$5:$E$187,A5) -> 0 | AB5: =SUMIFS(Communes!$AE$5:$AE$187,Communes!$E$5:$E$187,A5) -> 75 | AC5: =SUMIFS(Communes!$AF$5:$AF$187,Communes!$E$5:$E$187,A5) -> 78 | AD5: =SUMIFS(Communes!$AG$5:$AG$187,Communes!$E$5:$E$187,A5) -> 83 | AE5: =SUMIFS(Communes!$AH$5:$AH$187,Communes!$E$5:$E$187,A5) -> 77 | AF5: =SUMIFS(Communes!$AI$5:$AI$187,Communes!$E$5:$E$187,A5) -> 76 | AG5: =SUMIFS(Communes!$AJ$5:$AJ$187,Communes!$E$5:$E$187,A5) -> 18453 | AH5: =SUMIFS(Communes!$AK$5:$AK$187,Communes!$E$5:$E$187,A5) -> 18826 | AI5: =SUMIFS(Communes!$AL$5:$AL$187,Communes!$E$5:$E$187,A5) -> 18285 | AJ5: =SUMIFS(Communes!$AM$5:$AM$187,Communes!$E$5:$E$187,A5) -> 18023 | AK5: =SUMIFS(Communes!$AN$5:$AN$187,Communes!$E$5:$E$187,A5) -> 19162 | AL5: =SUMIFS(Communes!$AO$5:$AO$187,Communes!$E$5:$E$187,A5) -> 21886 | AM5: =SUMIFS(Communes!$AP$5:$AP$187,Communes!$E$5:$E$187,A5) -> 21432 | AN5: =F5+G5 -> 21432 | AO5: =IF(AN5>0,F5/AN5,"") -> 0.37868608 | AP5: =IF((M5+N5)>0,M5/(M5+N5),"") -> 0.38668555 | AQ5: =IF(AND(ISNUMBER(AO5),ISNUMBER(AP5)),(AO5-AP5)*100,"") -> -0.79994755 | AR5: =IF(D5>0,F5/D5*1000,"") -> 43.375091 | AS5: =IF(D5>0,E5/D5*10000,"") -> 3.9548506 | AT5: =IF(D5>0,T5/D5*10000,"") -> 9.8871264 | AU5: =IF(F5>0,H5/F5*100,"") -> 22.535732 | AV5: =IF(AN5>=100,"ok",IF(AN5>0,"effectif faible (<100)","aucune association")) -> ok
A6: CA Roissy Pays de France | B6: =COUNTIF(Communes!$E$5:$E$187,A6) -> 25 | C6: =COUNTIFS(Communes!$E$5:$E$187,A6,Communes!$H$5:$H$187,0) -> 7 | D6: =SUMIFS(Communes!$G$5:$G$187,Communes!$E$5:$E$187,A6) -> 269382 | E6: =SUMIFS(Communes!$H$5:$H$187,Communes!$E$5:$E$187,A6) -> 92 | F6: =SUMIFS(Communes!$I$5:$I$187,Communes!$E$5:$E$187,A6) -> 11938 | G6: =SUMIFS(Communes!$J$5:$J$187,Communes!$E$5:$E$187,A6) -> 16668 | H6: =SUMIFS(Communes!$K$5:$K$187,Communes!$E$5:$E$187,A6) -> 1426 | I6: =SUMIFS(Communes!$L$5:$L$187,Communes!$E$5:$E$187,A6) -> 180 | J6: =SUMIFS(Communes!$M$5:$M$187,Communes!$E$5:$E$187,A6) -> 14 | K6: =SUMIFS(Communes!$N$5:$N$187,Communes!$E$5:$E$187,A6) -> 28 | L6: =SUMIFS(Communes!$O$5:$O$187,Communes!$E$5:$E$187,A6) -> 93 | M6: =SUMIFS(Communes!$P$5:$P$187,Communes!$E$5:$E$187,A6) -> 13271 | N6: =SUMIFS(Communes!$Q$5:$Q$187,Communes!$E$5:$E$187,A6) -> 17717 | O6: =SUMIFS(Communes!$R$5:$R$187,Communes!$E$5:$E$187,A6) -> 19 | P6: =SUMIFS(Communes!$S$5:$S$187,Communes!$E$5:$E$187,A6) -> 2826 | Q6: =SUMIFS(Communes!$T$5:$T$187,Communes!$E$5:$E$187,A6) -> 100 | R6: =SUMIFS(Communes!$U$5:$U$187,Communes!$E$5:$E$187,A6) -> 92 | S6: =SUMIFS(Communes!$V$5:$V$187,Communes!$E$5:$E$187,A6) -> 18 | T6: =SUMIFS(Communes!$W$5:$W$187,Communes!$E$5:$E$187,A6) -> 299 | U6: =SUMIFS(Communes!$X$5:$X$187,Communes!$E$5:$E$187,A6) -> 93 | V6: =SUMIFS(Communes!$Y$5:$Y$187,Communes!$E$5:$E$187,A6) -> 11 | W6: =SUMIFS(Communes!$Z$5:$Z$187,Communes!$E$5:$E$187,A6) -> 4 | X6: =SUMIFS(Communes!$AA$5:$AA$187,Communes!$E$5:$E$187,A6) -> 5 | Y6: =SUMIFS(Communes!$AB$5:$AB$187,Communes!$E$5:$E$187,A6) -> 6 | Z6: =SUMIFS(Communes!$AC$5:$AC$187,Communes!$E$5:$E$187,A6) -> 15 | AA6: =SUMIFS(Communes!$AD$5:$AD$187,Communes!$E$5:$E$187,A6) -> 0 | AB6: =SUMIFS(Communes!$AE$5:$AE$187,Communes!$E$5:$E$187,A6) -> 88 | AC6: =SUMIFS(Communes!$AF$5:$AF$187,Communes!$E$5:$E$187,A6) -> 92 | AD6: =SUMIFS(Communes!$AG$5:$AG$187,Communes!$E$5:$E$187,A6) -> 96 | AE6: =SUMIFS(Communes!$AH$5:$AH$187,Communes!$E$5:$E$187,A6) -> 92 | AF6: =SUMIFS(Communes!$AI$5:$AI$187,Communes!$E$5:$E$187,A6) -> 87 | AG6: =SUMIFS(Communes!$AJ$5:$AJ$187,Communes!$E$5:$E$187,A6) -> 27609 | AH6: =SUMIFS(Communes!$AK$5:$AK$187,Communes!$E$5:$E$187,A6) -> 26605 | AI6: =SUMIFS(Communes!$AL$5:$AL$187,Communes!$E$5:$E$187,A6) -> 26537 | AJ6: =SUMIFS(Communes!$AM$5:$AM$187,Communes!$E$5:$E$187,A6) -> 23295 | AK6: =SUMIFS(Communes!$AN$5:$AN$187,Communes!$E$5:$E$187,A6) -> 26940 | AL6: =SUMIFS(Communes!$AO$5:$AO$187,Communes!$E$5:$E$187,A6) -> 30988 | AM6: =SUMIFS(Communes!$AP$5:$AP$187,Communes!$E$5:$E$187,A6) -> 28606 | AN6: =F6+G6 -> 28606 | AO6: =IF(AN6>0,F6/AN6,"") -> 0.41732504 | AP6: =IF((M6+N6)>0,M6/(M6+N6),"") -> 0.42826255 | AQ6: =IF(AND(ISNUMBER(AO6),ISNUMBER(AP6)),(AO6-AP6)*100,"") -> -1.0937517 | AR6: =IF(D6>0,F6/D6*1000,"") -> 44.31625 | AS6: =IF(D6>0,E6/D6*10000,"") -> 3.4152245 | AT6: =IF(D6>0,T6/D6*10000,"") -> 11.09948 | AU6: =IF(F6>0,H6/F6*100,"") -> 11.945049 | AV6: =IF(AN6>=100,"ok",IF(AN6>0,"effectif faible (<100)","aucune association")) -> ok
A7: CA Saint Germain Boucles de Seine | B7: =COUNTIF(Communes!$E$5:$E$187,A7) -> 1 | C7: =COUNTIFS(Communes!$E$5:$E$187,A7,Communes!$H$5:$H$187,0) -> 0 | D7: =SUMIFS(Communes!$G$5:$G$187,Communes!$E$5:$E$187,A7) -> 36434 | E7: =SUMIFS(Communes!$H$5:$H$187,Communes!$E$5:$E$187,A7) -> 2 | F7: =SUMIFS(Communes!$I$5:$I$187,Communes!$E$5:$E$187,A7) -> 1246 | G7: =SUMIFS(Communes!$J$5:$J$187,Communes!$E$5:$E$187,A7) -> 1833 | H7: =SUMIFS(Communes!$K$5:$K$187,Communes!$E$5:$E$187,A7) -> 310 | I7: =SUMIFS(Communes!$L$5:$L$187,Communes!$E$5:$E$187,A7) -> 22 | J7: =SUMIFS(Communes!$M$5:$M$187,Communes!$E$5:$E$187,A7) -> 1 | K7: =SUMIFS(Communes!$N$5:$N$187,Communes!$E$5:$E$187,A7) -> 0 | L7: =SUMIFS(Communes!$O$5:$O$187,Communes!$E$5:$E$187,A7) -> 2 | M7: =SUMIFS(Communes!$P$5:$P$187,Communes!$E$5:$E$187,A7) -> 1087 | N7: =SUMIFS(Communes!$Q$5:$Q$187,Communes!$E$5:$E$187,A7) -> 1906 | O7: =SUMIFS(Communes!$R$5:$R$187,Communes!$E$5:$E$187,A7) -> 1 | P7: =SUMIFS(Communes!$S$5:$S$187,Communes!$E$5:$E$187,A7) -> 234 | Q7: =SUMIFS(Communes!$T$5:$T$187,Communes!$E$5:$E$187,A7) -> 7 | R7: =SUMIFS(Communes!$U$5:$U$187,Communes!$E$5:$E$187,A7) -> 2 | S7: =SUMIFS(Communes!$V$5:$V$187,Communes!$E$5:$E$187,A7) -> 1 | T7: =SUMIFS(Communes!$W$5:$W$187,Communes!$E$5:$E$187,A7) -> 22 | U7: =SUMIFS(Communes!$X$5:$X$187,Communes!$E$5:$E$187,A7) -> 3 | V7: =SUMIFS(Communes!$Y$5:$Y$187,Communes!$E$5:$E$187,A7) -> 0 | W7: =SUMIFS(Communes!$Z$5:$Z$187,Communes!$E$5:$E$187,A7) -> 1 | X7: =SUMIFS(Communes!$AA$5:$AA$187,Communes!$E$5:$E$187,A7) -> 1 | Y7: =SUMIFS(Communes!$AB$5:$AB$187,Communes!$E$5:$E$187,A7) -> 1 | Z7: =SUMIFS(Communes!$AC$5:$AC$187,Communes!$E$5:$E$187,A7) -> 1 | AA7: =SUMIFS(Communes!$AD$5:$AD$187,Communes!$E$5:$E$187,A7) -> 0 | AB7: =SUMIFS(Communes!$AE$5:$AE$187,Communes!$E$5:$E$187,A7) -> 3 | AC7: =SUMIFS(Communes!$AF$5:$AF$187,Communes!$E$5:$E$187,A7) -> 2 | AD7: =SUMIFS(Communes!$AG$5:$AG$187,Communes!$E$5:$E$187,A7) -> 2 | AE7: =SUMIFS(Communes!$AH$5:$AH$187,Communes!$E$5:$E$187,A7) -> 1 | AF7: =SUMIFS(Communes!$AI$5:$AI$187,Communes!$E$5:$E$187,A7) -> 2 | AG7: =SUMIFS(Communes!$AJ$5:$AJ$187,Communes!$E$5:$E$187,A7) -> 2334 | AH7: =SUMIFS(Communes!$AK$5:$AK$187,Communes!$E$5:$E$187,A7) -> 2196 | AI7: =SUMIFS(Communes!$AL$5:$AL$187,Communes!$E$5:$E$187,A7) -> 1861 | AJ7: =SUMIFS(Communes!$AM$5:$AM$187,Communes!$E$5:$E$187,A7) -> 2216 | AK7: =SUMIFS(Communes!$AN$5:$AN$187,Communes!$E$5:$E$187,A7) -> 2310 | AL7: =SUMIFS(Communes!$AO$5:$AO$187,Communes!$E$5:$E$187,A7) -> 2993 | AM7: =SUMIFS(Communes!$AP$5:$AP$187,Communes!$E$5:$E$187,A7) -> 3079 | AN7: =F7+G7 -> 3079 | AO7: =IF(AN7>0,F7/AN7,"") -> 0.40467684 | AP7: =IF((M7+N7)>0,M7/(M7+N7),"") -> 0.36318076 | AQ7: =IF(AND(ISNUMBER(AO7),ISNUMBER(AP7)),(AO7-AP7)*100,"") -> 4.1496088 | AR7: =IF(D7>0,F7/D7*1000,"") -> 34.198825 | AS7: =IF(D7>0,E7/D7*10000,"") -> 0.54893781 | AT7: =IF(D7>0,T7/D7*10000,"") -> 6.0383159 | AU7: =IF(F7>0,H7/F7*100,"") -> 24.879615 | AV7: =IF(AN7>=100,"ok",IF(AN7>0,"effectif faible (<100)","aucune association")) -> ok
A8: CA Val Parisis | B8: =COUNTIF(Communes!$E$5:$E$187,A8) -> 15 | C8: =COUNTIFS(Communes!$E$5:$E$187,A8,Communes!$H$5:$H$187,0) -> 0 | D8: =SUMIFS(Communes!$G$5:$G$187,Communes!$E$5:$E$187,A8) -> 290890 | E8: =SUMIFS(Communes!$H$5:$H$187,Communes!$E$5:$E$187,A8) -> 124 | F8: =SUMIFS(Communes!$I$5:$I$187,Communes!$E$5:$E$187,A8) -> 19712 | G8: =SUMIFS(Communes!$J$5:$J$187,Communes!$E$5:$E$187,A8) -> 19665 | H8: =SUMIFS(Communes!$K$5:$K$187,Communes!$E$5:$E$187,A8) -> 2533 | I8: =SUMIFS(Communes!$L$5:$L$187,Communes!$E$5:$E$187,A8) -> 395 | J8: =SUMIFS(Communes!$M$5:$M$187,Communes!$E$5:$E$187,A8) -> 22 | K8: =SUMIFS(Communes!$N$5:$N$187,Communes!$E$5:$E$187,A8) -> 34 | L8: =SUMIFS(Communes!$O$5:$O$187,Communes!$E$5:$E$187,A8) -> 127 | M8: =SUMIFS(Communes!$P$5:$P$187,Communes!$E$5:$E$187,A8) -> 18355 | N8: =SUMIFS(Communes!$Q$5:$Q$187,Communes!$E$5:$E$187,A8) -> 19156 | O8: =SUMIFS(Communes!$R$5:$R$187,Communes!$E$5:$E$187,A8) -> 12 | P8: =SUMIFS(Communes!$S$5:$S$187,Communes!$E$5:$E$187,A8) -> 1596 | Q8: =SUMIFS(Communes!$T$5:$T$187,Communes!$E$5:$E$187,A8) -> 51 | R8: =SUMIFS(Communes!$U$5:$U$187,Communes!$E$5:$E$187,A8) -> 122 | S8: =SUMIFS(Communes!$V$5:$V$187,Communes!$E$5:$E$187,A8) -> 12 | T8: =SUMIFS(Communes!$W$5:$W$187,Communes!$E$5:$E$187,A8) -> 255 | U8: =SUMIFS(Communes!$X$5:$X$187,Communes!$E$5:$E$187,A8) -> 72 | V8: =SUMIFS(Communes!$Y$5:$Y$187,Communes!$E$5:$E$187,A8) -> 9 | W8: =SUMIFS(Communes!$Z$5:$Z$187,Communes!$E$5:$E$187,A8) -> 9 | X8: =SUMIFS(Communes!$AA$5:$AA$187,Communes!$E$5:$E$187,A8) -> 3 | Y8: =SUMIFS(Communes!$AB$5:$AB$187,Communes!$E$5:$E$187,A8) -> 11 | Z8: =SUMIFS(Communes!$AC$5:$AC$187,Communes!$E$5:$E$187,A8) -> 7 | AA8: =SUMIFS(Communes!$AD$5:$AD$187,Communes!$E$5:$E$187,A8) -> 1 | AB8: =SUMIFS(Communes!$AE$5:$AE$187,Communes!$E$5:$E$187,A8) -> 118 | AC8: =SUMIFS(Communes!$AF$5:$AF$187,Communes!$E$5:$E$187,A8) -> 121 | AD8: =SUMIFS(Communes!$AG$5:$AG$187,Communes!$E$5:$E$187,A8) -> 117 | AE8: =SUMIFS(Communes!$AH$5:$AH$187,Communes!$E$5:$E$187,A8) -> 118 | AF8: =SUMIFS(Communes!$AI$5:$AI$187,Communes!$E$5:$E$187,A8) -> 124 | AG8: =SUMIFS(Communes!$AJ$5:$AJ$187,Communes!$E$5:$E$187,A8) -> 32578 | AH8: =SUMIFS(Communes!$AK$5:$AK$187,Communes!$E$5:$E$187,A8) -> 36508 | AI8: =SUMIFS(Communes!$AL$5:$AL$187,Communes!$E$5:$E$187,A8) -> 33489 | AJ8: =SUMIFS(Communes!$AM$5:$AM$187,Communes!$E$5:$E$187,A8) -> 28788 | AK8: =SUMIFS(Communes!$AN$5:$AN$187,Communes!$E$5:$E$187,A8) -> 33515 | AL8: =SUMIFS(Communes!$AO$5:$AO$187,Communes!$E$5:$E$187,A8) -> 37511 | AM8: =SUMIFS(Communes!$AP$5:$AP$187,Communes!$E$5:$E$187,A8) -> 39377 | AN8: =F8+G8 -> 39377 | AO8: =IF(AN8>0,F8/AN8,"") -> 0.5005968 | AP8: =IF((M8+N8)>0,M8/(M8+N8),"") -> 0.48932313 | AQ8: =IF(AND(ISNUMBER(AO8),ISNUMBER(AP8)),(AO8-AP8)*100,"") -> 1.1273663 | AR8: =IF(D8>0,F8/D8*1000,"") -> 67.764447 | AS8: =IF(D8>0,E8/D8*10000,"") -> 4.2627797 | AT8: =IF(D8>0,T8/D8*10000,"") -> 8.7662003 | AU8: =IF(F8>0,H8/F8*100,"") -> 12.850041 | AV8: =IF(AN8>=100,"ok",IF(AN8>0,"effectif faible (<100)","aucune association")) -> ok
A9: CA de Cergy-Pontoise | B9: =COUNTIF(Communes!$E$5:$E$187,A9) -> 12 | C9: =COUNTIFS(Communes!$E$5:$E$187,A9,Communes!$H$5:$H$187,0) -> 2 | D9: =SUMIFS(Communes!$G$5:$G$187,Communes!$E$5:$E$187,A9) -> 215825 | E9: =SUMIFS(Communes!$H$5:$H$187,Communes!$E$5:$E$187,A9) -> 106 | F9: =SUMIFS(Communes!$I$5:$I$187,Communes!$E$5:$E$187,A9) -> 13997 | G9: =SUMIFS(Communes!$J$5:$J$187,Communes!$E$5:$E$187,A9) -> 18553 | H9: =SUMIFS(Communes!$K$5:$K$187,Communes!$E$5:$E$187,A9) -> 2279 | I9: =SUMIFS(Communes!$L$5:$L$187,Communes!$E$5:$E$187,A9) -> 275 | J9: =SUMIFS(Communes!$M$5:$M$187,Communes!$E$5:$E$187,A9) -> 23 | K9: =SUMIFS(Communes!$N$5:$N$187,Communes!$E$5:$E$187,A9) -> 24 | L9: =SUMIFS(Communes!$O$5:$O$187,Communes!$E$5:$E$187,A9) -> 112 | M9: =SUMIFS(Communes!$P$5:$P$187,Communes!$E$5:$E$187,A9) -> 12998 | N9: =SUMIFS(Communes!$Q$5:$Q$187,Communes!$E$5:$E$187,A9) -> 18186 | O9: =SUMIFS(Communes!$R$5:$R$187,Communes!$E$5:$E$187,A9) -> 36 | P9: =SUMIFS(Communes!$S$5:$S$187,Communes!$E$5:$E$187,A9) -> 6821 | Q9: =SUMIFS(Communes!$T$5:$T$187,Communes!$E$5:$E$187,A9) -> 245 | R9: =SUMIFS(Communes!$U$5:$U$187,Communes!$E$5:$E$187,A9) -> 109 | S9: =SUMIFS(Communes!$V$5:$V$187,Communes!$E$5:$E$187,A9) -> 37 | T9: =SUMIFS(Communes!$W$5:$W$187,Communes!$E$5:$E$187,A9) -> 258 | U9: =SUMIFS(Communes!$X$5:$X$187,Communes!$E$5:$E$187,A9) -> 65 | V9: =SUMIFS(Communes!$Y$5:$Y$187,Communes!$E$5:$E$187,A9) -> 7 | W9: =SUMIFS(Communes!$Z$5:$Z$187,Communes!$E$5:$E$187,A9) -> 7 | X9: =SUMIFS(Communes!$AA$5:$AA$187,Communes!$E$5:$E$187,A9) -> 11 | Y9: =SUMIFS(Communes!$AB$5:$AB$187,Communes!$E$5:$E$187,A9) -> 10 | Z9: =SUMIFS(Communes!$AC$5:$AC$187,Communes!$E$5:$E$187,A9) -> 11 | AA9: =SUMIFS(Communes!$AD$5:$AD$187,Communes!$E$5:$E$187,A9) -> 0 | AB9: =SUMIFS(Communes!$AE$5:$AE$187,Communes!$E$5:$E$187,A9) -> 101 | AC9: =SUMIFS(Communes!$AF$5:$AF$187,Communes!$E$5:$E$187,A9) -> 112 | AD9: =SUMIFS(Communes!$AG$5:$AG$187,Communes!$E$5:$E$187,A9) -> 106 | AE9: =SUMIFS(Communes!$AH$5:$AH$187,Communes!$E$5:$E$187,A9) -> 105 | AF9: =SUMIFS(Communes!$AI$5:$AI$187,Communes!$E$5:$E$187,A9) -> 105 | AG9: =SUMIFS(Communes!$AJ$5:$AJ$187,Communes!$E$5:$E$187,A9) -> 24293 | AH9: =SUMIFS(Communes!$AK$5:$AK$187,Communes!$E$5:$E$187,A9) -> 26235 | AI9: =SUMIFS(Communes!$AL$5:$AL$187,Communes!$E$5:$E$187,A9) -> 22304 | AJ9: =SUMIFS(Communes!$AM$5:$AM$187,Communes!$E$5:$E$187,A9) -> 21735 | AK9: =SUMIFS(Communes!$AN$5:$AN$187,Communes!$E$5:$E$187,A9) -> 24622 | AL9: =SUMIFS(Communes!$AO$5:$AO$187,Communes!$E$5:$E$187,A9) -> 31184 | AM9: =SUMIFS(Communes!$AP$5:$AP$187,Communes!$E$5:$E$187,A9) -> 32550 | AN9: =F9+G9 -> 32550 | AO9: =IF(AN9>0,F9/AN9,"") -> 0.43001536 | AP9: =IF((M9+N9)>0,M9/(M9+N9),"") -> 0.41681632 | AQ9: =IF(AND(ISNUMBER(AO9),ISNUMBER(AP9)),(AO9-AP9)*100,"") -> 1.3199045 | AR9: =IF(D9>0,F9/D9*1000,"") -> 64.853469 | AS9: =IF(D9>0,E9/D9*10000,"") -> 4.9113865 | AT9: =IF(D9>0,T9/D9*10000,"") -> 11.95413 | AU9: =IF(F9>0,H9/F9*100,"") -> 16.28206 | AV9: =IF(AN9>=100,"ok",IF(AN9>0,"effectif faible (<100)","aucune association")) -> ok
A10: CC Carnelle Pays-de-France | B10: =COUNTIF(Communes!$E$5:$E$187,A10) -> 19 | C10: =COUNTIFS(Communes!$E$5:$E$187,A10,Communes!$H$5:$H$187,0) -> 9 | D10: =SUMIFS(Communes!$G$5:$G$187,Communes!$E$5:$E$187,A10) -> 33841 | E10: =SUMIFS(Communes!$H$5:$H$187,Communes!$E$5:$E$187,A10) -> 22 | F10: =SUMIFS(Communes!$I$5:$I$187,Communes!$E$5:$E$187,A10) -> 2029 | G10: =SUMIFS(Communes!$J$5:$J$187,Communes!$E$5:$E$187,A10) -> 3213 | H10: =SUMIFS(Communes!$K$5:$K$187,Communes!$E$5:$E$187,A10) -> 500 | I10: =SUMIFS(Communes!$L$5:$L$187,Communes!$E$5:$E$187,A10) -> 25 | J10: =SUMIFS(Communes!$M$5:$M$187,Communes!$E$5:$E$187,A10) -> 7 | K10: =SUMIFS(Communes!$N$5:$N$187,Communes!$E$5:$E$187,A10) -> 6 | L10: =SUMIFS(Communes!$O$5:$O$187,Communes!$E$5:$E$187,A10) -> 25 | M10: =SUMIFS(Communes!$P$5:$P$187,Communes!$E$5:$E$187,A10) -> 2362 | N10: =SUMIFS(Communes!$Q$5:$Q$187,Communes!$E$5:$E$187,A10) -> 3562 | O10: =SUMIFS(Communes!$R$5:$R$187,Communes!$E$5:$E$187,A10) -> 2 | P10: =SUMIFS(Communes!$S$5:$S$187,Communes!$E$5:$E$187,A10) -> 269 | Q10: =SUMIFS(Communes!$T$5:$T$187,Communes!$E$5:$E$187,A10) -> 9 | R10: =SUMIFS(Communes!$U$5:$U$187,Communes!$E$5:$E$187,A10) -> 22 | S10: =SUMIFS(Communes!$V$5:$V$187,Communes!$E$5:$E$187,A10) -> 2 | T10: =SUMIFS(Communes!$W$5:$W$187,Communes!$E$5:$E$187,A10) -> 82 | U10: =SUMIFS(Communes!$X$5:$X$187,Communes!$E$5:$E$187,A10) -> 9 | V10: =SUMIFS(Communes!$Y$5:$Y$187,Communes!$E$5:$E$187,A10) -> 0 | W10: =SUMIFS(Communes!$Z$5:$Z$187,Communes!$E$5:$E$187,A10) -> 2 | X10: =SUMIFS(Communes!$AA$5:$AA$187,Communes!$E$5:$E$187,A10) -> 0 | Y10: =SUMIFS(Communes!$AB$5:$AB$187,Communes!$E$5:$E$187,A10) -> 0 | Z10: =SUMIFS(Communes!$AC$5:$AC$187,Communes!$E$5:$E$187,A10) -> 2 | AA10: =SUMIFS(Communes!$AD$5:$AD$187,Communes!$E$5:$E$187,A10) -> 0 | AB10: =SUMIFS(Communes!$AE$5:$AE$187,Communes!$E$5:$E$187,A10) -> 24 | AC10: =SUMIFS(Communes!$AF$5:$AF$187,Communes!$E$5:$E$187,A10) -> 22 | AD10: =SUMIFS(Communes!$AG$5:$AG$187,Communes!$E$5:$E$187,A10) -> 23 | AE10: =SUMIFS(Communes!$AH$5:$AH$187,Communes!$E$5:$E$187,A10) -> 24 | AF10: =SUMIFS(Communes!$AI$5:$AI$187,Communes!$E$5:$E$187,A10) -> 24 | AG10: =SUMIFS(Communes!$AJ$5:$AJ$187,Communes!$E$5:$E$187,A10) -> 5272 | AH10: =SUMIFS(Communes!$AK$5:$AK$187,Communes!$E$5:$E$187,A10) -> 5371 | AI10: =SUMIFS(Communes!$AL$5:$AL$187,Communes!$E$5:$E$187,A10) -> 4696 | AJ10: =SUMIFS(Communes!$AM$5:$AM$187,Communes!$E$5:$E$187,A10) -> 4965 | AK10: =SUMIFS(Communes!$AN$5:$AN$187,Communes!$E$5:$E$187,A10) -> 5340 | AL10: =SUMIFS(Communes!$AO$5:$AO$187,Communes!$E$5:$E$187,A10) -> 5924 | AM10: =SUMIFS(Communes!$AP$5:$AP$187,Communes!$E$5:$E$187,A10) -> 5242 | AN10: =F10+G10 -> 5242 | AO10: =IF(AN10>0,F10/AN10,"") -> 0.38706601 | AP10: =IF((M10+N10)>0,M10/(M10+N10),"") -> 0.39871708 | AQ10: =IF(AND(ISNUMBER(AO10),ISNUMBER(AP10)),(AO10-AP10)*100,"") -> -1.1651078 | AR10: =IF(D10>0,F10/D10*1000,"") -> 59.956857 | AS10: =IF(D10>0,E10/D10*10000,"") -> 6.5009899 | AT10: =IF(D10>0,T10/D10*10000,"") -> 24.230962 | AU10: =IF(F10>0,H10/F10*100,"") -> 24.642681 | AV10: =IF(AN10>=100,"ok",IF(AN10>0,"effectif faible (<100)","aucune association")) -> ok
A11: CC Sausseron Impressionnistes | B11: =COUNTIF(Communes!$E$5:$E$187,A11) -> 15 | C11: =COUNTIFS(Communes!$E$5:$E$187,A11,Communes!$H$5:$H$187,0) -> 10 | D11: =SUMIFS(Communes!$G$5:$G$187,Communes!$E$5:$E$187,A11) -> 19069 | E11: =SUMIFS(Communes!$H$5:$H$187,Communes!$E$5:$E$187,A11) -> 14 | F11: =SUMIFS(Communes!$I$5:$I$187,Communes!$E$5:$E$187,A11) -> 743 | G11: =SUMIFS(Communes!$J$5:$J$187,Communes!$E$5:$E$187,A11) -> 1396 | H11: =SUMIFS(Communes!$K$5:$K$187,Communes!$E$5:$E$187,A11) -> 198 | I11: =SUMIFS(Communes!$L$5:$L$187,Communes!$E$5:$E$187,A11) -> 18 | J11: =SUMIFS(Communes!$M$5:$M$187,Communes!$E$5:$E$187,A11) -> 2 | K11: =SUMIFS(Communes!$N$5:$N$187,Communes!$E$5:$E$187,A11) -> 3 | L11: =SUMIFS(Communes!$O$5:$O$187,Communes!$E$5:$E$187,A11) -> 15 | M11: =SUMIFS(Communes!$P$5:$P$187,Communes!$E$5:$E$187,A11) -> 767 | N11: =SUMIFS(Communes!$Q$5:$Q$187,Communes!$E$5:$E$187,A11) -> 1383 | O11: =SUMIFS(Communes!$R$5:$R$187,Communes!$E$5:$E$187,A11) -> 3 | P11: =SUMIFS(Communes!$S$5:$S$187,Communes!$E$5:$E$187,A11) -> 528 | Q11: =SUMIFS(Communes!$T$5:$T$187,Communes!$E$5:$E$187,A11) -> 13 | R11: =SUMIFS(Communes!$U$5:$U$187,Communes!$E$5:$E$187,A11) -> 15 | S11: =SUMIFS(Communes!$V$5:$V$187,Communes!$E$5:$E$187,A11) -> 3 | T11: =SUMIFS(Communes!$W$5:$W$187,Communes!$E$5:$E$187,A11) -> 61 | U11: =SUMIFS(Communes!$X$5:$X$187,Communes!$E$5:$E$187,A11) -> 6 | V11: =SUMIFS(Communes!$Y$5:$Y$187,Communes!$E$5:$E$187,A11) -> 0 | W11: =SUMIFS(Communes!$Z$5:$Z$187,Communes!$E$5:$E$187,A11) -> 0 | X11: =SUMIFS(Communes!$AA$5:$AA$187,Communes!$E$5:$E$187,A11) -> 0 | Y11: =SUMIFS(Communes!$AB$5:$AB$187,Communes!$E$5:$E$187,A11) -> 0 | Z11: =SUMIFS(Communes!$AC$5:$AC$187,Communes!$E$5:$E$187,A11) -> 1 | AA11: =SUMIFS(Communes!$AD$5:$AD$187,Communes!$E$5:$E$187,A11) -> 0 | AB11: =SUMIFS(Communes!$AE$5:$AE$187,Communes!$E$5:$E$187,A11) -> 19 | AC11: =SUMIFS(Communes!$AF$5:$AF$187,Communes!$E$5:$E$187,A11) -> 18 | AD11: =SUMIFS(Communes!$AG$5:$AG$187,Communes!$E$5:$E$187,A11) -> 17 | AE11: =SUMIFS(Communes!$AH$5:$AH$187,Communes!$E$5:$E$187,A11) -> 14 | AF11: =SUMIFS(Communes!$AI$5:$AI$187,Communes!$E$5:$E$187,A11) -> 15 | AG11: =SUMIFS(Communes!$AJ$5:$AJ$187,Communes!$E$5:$E$187,A11) -> 3030 | AH11: =SUMIFS(Communes!$AK$5:$AK$187,Communes!$E$5:$E$187,A11) -> 2610 | AI11: =SUMIFS(Communes!$AL$5:$AL$187,Communes!$E$5:$E$187,A11) -> 2068 | AJ11: =SUMIFS(Communes!$AM$5:$AM$187,Communes!$E$5:$E$187,A11) -> 1884 | AK11: =SUMIFS(Communes!$AN$5:$AN$187,Communes!$E$5:$E$187,A11) -> 1917 | AL11: =SUMIFS(Communes!$AO$5:$AO$187,Communes!$E$5:$E$187,A11) -> 2150 | AM11: =SUMIFS(Communes!$AP$5:$AP$187,Communes!$E$5:$E$187,A11) -> 2139 | AN11: =F11+G11 -> 2139 | AO11: =IF(AN11>0,F11/AN11,"") -> 0.34735858 | AP11: =IF((M11+N11)>0,M11/(M11+N11),"") -> 0.35674419 | AQ11: =IF(AND(ISNUMBER(AO11),ISNUMBER(AP11)),(AO11-AP11)*100,"") -> -0.93856073 | AR11: =IF(D11>0,F11/D11*1000,"") -> 38.963763 | AS11: =IF(D11>0,E11/D11*10000,"") -> 7.3417589 | AT11: =IF(D11>0,T11/D11*10000,"") -> 31.989092 | AU11: =IF(F11>0,H11/F11*100,"") -> 26.648721 | AV11: =IF(AN11>=100,"ok",IF(AN11>0,"effectif faible (<100)","aucune association")) -> ok
A12: CC Vexin Centre | B12: =COUNTIF(Communes!$E$5:$E$187,A12) -> 33 | C12: =COUNTIFS(Communes!$E$5:$E$187,A12,Communes!$H$5:$H$187,0) -> 22 | D12: =SUMIFS(Communes!$G$5:$G$187,Communes!$E$5:$E$187,A12) -> 25317 | E12: =SUMIFS(Communes!$H$5:$H$187,Communes!$E$5:$E$187,A12) -> 22 | F12: =SUMIFS(Communes!$I$5:$I$187,Communes!$E$5:$E$187,A12) -> 1222 | G12: =SUMIFS(Communes!$J$5:$J$187,Communes!$E$5:$E$187,A12) -> 1728 | H12: =SUMIFS(Communes!$K$5:$K$187,Communes!$E$5:$E$187,A12) -> 260 | I12: =SUMIFS(Communes!$L$5:$L$187,Communes!$E$5:$E$187,A12) -> 20 | J12: =SUMIFS(Communes!$M$5:$M$187,Communes!$E$5:$E$187,A12) -> 8 | K12: =SUMIFS(Communes!$N$5:$N$187,Communes!$E$5:$E$187,A12) -> 2 | L12: =SUMIFS(Communes!$O$5:$O$187,Communes!$E$5:$E$187,A12) -> 24 | M12: =SUMIFS(Communes!$P$5:$P$187,Communes!$E$5:$E$187,A12) -> 1254 | N12: =SUMIFS(Communes!$Q$5:$Q$187,Communes!$E$5:$E$187,A12) -> 2095 | O12: =SUMIFS(Communes!$R$5:$R$187,Communes!$E$5:$E$187,A12) -> 2 | P12: =SUMIFS(Communes!$S$5:$S$187,Communes!$E$5:$E$187,A12) -> 204 | Q12: =SUMIFS(Communes!$T$5:$T$187,Communes!$E$5:$E$187,A12) -> 21 | R12: =SUMIFS(Communes!$U$5:$U$187,Communes!$E$5:$E$187,A12) -> 23 | S12: =SUMIFS(Communes!$V$5:$V$187,Communes!$E$5:$E$187,A12) -> 2 | T12: =SUMIFS(Communes!$W$5:$W$187,Communes!$E$5:$E$187,A12) -> 101 | U12: =SUMIFS(Communes!$X$5:$X$187,Communes!$E$5:$E$187,A12) -> 16 | V12: =SUMIFS(Communes!$Y$5:$Y$187,Communes!$E$5:$E$187,A12) -> 0 | W12: =SUMIFS(Communes!$Z$5:$Z$187,Communes!$E$5:$E$187,A12) -> 0 | X12: =SUMIFS(Communes!$AA$5:$AA$187,Communes!$E$5:$E$187,A12) -> 1 | Y12: =SUMIFS(Communes!$AB$5:$AB$187,Communes!$E$5:$E$187,A12) -> 0 | Z12: =SUMIFS(Communes!$AC$5:$AC$187,Communes!$E$5:$E$187,A12) -> 0 | AA12: =SUMIFS(Communes!$AD$5:$AD$187,Communes!$E$5:$E$187,A12) -> 0 | AB12: =SUMIFS(Communes!$AE$5:$AE$187,Communes!$E$5:$E$187,A12) -> 28 | AC12: =SUMIFS(Communes!$AF$5:$AF$187,Communes!$E$5:$E$187,A12) -> 29 | AD12: =SUMIFS(Communes!$AG$5:$AG$187,Communes!$E$5:$E$187,A12) -> 26 | AE12: =SUMIFS(Communes!$AH$5:$AH$187,Communes!$E$5:$E$187,A12) -> 25 | AF12: =SUMIFS(Communes!$AI$5:$AI$187,Communes!$E$5:$E$187,A12) -> 23 | AG12: =SUMIFS(Communes!$AJ$5:$AJ$187,Communes!$E$5:$E$187,A12) -> 2817 | AH12: =SUMIFS(Communes!$AK$5:$AK$187,Communes!$E$5:$E$187,A12) -> 2418 | AI12: =SUMIFS(Communes!$AL$5:$AL$187,Communes!$E$5:$E$187,A12) -> 2000 | AJ12: =SUMIFS(Communes!$AM$5:$AM$187,Communes!$E$5:$E$187,A12) -> 1951 | AK12: =SUMIFS(Communes!$AN$5:$AN$187,Communes!$E$5:$E$187,A12) -> 1735 | AL12: =SUMIFS(Communes!$AO$5:$AO$187,Communes!$E$5:$E$187,A12) -> 3349 | AM12: =SUMIFS(Communes!$AP$5:$AP$187,Communes!$E$5:$E$187,A12) -> 2950 | AN12: =F12+G12 -> 2950 | AO12: =IF(AN12>0,F12/AN12,"") -> 0.41423729 | AP12: =IF((M12+N12)>0,M12/(M12+N12),"") -> 0.37444013 | AQ12: =IF(AND(ISNUMBER(AO12),ISNUMBER(AP12)),(AO12-AP12)*100,"") -> 3.9797157 | AR12: =IF(D12>0,F12/D12*1000,"") -> 48.267962 | AS12: =IF(D12>0,E12/D12*10000,"") -> 8.6898132 | AT12: =IF(D12>0,T12/D12*10000,"") -> 39.894142 | AU12: =IF(F12>0,H12/F12*100,"") -> 21.276596 | AV12: =IF(AN12>=100,"ok",IF(AN12>0,"effectif faible (<100)","aucune association")) -> ok
A13: CC de la Vallée de l'Oise et des Trois Forêts | B13: =COUNTIF(Communes!$E$5:$E$187,A13) -> 9 | C13: =COUNTIFS(Communes!$E$5:$E$187,A13,Communes!$H$5:$H$187,0) -> 2 | D13: =SUMIFS(Communes!$G$5:$G$187,Communes!$E$5:$E$187,A13) -> 39841 | E13: =SUMIFS(Communes!$H$5:$H$187,Communes!$E$5:$E$187,A13) -> 35 | F13: =SUMIFS(Communes!$I$5:$I$187,Communes!$E$5:$E$187,A13) -> 4306 | G13: =SUMIFS(Communes!$J$5:$J$187,Communes!$E$5:$E$187,A13) -> 5871 | H13: =SUMIFS(Communes!$K$5:$K$187,Communes!$E$5:$E$187,A13) -> 449 | I13: =SUMIFS(Communes!$L$5:$L$187,Communes!$E$5:$E$187,A13) -> 61 | J13: =SUMIFS(Communes!$M$5:$M$187,Communes!$E$5:$E$187,A13) -> 9 | K13: =SUMIFS(Communes!$N$5:$N$187,Communes!$E$5:$E$187,A13) -> 7 | L13: =SUMIFS(Communes!$O$5:$O$187,Communes!$E$5:$E$187,A13) -> 34 | M13: =SUMIFS(Communes!$P$5:$P$187,Communes!$E$5:$E$187,A13) -> 3965 | N13: =SUMIFS(Communes!$Q$5:$Q$187,Communes!$E$5:$E$187,A13) -> 5578 | O13: =SUMIFS(Communes!$R$5:$R$187,Communes!$E$5:$E$187,A13) -> 3 | P13: =SUMIFS(Communes!$S$5:$S$187,Communes!$E$5:$E$187,A13) -> 202 | Q13: =SUMIFS(Communes!$T$5:$T$187,Communes!$E$5:$E$187,A13) -> 12 | R13: =SUMIFS(Communes!$U$5:$U$187,Communes!$E$5:$E$187,A13) -> 36 | S13: =SUMIFS(Communes!$V$5:$V$187,Communes!$E$5:$E$187,A13) -> 3 | T13: =SUMIFS(Communes!$W$5:$W$187,Communes!$E$5:$E$187,A13) -> 77 | U13: =SUMIFS(Communes!$X$5:$X$187,Communes!$E$5:$E$187,A13) -> 11 | V13: =SUMIFS(Communes!$Y$5:$Y$187,Communes!$E$5:$E$187,A13) -> 2 | W13: =SUMIFS(Communes!$Z$5:$Z$187,Communes!$E$5:$E$187,A13) -> 0 | X13: =SUMIFS(Communes!$AA$5:$AA$187,Communes!$E$5:$E$187,A13) -> 1 | Y13: =SUMIFS(Communes!$AB$5:$AB$187,Communes!$E$5:$E$187,A13) -> 1 | Z13: =SUMIFS(Communes!$AC$5:$AC$187,Communes!$E$5:$E$187,A13) -> 0 | AA13: =SUMIFS(Communes!$AD$5:$AD$187,Communes!$E$5:$E$187,A13) -> 0 | AB13: =SUMIFS(Communes!$AE$5:$AE$187,Communes!$E$5:$E$187,A13) -> 29 | AC13: =SUMIFS(Communes!$AF$5:$AF$187,Communes!$E$5:$E$187,A13) -> 34 | AD13: =SUMIFS(Communes!$AG$5:$AG$187,Communes!$E$5:$E$187,A13) -> 35 | AE13: =SUMIFS(Communes!$AH$5:$AH$187,Communes!$E$5:$E$187,A13) -> 31 | AF13: =SUMIFS(Communes!$AI$5:$AI$187,Communes!$E$5:$E$187,A13) -> 32 | AG13: =SUMIFS(Communes!$AJ$5:$AJ$187,Communes!$E$5:$E$187,A13) -> 5205 | AH13: =SUMIFS(Communes!$AK$5:$AK$187,Communes!$E$5:$E$187,A13) -> 8871 | AI13: =SUMIFS(Communes!$AL$5:$AL$187,Communes!$E$5:$E$187,A13) -> 7245 | AJ13: =SUMIFS(Communes!$AM$5:$AM$187,Communes!$E$5:$E$187,A13) -> 7875 | AK13: =SUMIFS(Communes!$AN$5:$AN$187,Communes!$E$5:$E$187,A13) -> 8143 | AL13: =SUMIFS(Communes!$AO$5:$AO$187,Communes!$E$5:$E$187,A13) -> 9543 | AM13: =SUMIFS(Communes!$AP$5:$AP$187,Communes!$E$5:$E$187,A13) -> 10177 | AN13: =F13+G13 -> 10177 | AO13: =IF(AN13>0,F13/AN13,"") -> 0.42311094 | AP13: =IF((M13+N13)>0,M13/(M13+N13),"") -> 0.41548779 | AQ13: =IF(AND(ISNUMBER(AO13),ISNUMBER(AP13)),(AO13-AP13)*100,"") -> 0.76231443 | AR13: =IF(D13>0,F13/D13*1000,"") -> 108.07962 | AS13: =IF(D13>0,E13/D13*10000,"") -> 8.7849201 | AT13: =IF(D13>0,T13/D13*10000,"") -> 19.326824 | AU13: =IF(F13>0,H13/F13*100,"") -> 10.427311 | AV13: =IF(AN13>=100,"ok",IF(AN13>0,"effectif faible (<100)","aucune association")) -> ok
A14: CC du Haut Val d'Oise | B14: =COUNTIF(Communes!$E$5:$E$187,A14) -> 9 | C14: =COUNTIFS(Communes!$E$5:$E$187,A14,Communes!$H$5:$H$187,0) -> 4 | D14: =SUMIFS(Communes!$G$5:$G$187,Communes!$E$5:$E$187,A14) -> 41284 | E14: =SUMIFS(Communes!$H$5:$H$187,Communes!$E$5:$E$187,A14) -> 27 | F14: =SUMIFS(Communes!$I$5:$I$187,Communes!$E$5:$E$187,A14) -> 1502 | G14: =SUMIFS(Communes!$J$5:$J$187,Communes!$E$5:$E$187,A14) -> 3085 | H14: =SUMIFS(Communes!$K$5:$K$187,Communes!$E$5:$E$187,A14) -> 611 | I14: =SUMIFS(Communes!$L$5:$L$187,Communes!$E$5:$E$187,A14) -> 21 | J14: =SUMIFS(Communes!$M$5:$M$187,Communes!$E$5:$E$187,A14) -> 9 | K14: =SUMIFS(Communes!$N$5:$N$187,Communes!$E$5:$E$187,A14) -> 3 | L14: =SUMIFS(Communes!$O$5:$O$187,Communes!$E$5:$E$187,A14) -> 28 | M14: =SUMIFS(Communes!$P$5:$P$187,Communes!$E$5:$E$187,A14) -> 1679 | N14: =SUMIFS(Communes!$Q$5:$Q$187,Communes!$E$5:$E$187,A14) -> 3376 | O14: =SUMIFS(Communes!$R$5:$R$187,Communes!$E$5:$E$187,A14) -> 7 | P14: =SUMIFS(Communes!$S$5:$S$187,Communes!$E$5:$E$187,A14) -> 1469 | Q14: =SUMIFS(Communes!$T$5:$T$187,Communes!$E$5:$E$187,A14) -> 44 | R14: =SUMIFS(Communes!$U$5:$U$187,Communes!$E$5:$E$187,A14) -> 29 | S14: =SUMIFS(Communes!$V$5:$V$187,Communes!$E$5:$E$187,A14) -> 7 | T14: =SUMIFS(Communes!$W$5:$W$187,Communes!$E$5:$E$187,A14) -> 66 | U14: =SUMIFS(Communes!$X$5:$X$187,Communes!$E$5:$E$187,A14) -> 15 | V14: =SUMIFS(Communes!$Y$5:$Y$187,Communes!$E$5:$E$187,A14) -> 1 | W14: =SUMIFS(Communes!$Z$5:$Z$187,Communes!$E$5:$E$187,A14) -> 1 | X14: =SUMIFS(Communes!$AA$5:$AA$187,Communes!$E$5:$E$187,A14) -> 2 | Y14: =SUMIFS(Communes!$AB$5:$AB$187,Communes!$E$5:$E$187,A14) -> 2 | Z14: =SUMIFS(Communes!$AC$5:$AC$187,Communes!$E$5:$E$187,A14) -> 2 | AA14: =SUMIFS(Communes!$AD$5:$AD$187,Communes!$E$5:$E$187,A14) -> 0 | AB14: =SUMIFS(Communes!$AE$5:$AE$187,Communes!$E$5:$E$187,A14) -> 26 | AC14: =SUMIFS(Communes!$AF$5:$AF$187,Communes!$E$5:$E$187,A14) -> 30 | AD14: =SUMIFS(Communes!$AG$5:$AG$187,Communes!$E$5:$E$187,A14) -> 31 | AE14: =SUMIFS(Communes!$AH$5:$AH$187,Communes!$E$5:$E$187,A14) -> 30 | AF14: =SUMIFS(Communes!$AI$5:$AI$187,Communes!$E$5:$E$187,A14) -> 31 | AG14: =SUMIFS(Communes!$AJ$5:$AJ$187,Communes!$E$5:$E$187,A14) -> 3603 | AH14: =SUMIFS(Communes!$AK$5:$AK$187,Communes!$E$5:$E$187,A14) -> 4212 | AI14: =SUMIFS(Communes!$AL$5:$AL$187,Communes!$E$5:$E$187,A14) -> 4015 | AJ14: =SUMIFS(Communes!$AM$5:$AM$187,Communes!$E$5:$E$187,A14) -> 4526 | AK14: =SUMIFS(Communes!$AN$5:$AN$187,Communes!$E$5:$E$187,A14) -> 4494 | AL14: =SUMIFS(Communes!$AO$5:$AO$187,Communes!$E$5:$E$187,A14) -> 5055 | AM14: =SUMIFS(Communes!$AP$5:$AP$187,Communes!$E$5:$E$187,A14) -> 4587 | AN14: =F14+G14 -> 4587 | AO14: =IF(AN14>0,F14/AN14,"") -> 0.32744713 | AP14: =IF((M14+N14)>0,M14/(M14+N14),"") -> 0.33214639 | AQ14: =IF(AND(ISNUMBER(AO14),ISNUMBER(AP14)),(AO14-AP14)*100,"") -> -0.46992565 | AR14: =IF(D14>0,F14/D14*1000,"") -> 36.382134 | AS14: =IF(D14>0,E14/D14*10000,"") -> 6.5400639 | AT14: =IF(D14>0,T14/D14*10000,"") -> 15.986823 | AU14: =IF(F14>0,H14/F14*100,"") -> 40.679095 | AV14: =IF(AN14>=100,"ok",IF(AN14>0,"effectif faible (<100)","aucune association")) -> ok
A15: CC du Vexin-Val de Seine | B15: =COUNTIF(Communes!$E$5:$E$187,A15) -> 26 | C15: =COUNTIFS(Communes!$E$5:$E$187,A15,Communes!$H$5:$H$187,0) -> 18 | D15: =SUMIFS(Communes!$G$5:$G$187,Communes!$E$5:$E$187,A15) -> 16528 | E15: =SUMIFS(Communes!$H$5:$H$187,Communes!$E$5:$E$187,A15) -> 9 | F15: =SUMIFS(Communes!$I$5:$I$187,Communes!$E$5:$E$187,A15) -> 448 | G15: =SUMIFS(Communes!$J$5:$J$187,Communes!$E$5:$E$187,A15) -> 690 | H15: =SUMIFS(Communes!$K$5:$K$187,Communes!$E$5:$E$187,A15) -> 187 | I15: =SUMIFS(Communes!$L$5:$L$187,Communes!$E$5:$E$187,A15) -> 23 | J15: =SUMIFS(Communes!$M$5:$M$187,Communes!$E$5:$E$187,A15) -> 1 | K15: =SUMIFS(Communes!$N$5:$N$187,Communes!$E$5:$E$187,A15) -> 2 | L15: =SUMIFS(Communes!$O$5:$O$187,Communes!$E$5:$E$187,A15) -> 11 | M15: =SUMIFS(Communes!$P$5:$P$187,Communes!$E$5:$E$187,A15) -> 521 | N15: =SUMIFS(Communes!$Q$5:$Q$187,Communes!$E$5:$E$187,A15) -> 662 | O15: =SUMIFS(Communes!$R$5:$R$187,Communes!$E$5:$E$187,A15) -> 1 | P15: =SUMIFS(Communes!$S$5:$S$187,Communes!$E$5:$E$187,A15) -> 69 | Q15: =SUMIFS(Communes!$T$5:$T$187,Communes!$E$5:$E$187,A15) -> 10 | R15: =SUMIFS(Communes!$U$5:$U$187,Communes!$E$5:$E$187,A15) -> 8 | S15: =SUMIFS(Communes!$V$5:$V$187,Communes!$E$5:$E$187,A15) -> 1 | T15: =SUMIFS(Communes!$W$5:$W$187,Communes!$E$5:$E$187,A15) -> 69 | U15: =SUMIFS(Communes!$X$5:$X$187,Communes!$E$5:$E$187,A15) -> 10 | V15: =SUMIFS(Communes!$Y$5:$Y$187,Communes!$E$5:$E$187,A15) -> 0 | W15: =SUMIFS(Communes!$Z$5:$Z$187,Communes!$E$5:$E$187,A15) -> 1 | X15: =SUMIFS(Communes!$AA$5:$AA$187,Communes!$E$5:$E$187,A15) -> 0 | Y15: =SUMIFS(Communes!$AB$5:$AB$187,Communes!$E$5:$E$187,A15) -> 1 | Z15: =SUMIFS(Communes!$AC$5:$AC$187,Communes!$E$5:$E$187,A15) -> 0 | AA15: =SUMIFS(Communes!$AD$5:$AD$187,Communes!$E$5:$E$187,A15) -> 0 | AB15: =SUMIFS(Communes!$AE$5:$AE$187,Communes!$E$5:$E$187,A15) -> 10 | AC15: =SUMIFS(Communes!$AF$5:$AF$187,Communes!$E$5:$E$187,A15) -> 10 | AD15: =SUMIFS(Communes!$AG$5:$AG$187,Communes!$E$5:$E$187,A15) -> 10 | AE15: =SUMIFS(Communes!$AH$5:$AH$187,Communes!$E$5:$E$187,A15) -> 10 | AF15: =SUMIFS(Communes!$AI$5:$AI$187,Communes!$E$5:$E$187,A15) -> 11 | AG15: =SUMIFS(Communes!$AJ$5:$AJ$187,Communes!$E$5:$E$187,A15) -> 1055 | AH15: =SUMIFS(Communes!$AK$5:$AK$187,Communes!$E$5:$E$187,A15) -> 871 | AI15: =SUMIFS(Communes!$AL$5:$AL$187,Communes!$E$5:$E$187,A15) -> 837 | AJ15: =SUMIFS(Communes!$AM$5:$AM$187,Communes!$E$5:$E$187,A15) -> 831 | AK15: =SUMIFS(Communes!$AN$5:$AN$187,Communes!$E$5:$E$187,A15) -> 952 | AL15: =SUMIFS(Communes!$AO$5:$AO$187,Communes!$E$5:$E$187,A15) -> 1183 | AM15: =SUMIFS(Communes!$AP$5:$AP$187,Communes!$E$5:$E$187,A15) -> 1138 | AN15: =F15+G15 -> 1138 | AO15: =IF(AN15>0,F15/AN15,"") -> 0.39367311 | AP15: =IF((M15+N15)>0,M15/(M15+N15),"") -> 0.44040575 | AQ15: =IF(AND(ISNUMBER(AO15),ISNUMBER(AP15)),(AO15-AP15)*100,"") -> -4.6732637 | AR15: =IF(D15>0,F15/D15*1000,"") -> 27.105518 | AS15: =IF(D15>0,E15/D15*10000,"") -> 5.4453049 | AT15: =IF(D15>0,T15/D15*10000,"") -> 41.747338 | AU15: =IF(F15>0,H15/F15*100,"") -> 41.741071 | AV15: =IF(AN15>=100,"ok",IF(AN15>0,"effectif faible (<100)","aucune association")) -> ok
A16: Métropole du Grand Paris | B16: =COUNTIF(Communes!$E$5:$E$187,A16) -> 1 | C16: =COUNTIFS(Communes!$E$5:$E$187,A16,Communes!$H$5:$H$187,0) -> 0 | D16: =SUMIFS(Communes!$G$5:$G$187,Communes!$E$5:$E$187,A16) -> 106130 | E16: =SUMIFS(Communes!$H$5:$H$187,Communes!$E$5:$E$187,A16) -> 24 | F16: =SUMIFS(Communes!$I$5:$I$187,Communes!$E$5:$E$187,A16) -> 3364 | G16: =SUMIFS(Communes!$J$5:$J$187,Communes!$E$5:$E$187,A16) -> 5334 | H16: =SUMIFS(Communes!$K$5:$K$187,Communes!$E$5:$E$187,A16) -> 679 | I16: =SUMIFS(Communes!$L$5:$L$187,Communes!$E$5:$E$187,A16) -> 68 | J16: =SUMIFS(Communes!$M$5:$M$187,Communes!$E$5:$E$187,A16) -> 6 | K16: =SUMIFS(Communes!$N$5:$N$187,Communes!$E$5:$E$187,A16) -> 3 | L16: =SUMIFS(Communes!$O$5:$O$187,Communes!$E$5:$E$187,A16) -> 22 | M16: =SUMIFS(Communes!$P$5:$P$187,Communes!$E$5:$E$187,A16) -> 3398 | N16: =SUMIFS(Communes!$Q$5:$Q$187,Communes!$E$5:$E$187,A16) -> 3688 | O16: =SUMIFS(Communes!$R$5:$R$187,Communes!$E$5:$E$187,A16) -> 6 | P16: =SUMIFS(Communes!$S$5:$S$187,Communes!$E$5:$E$187,A16) -> 683 | Q16: =SUMIFS(Communes!$T$5:$T$187,Communes!$E$5:$E$187,A16) -> 26 | R16: =SUMIFS(Communes!$U$5:$U$187,Communes!$E$5:$E$187,A16) -> 24 | S16: =SUMIFS(Communes!$V$5:$V$187,Communes!$E$5:$E$187,A16) -> 6 | T16: =SUMIFS(Communes!$W$5:$W$187,Communes!$E$5:$E$187,A16) -> 68 | U16: =SUMIFS(Communes!$X$5:$X$187,Communes!$E$5:$E$187,A16) -> 14 | V16: =SUMIFS(Communes!$Y$5:$Y$187,Communes!$E$5:$E$187,A16) -> 1 | W16: =SUMIFS(Communes!$Z$5:$Z$187,Communes!$E$5:$E$187,A16) -> 2 | X16: =SUMIFS(Communes!$AA$5:$AA$187,Communes!$E$5:$E$187,A16) -> 2 | Y16: =SUMIFS(Communes!$AB$5:$AB$187,Communes!$E$5:$E$187,A16) -> 0 | Z16: =SUMIFS(Communes!$AC$5:$AC$187,Communes!$E$5:$E$187,A16) -> 4 | AA16: =SUMIFS(Communes!$AD$5:$AD$187,Communes!$E$5:$E$187,A16) -> 0 | AB16: =SUMIFS(Communes!$AE$5:$AE$187,Communes!$E$5:$E$187,A16) -> 21 | AC16: =SUMIFS(Communes!$AF$5:$AF$187,Communes!$E$5:$E$187,A16) -> 26 | AD16: =SUMIFS(Communes!$AG$5:$AG$187,Communes!$E$5:$E$187,A16) -> 25 | AE16: =SUMIFS(Communes!$AH$5:$AH$187,Communes!$E$5:$E$187,A16) -> 25 | AF16: =SUMIFS(Communes!$AI$5:$AI$187,Communes!$E$5:$E$187,A16) -> 23 | AG16: =SUMIFS(Communes!$AJ$5:$AJ$187,Communes!$E$5:$E$187,A16) -> 7854 | AH16: =SUMIFS(Communes!$AK$5:$AK$187,Communes!$E$5:$E$187,A16) -> 8955 | AI16: =SUMIFS(Communes!$AL$5:$AL$187,Communes!$E$5:$E$187,A16) -> 8268 | AJ16: =SUMIFS(Communes!$AM$5:$AM$187,Communes!$E$5:$E$187,A16) -> 6751 | AK16: =SUMIFS(Communes!$AN$5:$AN$187,Communes!$E$5:$E$187,A16) -> 6733 | AL16: =SUMIFS(Communes!$AO$5:$AO$187,Communes!$E$5:$E$187,A16) -> 7086 | AM16: =SUMIFS(Communes!$AP$5:$AP$187,Communes!$E$5:$E$187,A16) -> 8698 | AN16: =F16+G16 -> 8698 | AO16: =IF(AN16>0,F16/AN16,"") -> 0.38675558 | AP16: =IF((M16+N16)>0,M16/(M16+N16),"") -> 0.47953712 | AQ16: =IF(AND(ISNUMBER(AO16),ISNUMBER(AP16)),(AO16-AP16)*100,"") -> -9.2781539 | AR16: =IF(D16>0,F16/D16*1000,"") -> 31.696975 | AS16: =IF(D16>0,E16/D16*10000,"") -> 2.2613776 | AT16: =IF(D16>0,T16/D16*10000,"") -> 6.4072364 | AU16: =IF(F16>0,H16/F16*100,"") -> 20.184304 | AV16: =IF(AN16>=100,"ok",IF(AN16>0,"effectif faible (<100)","aucune association")) -> ok
A17: Total Val d'Oise | B17: =SUM(B5:B16) -> 183 | C17: =SUM(C5:C16) -> 78 | D17: =SUM(D5:D16) -> 1281653 | E17: =SUM(E5:E16) -> 551 | F17: =SUM(F5:F16) -> 68623 | G17: =SUM(G5:G16) -> 91352 | H17: =SUM(H5:H16) -> 11261 | I17: =SUM(I5:I16) -> 1285 | ... AM17: =SUM(AM5:AM16) -> 159975 | AN17: =F17+G17 -> 159975 | AO17: =IF(AN17>0,F17/AN17,"") -> 0.42896078 | AP17: =IF((M17+N17)>0,M17/(M17+N17),"") -> 0.42882683 | AQ17: =IF(AND(ISNUMBER(AO17),ISNUMBER(AP17)),(AO17-AP17)*100,"") -> 0.01339426 | AR17: =IF(D17>0,F17/D17*1000,"") -> 53.542574 | AS17: =IF(D17>0,E17/D17*10000,"") -> 4.2991356 | AT17: =IF(D17>0,T17/D17*10000,"") -> 12.03914 | AU17: =IF(F17>0,H17/F17*100,"") -> 16.40995 | AV17: =IF(AN17>=100,"ok",IF(AN17>0,"effectif faible (<100)","aucune association")) -> ok

Sheet Associations_2025
A1: Associations sportives civiles aidées, 2025
A2: Source : onglet « 2025 ASS CIVILES ». Part F et profil calculés par formule.
A4: Association | B4: Ville (source) | C4: Code INSEE | D4: Commune | E4: Canton | F4: EPCI | G4: Adhérentes F | H4: Adhérents H | I4: Bénévoles F | J4: Salariées F | K4: Adhérent·es total | L4: Part F | M4: Profil de mixité
A5: ASS SPORTIVE DU GOLF CLUB D ABLEIGES | B5: ABLEIGES | C5: 95002 | D5: Ableiges | E5: Pontoise | F5: CC Vexin Centre | G5: 38 | H5: 185 | I5: 7 | J5: 0 | K5: =G5+H5 -> 223 | L5: =IF(K5>0,G5/K5,"") -> 0.17040359 | M5: =IF(K5=0,"",IF(L5<0.2,"Très masculine (<20 % F)",IF(L5<0.4,"Plutôt masculine (20-40 %)",IF(L5<0.6,"Mixte (40-60 %)","À dominante féminine (≥60 %)")))) -> Très masculine (<20 % F)
A6: APCLES | B6: ARGENTEUIL | C6: 95018 | D6: Argenteuil | E6: Argenteuil (1-2-3) | F6: Métropole du Grand Paris | G6: 96 | H6: 136 | I6: 12 | J6: 0 | K6: =G6+H6 -> 232 | L6: =IF(K6>0,G6/K6,"") -> 0.4137931 | M6: =IF(K6=0,"",IF(L6<0.2,"Très masculine (<20 % F)",IF(L6<0.4,"Plutôt masculine (20-40 %)",IF(L6<0.6,"Mixte (40-60 %)","À dominante féminine (≥60 %)")))) -> Mixte (40-60 %)
A7: ARGENTEUIL BASKET BALL | B7: ARGENTEUIL | C7: 95018 | D7: Argenteuil | E7: Argenteuil (1-2-3) | F7: Métropole du Grand Paris | G7: 152 | H7: 249 | I7: 18 | J7: 0 | K7: =G7+H7 -> 401 | L7: =IF(K7>0,G7/K7,"") -> 0.37905237 | M7: =IF(K7=0,"",IF(L7<0.2,"Très masculine (<20 % F)",IF(L7<0.4,"Plutôt masculine (20-40 %)",IF(L7<0.6,"Mixte (40-60 %)","À dominante féminine (≥60 %)")))) -> Plutôt masculine (20-40 %)
A8: ARGENTEUIL FOOTBALL CLUB | B8: ARGENTEUIL | C8: 95018 | D8: Argenteuil | E8: Argenteuil (1-2-3) | F8: Métropole du Grand Paris | G8: 105 | H8: 937 | I8: 87 | J8: 3 | K8: =G8+H8 -> 1042 | L8: =IF(K8>0,G8/K8,"") -> 0.10076775 | M8: =IF(K8=0,"",IF(L8<0.2,"Très masculine (<20 % F)",IF(L8<0.4,"Plutôt masculine (20-40 %)",IF(L8<0.6,"Mixte (40-60 %)","À dominante féminine (≥60 %)")))) -> Très masculine (<20 % F)
A9: ARGENTEUIL NATATION | B9: ARGENTEUIL | C9: 95018 | D9: Argenteuil | E9: Argenteuil (1-2-3) | F9: Métropole du Grand Paris | G9: 229 | H9: 228 | I9: 9 | J9: 10 | K9: =G9+H9 -> 457 | L9: =IF(K9>0,G9/K9,"") -> 0.50109409 | M9: =IF(K9=0,"",IF(L9<0.2,"Très masculine (<20 % F)",IF(L9<0.4,"Plutôt masculine (20-40 %)",IF(L9<0.6,"Mixte (40-60 %)","À dominante féminine (≥60 %)")))) -> Mixte (40-60 %)
A10: ARGENTEUIL TENNIS DE TABLE | B10: ARGENTEUIL | C10: 95018 | D10: Argenteuil | E10: Argenteuil (1-2-3) | F10: Métropole du Grand Paris | G10: 15 | H10: 85 | I10: 11 | J10: 3 | K10: =G10+H10 -> 100 | L10: =IF(K10>0,G10/K10,"") -> 0.15 | M10: =IF(K10=0,"",IF(L10<0.2,"Très masculine (<20 % F)",IF(L10<0.4,"Plutôt masculine (20-40 %)",IF(L10<0.6,"Mixte (40-60 %)","À dominante féminine (≥60 %)")))) -> Très masculine (<20 % F)
A11: ARGENTEUIL VAL DE SEINE CYCLISME | B11: ARGENTEUIL | C11: 95018 | D11: Argenteuil | E11: Argenteuil (1-2-3) | F11: Métropole du Grand Paris | G11: 11 | H11: 61 | I11: 21 | J11: 0 | K11: =G11+H11 -> 72 | L11: =IF(K11>0,G11/K11,"") -> 0.15277778 | M11: =IF(K11=0,"",IF(L11<0.2,"Très masculine (<20 % F)",IF(L11<0.4,"Plutôt masculine (20-40 %)",IF(L11<0.6,"Mixte (40-60 %)","À dominante féminine (≥60 %)")))) -> Très masculine (<20 % F)
A12: ARGENTEUIL VOLLEY BALL 95 | B12: ARGENTEUIL | C12: 95018 | D12: Argenteuil | E12: Argenteuil (1-2-3) | F12: Métropole du Grand Paris | G12: 131 | H12: 117 | I12: 18 | J12: 2 | K12: =G12+H12 -> 248 | L12: =IF(K12>0,G12/K12,"") -> 0.52822581 | M12: =IF(K12=0,"",IF(L12<0.2,"Très masculine (<20 % F)",IF(L12<0.4,"Plutôt masculine (20-40 %)",IF(L12<0.6,"Mixte (40-60 %)","À dominante féminine (≥60 %)")))) -> Mixte (40-60 %)
A13: CLUB DE PLONGEE DE LA POLICE ET DE LA JUSTICE DU VAL D OISE | B13: ARGENTEUIL | C13: 95018 | D13: Argenteuil | E13: Argenteuil (1-2-3) | F13: Métropole du Grand Paris | G13: 21 | H13: 52 | I13: 16 | J13: 0 | K13: =G13+H13 -> 73 | L13: =IF(K13>0,G13/K13,"") -> 0.28767123 | M13: =IF(K13=0,"",IF(L13<0.2,"Très masculine (<20 % F)",IF(L13<0.4,"Plutôt masculine (20-40 %)",IF(L13<0.6,"Mixte (40-60 %)","À dominante féminine (≥60 %)")))) -> Plutôt masculine (20-40 %)
A14: CLUB DES PETITS PLONGEURS DE LA POLICE | B14: ARGENTEUIL | C14: 95018 | D14: Argenteuil | E14: Argenteuil (1-2-3) | F14: Métropole du Grand Paris | G14: 29 | H14: 48 | I14: 19 | J14: 0 | K14: =G14+H14 -> 77 | L14: =IF(K14>0,G14/K14,"") -> 0.37662338 | M14: =IF(K14=0,"",IF(L14<0.2,"Très masculine (<20 % F)",IF(L14<0.4,"Plutôt masculine (20-40 %)",IF(L14<0.6,"Mixte (40-60 %)","À dominante féminine (≥60 %)")))) -> Plutôt masculine (20-40 %)
A15: CLUB ECHIQUIER LAPIERRE ARGENTEUIL | B15: ARGENTEUIL | C15: 95018 | D15: Argenteuil | E15: Argenteuil (1-2-3) | F15: Métropole du Grand Paris | G15: 46 | H15: 115 | I15: 12 | J15: 2 | K15: =G15+H15 -> 161 | L15: =IF(K15>0,G15/K15,"") -> 0.28571429 | M15: =IF(K15=0,"",IF(L15<0.2,"Très masculine (<20 % F)",IF(L15<0.4,"Plutôt masculine (20-40 %)",IF(L15<0.6,"Mixte (40-60 %)","À dominante féminine (≥60 %)")))) -> Plutôt masculine (20-40 %)
A16: CLUB OLYMPIQUE MULTISPORTS D ARGENTEUIL HAND BALL | B16: ARGENTEUIL | C16: 95018 | D16: Argenteuil | E16: Argenteuil (1-2-3) | F16: Métropole du Grand Paris | G16: 95 | H16: 157 | I16: 16 | J16: 0 | K16: =G16+H16 -> 252 | L16: =IF(K16>0,G16/K16,"") -> 0.37698413 | M16: =IF(K16=0,"",IF(L16<0.2,"Très masculine (<20 % F)",IF(L16<0.4,"Plutôt masculine (20-40 %)",IF(L16<0.6,"Mixte (40-60 %)","À dominante féminine (≥60 %)")))) -> Plutôt masculine (20-40 %)
... A257: SECTION PLONGEE LIBRE SPLASH | B257: HERBLAY | C257: 95306 | D257: Herblay-sur-Seine | E257: Herblay-sur-Seine | F257: CA Val Parisis | G257: 42 | H257: 84 | I257: 35 | J257: 0 | K257: =G257+H257 -> 126 | L257: =IF(K257>0,G257/K257,"") -> 0.33333333 | M257: =IF(K257=0,"",IF(L257<0.2,"Très masculine (<20 % F)",IF(L257<0.4,"Plutôt masculine (20-40 %)",IF(L257<0.6,"Mixte (40-60 %)","À dominante féminine (≥60 %)")))) -> Plutôt masculine (20-40 %)
A258: SAM D ESPRIT GLISSE | B258: SACY LE GRAND | D258: Hors Val d'Oise | G258: 49 | H258: 33 | I258: 7 | J258: 0 | K258: =G258+H258 -> 82 | L258: =IF(K258>0,G258/K258,"") -> 0.59756098 | M258: =IF(K258=0,"",IF(L258<0.2,"Très masculine (<20 % F)",IF(L258<0.4,"Plutôt masculine (20-40 %)",IF(L258<0.6,"Mixte (40-60 %)","À dominante féminine (≥60 %)")))) -> Mixte (40-60 %)
A259: UNION SPORTIVE CONFLANS | B259: CONFLANS STE HONORINE | D259: Hors Val d'Oise | G259: 33 | H259: 71 | I259: 29 | J259: 4 | K259: =G259+H259 -> 104 | L259: =IF(K259>0,G259/K259,"") -> 0.31730769 | M259: =IF(K259=0,"",IF(L259<0.2,"Très masculine (<20 % F)",IF(L259<0.4,"Plutôt masculine (20-40 %)",IF(L259<0.6,"Mixte (40-60 %)","À dominante féminine (≥60 %)")))) -> Plutôt masculine (20-40 %)
A260: ASS SPORTIVE DU GOLF D ECANCOURT | B260: JOUY LE MOUTIER | C260: 95323 | D260: Jouy-le-Moutier | E260: Cergy (1-2) | F260: CA de Cergy-Pontoise | G260: 18 | H260: 82 | I260: 14 | J260: 1 | K260: =G260+H260 -> 100 | L260: =IF(K260>0,G260/K260,"") -> 0.18 | M260: =IF(K260=0,"",IF(L260<0.2,"Très masculine (<20 % F)",IF(L260<0.4,"Plutôt masculine (20-40 %)",IF(L260<0.6,"Mixte (40-60 %)","À dominante féminine (≥60 %)")))) -> Très masculine (<20 % F)
A261: FOOTBALL CLUB DE JOUY LE MOUTIER | B261: JOUY LE MOUTIER | C261: 95323 | D261: Jouy-le-Moutier | E261: Cergy (1-2) | F261: CA de Cergy-Pontoise | G261: 20 | H261: 732 | I261: 54 | J261: 5 | K261: =G261+H261 -> 752 | L261: =IF(K261>0,G261/K261,"") -> 0.026595745 | M261: =IF(K261=0,"",IF(L261<0.2,"Très masculine (<20 % F)",IF(L261<0.4,"Plutôt masculine (20-40 %)",IF(L261<0.6,"Mixte (40-60 %)","À dominante féminine (≥60 %)")))) -> Très masculine (<20 % F)
A262: FOUS DE LA RAQUETTE DE JOUY LE MOUTIER | B262: JOUY LE MOUTIER | C262: 95323 | D262: Jouy-le-Moutier | E262: Cergy (1-2) | F262: CA de Cergy-Pontoise | G262: 56 | H262: 96 | I262: 15 | J262: 1 | K262: =G262+H262 -> 152 | L262: =IF(K262>0,G262/K262,"") -> 0.36842105 | M262: =IF(K262=0,"",IF(L262<0.2,"Très masculine (<20 % F)",IF(L262<0.4,"Plutôt masculine (20-40 %)",IF(L262<0.6,"Mixte (40-60 %)","À dominante féminine (≥60 %)")))) -> Plutôt masculine (20-40 %)
A263: GROUPE ESCALADE RANDONNEE DE CERGY PONTOISE | B263: JOUY LE MOUTIER | C263: 95323 | D263: Jouy-le-Moutier | E263: Cergy (1-2) | F263: CA de Cergy-Pontoise | G263: 102 | H263: 126 | I263: 13 | J263: 0 | K263: =G263+H263 -> 228 | L263: =IF(K263>0,G263/K263,"") -> 0.44736842 | M263: =IF(K263=0,"",IF(L263<0.2,"Très masculine (<20 % F)",IF(L263<0.4,"Plutôt masculine (20-40 %)",IF(L263<0.6,"Mixte (40-60 %)","À dominante féminine (≥60 %)")))) -> Mixte (40-60 %)
A264: JOUY LE MOUTIER ELITE KARATE | B264: JOUY LE MOUTIER | C264: 95323 | D264: Jouy-le-Moutier | E264: Cergy (1-2) | F264: CA de Cergy-Pontoise | G264: 22 | H264: 38 | I264: 8 | J264: 0 | K264: =G264+H264 -> 60 | L264: =IF(K264>0,G264/K264,"") -> 0.36666667 | M264: =IF(K264=0,"",IF(L264<0.2,"Très masculine (<20 % F)",IF(L264<0.4,"Plutôt masculine (20-40 %)",IF(L264<0.6,"Mixte (40-60 %)","À dominante féminine (≥60 %)")))) -> Plutôt masculine (20-40 %)
A265: JUDO JU JITSU JOUY LE MOUTIER | B265: JOUY LE MOUTIER | C265: 95323 | D265: Jouy-le-Moutier | E265: Cergy (1-2) | F265: CA de Cergy-Pontoise | G265: 48 | H265: 56 | I265: 3 | J265: 0 | K265: =G265+H265 -> 104 | L265: =IF(K265>0,G265/K265,"") -> 0.46153846 | M265: =IF(K265=0,"",IF(L265<0.2,"Très masculine (<20 % F)",IF(L265<0.4,"Plutôt masculine (20-40 %)",IF(L265<0.6,"Mixte (40-60 %)","À dominante féminine (≥60 %)")))) -> Mixte (40-60 %)
A266: KODIAK 95 | B266: JOUY LE MOUTIER | C266: 95323 | D266: Jouy-le-Moutier | E266: Cergy (1-2) | F266: CA de Cergy-Pontoise | G266: 91 | H266: 83 | I266: 6 | J266: 1 | K266: =G266+H266 -> 174 | L266: =IF(K266>0,G266/K266,"") -> 0.52298851 | M266: =IF(K266=0,"",IF(L266<0.2,"Très masculine (<20 % F)",IF(L266<0.4,"Plutôt masculine (20-40 %)",IF(L266<0.6,"Mixte (40-60 %)","À dominante féminine (≥60 %)")))) -> Mixte (40-60 %)
A267: LA BOULE JOCASSIENNE CERGY | B267: JOUY LE MOUTIER | C267: 95323 | D267: Jouy-le-Moutier | E267: Cergy (1-2) | F267: CA de Cergy-Pontoise | G267: 6 | H267: 47 | I267: 30 | J267: 0 | K267: =G267+H267 -> 53 | L267: =IF(K267>0,G267/K267,"") -> 0.11320755 | M267: =IF(K267=0,"",IF(L267<0.2,"Très masculine (<20 % F)",IF(L267<0.4,"Plutôt masculine (20-40 %)",IF(L267<0.6,"Mixte (40-60 %)","À dominante féminine (≥60 %)")))) -> Très masculine (<20 % F)
A268: LA GODASSE JOCASSIENNE | B268: JOUY LE MOUTIER | C268: 95323 | D268: Jouy-le-Moutier | E268: Cergy (1-2) | F268: CA de Cergy-Pontoise | G268: 47 | H268: 37 | I268: 14 | J268: 0 | K268: =G268+H268 -> 84 | L268: =IF(K268>0,G268/K268,"") -> 0.55952381 | M268: =IF(K268=0,"",IF(L268<0.2,"Très masculine (<20 % F)",IF(L268<0.4,"Plutôt masculine (20-40 %)",IF(L268<0.6,"Mixte (40-60 %)","À dominante féminine (≥60 %)")))) -> Mixte (40-60 %)
A269: MOTO TEAM 95 | B269: JOUY LE MOUTIER | C269: 95323 | D269: Jouy-le-Moutier | E269: Cergy (1-2) | F269: CA de Cergy-Pontoise | G269: 7 | H269: 224 | I269: 8 | J269: 0 | K269: =G269+H269 -> 231 | L269: =IF(K269>0,G269/K269,"") -> 0.03030303 | M269: =IF(K269=0,"",IF(L269<0.2,"Très masculine (<20 % F)",IF(L269<0.4,"Plutôt masculine (20-40 %)",IF(L269<0.6,"Mixte (40-60 %)","À dominante féminine (≥60 %)")))) -> Très masculine (<20 % F)
A270: OLYMPIC CLUB DE JOUY LE MOUTIER | B270: JOUY LE MOUTIER | C270: 95323 | D270: Jouy-le-Moutier | E270: Cergy (1-2) | F270: CA de Cergy-Pontoise | G270: 269 | H270: 143 | I270: 9 | J270: 16 | K270: =G270+H270 -> 412 | L270: =IF(K270>0,G270/K270,"") -> 0.65291262 | M270: =IF(K270=0,"",IF(L270<0.2,"Très masculine (<20 % F)",IF(L270<0.4,"Plutôt masculine (20-40 %)",IF(L270<0.6,"Mixte (40-60 %)","À dominante féminine (≥60 %)")))) -> À dominante féminine (≥60 %)
A271: PALIERS 95 PLONGEE SOUS MARINE | B271: JOUY LE MOUTIER | C271: 95323 | D271: Jouy-le-Moutier | E271: Cergy (1-2) | F271: CA de Cergy-Pontoise | G271: 16 | H271: 36 | I271: 11 | J271: 0 | K271: =G271+H271 -> 52 | L271: =IF(K271>0,G271/K271,"") -> 0.30769231 | M271: =IF(K271=0,"",IF(L271<0.2,"Très masculine (<20 % F)",IF(L271<0.4,"Plutôt masculine (20-40 %)",IF(L271<0.6,"Mixte (40-60 %)","À dominante féminine (≥60 %)")))) -> Plutôt masculine (20-40 %)
... A557: UNION SPORTIVE EZANVILLE ECOUEN | B557: EZANVILLE | C557: 95229 | D557: Ézanville | E557: Fosses | F557: CA Plaine Vallée | G557: 627 | H557: 1384 | I557: 280 | J557: 10 | K557: =G557+H557 -> 2011 | L557: =IF(K557>0,G557/K557,"") -> 0.31178518 | M557: =IF(K557=0,"",IF(L557<0.2,"Très masculine (<20 % F)",IF(L557<0.4,"Plutôt masculine (20-40 %)",IF(L557<0.6,"Mixte (40-60 %)","À dominante féminine (≥60 %)")))) -> Plutôt masculine (20-40 %)

Sheet Evolution
A1: Évolution 2019-2025 des associations civiles aidées (Val d'Oise)
A2: Rupture de mesure en 2024 : licencié·es jusqu'en 2023, adhérent·es ensuite. Totaux par formule sur l'onglet Communes.
A4: Année | B4: Associations civiles | C4: Licencié·es / adhérent·es | D4: Mesure | E4: Adhérentes F | F4: Part F
A5: 2019 | B5: =SUM(Communes!AE5:AE187) -> 542 | C5: =SUM(Communes!AJ5:AJ187) -> 134103 | D5: licencié·es | E5: n.d.
A6: 2020 | B6: =SUM(Communes!AF5:AF187) -> 574 | C6: =SUM(Communes!AK5:AK187) -> 143678 | D6: licencié·es | E6: n.d.
A7: 2021 | B7: =SUM(Communes!AG5:AG187) -> 571 | C7: =SUM(Communes!AL5:AL187) -> 131605 | D7: licencié·es | E7: n.d.
A8: 2022 | B8: =SUM(Communes!AH5:AH187) -> 552 | C8: =SUM(Communes!AM5:AM187) -> 122840 | D8: licencié·es | E8: n.d.
A9: 2023 | B9: =SUM(Communes!AI5:AI187) -> 553 | C9: =SUM(Communes!AN5:AN187) -> 135863 | D9: licencié·es | E9: n.d.
A10: 2024 | B10: =SUM(Communes!O5:O187) -> 569 | C10: =SUM(Communes!AO5:AO187) -> 158852 | D10: adhérent·es F+H | E10: =SUM(Communes!P5:P187) -> 68120 | F10: =E10/C10 -> 0.42882683
A11: 2025 | B11: =SUM(Communes!H5:H187) -> 551 | C11: =SUM(Communes!AP5:AP187) -> 159975 | D11: adhérent·es F+H | E11: =SUM(Communes!I5:I187) -> 68623 | F11: =E11/C11 -> 0.42896078
A13: n.d. : pas de ventilation F/H fiable avant 2024 dans ce fichier.

Sheet Territoires_2019_2025
A1: Associations civiles aidées par territoire, 2019 à 2025
A2: Tous sexes confondus (pas de répartition F/H avant 2024). « Panel » = les 336 associations présentes les 7 années, pour suivre les effectifs sans l'effet des entrées et sorties de la liste. Volume = licencié·es jusqu'en 2023, adhérent·es ensuite.
A4: Par canton
A5: Canton | B5: Asso. 2019 | C5: Asso. 2020 | D5: Asso. 2021 | E5: Asso. 2022 | F5: Asso. 2023 | G5: Asso. 2024 | H5: Asso. 2025 | I5: Volume 2019 | J5: Volume 2020 | K5: Volume 2021 | L5: Volume 2022 | M5: Volume 2023 | N5: Volume 2024 | O5: Volume 2025 | P5: Panel 2019 | Q5: Panel 2020 | R5: Panel 2021 | S5: Panel 2022 | T5: Panel 2023 | U5: Panel 2024 | V5: Panel 2025 | W5: Évol. asso. 2019→2025 | X5: Évol. panel 2019→2022 | Y5: Évol. panel 2019→2025
A6: Argenteuil (1-2-3) | B6: 35 | C6: 40 | D6: 38 | E6: 36 | F6: 34 | G6: 33 | H6: 37 | I6: 12104 | J6: 13474 | K6: 12159 | L6: 10325 | M6: 10715 | N6: 12042 | O6: 14201 | P6: 11091 | Q6: 10799 | R6: 9612 | S6: 8394 | T6: 9496 | U6: 10686 | V6: 10843 | W6: =H6-B6 -> 2 | X6: =IF(P6>0,S6/P6-1,"") -> -0.24317014 | Y6: =IF(P6>0,V6/P6-1,"") -> -0.022360472
A7: Cergy (1-2) | B7: 56 | C7: 62 | D7: 59 | E7: 60 | F7: 58 | G7: 62 | H7: 59 | I7: 10575 | J7: 11173 | K7: 10256 | L7: 10592 | M7: 11871 | N7: 15784 | O7: 16668 | P7: 7414 | Q7: 7583 | R7: 6870 | S7: 6741 | T7: 7865 | U7: 10292 | V7: 11456 | W7: =H7-B7 -> 3 | X7: =IF(P7>0,S7/P7-1,"") -> -0.090774211 | Y7: =IF(P7>0,V7/P7-1,"") -> 0.54518479
A8: Deuil-la-Barre | B8: 22 | C8: 21 | D8: 21 | E8: 18 | F8: 17 | G8: 18 | H8: 14 | I8: 6928 | J8: 6664 | K8: 6225 | L8: 5732 | M8: 5844 | N8: 6717 | O8: 5773 | P8: 4127 | Q8: 4140 | R8: 3942 | S8: 4144 | T8: 4694 | U8: 5635 | V8: 5750 | W8: =H8-B8 -> -8 | X8: =IF(P8>0,S8/P8-1,"") -> 0.0041192149 | Y8: =IF(P8>0,V8/P8-1,"") -> 0.39326387
